Workbook
Name feuille_list: INDIRECT([2]param!$F$22)
Name NEWNOK__: '[3]SQA Genba Check'!$AK$14:$AK$15
Name NEWNOK__: '[4]Genba Check'!$AN$14:$AN$15
Name NEWNOK__: '[4]Genba Check'!$AN$14:$AN$15
Name NEWNOK__: 'SQA Genba Check'!$AK$14:$AK$15
Name NEWOK__: '[3]SQA Genba Check'!$AK$13:$AK$14
Name NEWOK__: '[4]Genba Check'!$AN$13:$AN$14
Name NEWOK__: '[4]Genba Check'!$AN$13:$AN$14
Name NEWOK__: 'SQA Genba Check'!$AK$13:$AK$14
Name TB: IF('SQA Genba Check'!$J$12="OK",'SQA Genba Check'!NEWOK,'SQA Genba Check'!NEWNOK)
Name TB__: IF('[3]SQA Genba Check'!$J$12="OK",'Process Flow (2)'!NEWOK__,'Process Flow (2)'!NEWNOK__)
Name TB__: IF('[4]Genba Check'!$L$12="OK",Revision!NEWOK__,Revision!NEWNOK__)
Name TB__: IF('[4]Genba Check'!$L$12="OK",'StEDE3 Matrix'!NEWOK__,'StEDE3 Matrix'!NEWNOK__)
Name TB__: IF('SQA Genba Check'!$J$12="OK",NEWOK__,NEWNOK__)
Name TC: IF('SQA Genba Check'!$K$12="OK",'SQA Genba Check'!NEWOK,'SQA Genba Check'!NEWNOK)
Name TC__: IF('[3]SQA Genba Check'!$K$12="OK",'Process Flow (2)'!NEWOK__,'Process Flow (2)'!NEWNOK__)
Name TC__: IF('[4]Genba Check'!$M$12="OK",Revision!NEWOK__,Revision!NEWNOK__)
Name TC__: IF('[4]Genba Check'!$M$12="OK",'StEDE3 Matrix'!NEWOK__,'StEDE3 Matrix'!NEWNOK__)
Name TC__: IF('SQA Genba Check'!$K$12="OK",NEWOK__,NEWNOK__)
Name TD: IF('SQA Genba Check'!$J$14="OK",'SQA Genba Check'!NEWOK,'SQA Genba Check'!NEWNOK)
Name TD__: IF('[3]SQA Genba Check'!$J$14="OK",'Process Flow (2)'!NEWOK__,'Process Flow (2)'!NEWNOK__)
Name TD__: IF('[4]Genba Check'!$L$14="OK",Revision!NEWOK__,Revision!NEWNOK__)
Name TD__: IF('[4]Genba Check'!$L$14="OK",'StEDE3 Matrix'!NEWOK__,'StEDE3 Matrix'!NEWNOK__)
Name TD__: IF('SQA Genba Check'!$J$14="OK",NEWOK__,NEWNOK__)
Name TE: IF('SQA Genba Check'!$K$14="OK",'SQA Genba Check'!NEWOK,'SQA Genba Check'!NEWNOK)
Name TE__: IF('[3]SQA Genba Check'!$K$14="OK",'Process Flow (2)'!NEWOK__,'Process Flow (2)'!NEWNOK__)
Name TE__: IF('[4]Genba Check'!$M$14="OK",Revision!NEWOK__,Revision!NEWNOK__)
Name TE__: IF('[4]Genba Check'!$M$14="OK",'StEDE3 Matrix'!NEWOK__,'StEDE3 Matrix'!NEWNOK__)
Name TE__: IF('SQA Genba Check'!$K$14="OK",NEWOK__,NEWNOK__)
Name TF: IF('SQA Genba Check'!$J$16="OK",'SQA Genba Check'!NEWOK,'SQA Genba Check'!NEWNOK)
Name TF__: IF('[3]SQA Genba Check'!$J$16="OK",'Process Flow (2)'!NEWOK__,'Process Flow (2)'!NEWNOK__)
Name TF__: IF('[4]Genba Check'!$L$16="OK",Revision!NEWOK__,Revision!NEWNOK__)
Name TF__: IF('[4]Genba Check'!$L$16="OK",'StEDE3 Matrix'!NEWOK__,'StEDE3 Matrix'!NEWNOK__)
Name TF__: IF('SQA Genba Check'!$J$16="OK",NEWOK__,NEWNOK__)
Name TG: IF('SQA Genba Check'!$K$16="OK",'SQA Genba Check'!NEWOK,'SQA Genba Check'!NEWNOK)
Name TG__: IF('[3]SQA Genba Check'!$K$16="OK",'Process Flow (2)'!NEWOK__,'Process Flow (2)'!NEWNOK__)
Name TG__: IF('[4]Genba Check'!$M$16="OK",Revision!NEWOK__,Revision!NEWNOK__)
Name TG__: IF('[4]Genba Check'!$M$16="OK",'StEDE3 Matrix'!NEWOK__,'StEDE3 Matrix'!NEWNOK__)
Name TG__: IF('SQA Genba Check'!$K$16="OK",NEWOK__,NEWNOK__)
Name TH: IF('SQA Genba Check'!$L$12="OK",'SQA Genba Check'!NEWOK,'SQA Genba Check'!NEWNOK)
Name TH__: IF('[3]SQA Genba Check'!$L$12="OK",'Process Flow (2)'!NEWOK__,'Process Flow (2)'!NEWNOK__)
Name TH__: IF('[4]Genba Check'!$N$12="OK",Revision!NEWOK__,Revision!NEWNOK__)
Name TH__: IF('[4]Genba Check'!$N$12="OK",'StEDE3 Matrix'!NEWOK__,'StEDE3 Matrix'!NEWNOK__)
Name TH__: IF('SQA Genba Check'!$L$12="OK",NEWOK__,NEWNOK__)
Name TI: IF('SQA Genba Check'!$L$14="OK",'SQA Genba Check'!NEWOK,'SQA Genba Check'!NEWNOK)
Name TI__: IF('[3]SQA Genba Check'!$L$14="OK",'Process Flow (2)'!NEWOK__,'Process Flow (2)'!NEWNOK__)
Name TI__: IF('[4]Genba Check'!$N$14="OK",Revision!NEWOK__,Revision!NEWNOK__)
Name TI__: IF('[4]Genba Check'!$N$14="OK",'StEDE3 Matrix'!NEWOK__,'StEDE3 Matrix'!NEWNOK__)
Name TI__: IF('SQA Genba Check'!$L$14="OK",NEWOK__,NEWNOK__)
Name TJ: IF('SQA Genba Check'!$L$16="OK",'SQA Genba Check'!NEWOK,'SQA Genba Check'!NEWNOK)
Name TJ__: IF('[3]SQA Genba Check'!$L$16="OK",'Process Flow (2)'!NEWOK__,'Process Flow (2)'!NEWNOK__)
Name TJ__: IF('[4]Genba Check'!$N$16="OK",Revision!NEWOK__,Revision!NEWNOK__)
Name TJ__: IF('[4]Genba Check'!$N$16="OK",'StEDE3 Matrix'!NEWOK__,'StEDE3 Matrix'!NEWNOK__)
Name TJ__: IF('SQA Genba Check'!$L$16="OK",NEWOK__,NEWNOK__)
Name TK__: IF('[3]SQA Genba Check'!$I$12="OK",'Process Flow (2)'!NEWOK__,'Process Flow (2)'!NEWNOK__)
Name TK__: IF('[4]Genba Check'!$K$12="OK",Revision!NEWOK__,Revision!NEWNOK__)
Name TK__: IF('[4]Genba Check'!$K$12="OK",'StEDE3 Matrix'!NEWOK__,'StEDE3 Matrix'!NEWNOK__)
Name TK__: IF('SQA Genba Check'!$I$12="OK",NEWOK__,NEWNOK__)
Name TL: IF('SQA Genba Check'!$I$14="OK",'SQA Genba Check'!NEWOK,'SQA Genba Check'!NEWNOK)
Name TL__: IF('[3]SQA Genba Check'!$I$14="OK",'Process Flow (2)'!NEWOK__,'Process Flow (2)'!NEWNOK__)

Sheet Comments on content expectation
A1: Language/Idioma/Langue/Lingua/Język/语言...etc:
B3: =IFERROR(__xludf.DUMMYFUNCTION("IMPORTRANGE(""https://docs.google.com/spreadsheets/d/1LUmYcQDWNJrUScJfWrqXWxJ7uWSU668YPR7jSkYjsPo/edit#gid=477872199"",""PDCA/FTA comments!B1:AC"")"),"Content expectations") -> Content expectations | C3: -attentes de contenu") | D3: -Expectativas de Conteúdo") | E3: -expectativas de contenido") | F3: -内容预期") | G3: -Obsah") | H3: -Inhalt Erwartungen") | I3: -Tartalmi elvárások") | J3: -harapan konten") | K3: -Spiegazione del contenuto") | L3: -内容に関する期待値") | M3: -요구 내용") | N3: -oczekiwania treści") | O3: -așteptările de conținut") | P3: -Ожидания по содержанию") | Q3: -ความคาดหวังของเนื้อหา") | R3: -İçerik beklentiler")
B4: -English") | C4: -Français (Googletranslate)") | D4: -PORTUGUÊS") | E4: -Spanish (Googletranslate)") | F4: -Chinese Simplified - Translated ") | G4: -Czech") | H4: -German (Googletranslate)") | I4: -Hungarian (Googletranslate)") | J4: -Indonesian (Googletranslate)") | K4: -Italian - Completed") | L4: -Japanese - Completed") | M4: -Korean - Completed") | N4: -Polish (Googletranslate)") | O4: -Romanian (Googletranslate)") | P4: -Russian ") | Q4: -Thai (Googletranslate)") | R4: -Turkish (Googletranslate)")
B5: -Quick Response PDCA") | C5: -Quick Response PDCA") | D5: -Resposta Rápida PDCA") | E5: -Respuesta rápida PDCA") | F5: -快速响应PDCA") | G5: -Quick Response PDCA") | H5: -Quick Response PDCA") | I5: -Gyors válasz PDCA") | J5: -Quick Response PDCA") | K5: -Quick Response PDCA") | L5: -クイックレスポンスPDCA") | M5: -Quick Response PDCA") | N5: -Szybka reakcja PDCA") | O5: -Quick Response PDCA") | P5: -Быстрая реакция PDCA") | Q5: -ตอบสนองอย่างรวดเร็ว PDCA") | R5: -Hızlı Yanıt PUKÖ")
A6: [1] | B6: Customer / contact name Enter the customer affected and the contact name at the customer with his phone number and /or his E mail") | C6: -Client / Nom de contact Entrez le client affecté et le nom du contact chez le client avec son numéro de téléphone et / ou son e-mail") | D6: -Cliente / Nome do contato Insira o cliente afetado e o nome de contato do cliente com seu número de telefone e / ou seu e-mail") | E6: -Nombre del cliente / contacto Introduzca el cliente afectado y el nombre del contacto al cliente con su número de teléfono y / o su mail Correo") | F6: -客户/联系人姓名 输入影响到的客户和对应联系人姓名及他们的电话号码和/或电子信箱。") | G6: -Zákazník / jméno kontaktní osoby Vstoupit zákazníka postiženého a jméno kontaktní osoby u zákazníka se svým telefonním číslem a / nebo jeho E mailem") | H6: -Kunden- / Kontaktnamen Geben Sie die betroffenen Kunden und die Kontaktnamen beim Kunden mit seiner Telefonnummer und / oder seiner E Mail an") | I6: -Vevő / kapcsolattartó neve Írja be az ügyfél az érintett és a kapcsolattartó nevét az ügyfél a telefonszámát és / vagy a E-mail") | J6: -Pelanggan / nama kontak Masukkan pelanggan yang terkena dampak dan nama kontak di pelanggan dengan nomor telepon dan / atau surat E-nya") | K6: -Cliente / nome del contatto Inserisci il cliente interessato e il nome del contatto presso il cliente con il suo numero di telefono e / o il suo E mail") | L6: -顧客/連絡先名 影響を受けた顧客ならびに、その電話番号および/またはEメールアドレスを入力") | M6: -고객 / 연락처 이름 고객 이름, 연락 가능한 전화번호 또는 이메일 주소를 입력") | N6: -Klient / nazwisko osoby kontaktowej Wprowadź klientowi dotyczy i nazwę kontaktu u klienta z jego numer telefonu i / lub jego poczty E") | O6: -Clienți / Numele persoanei de contact Introduceți clientul afectat și numele de contact de la client cu numărul său de telefon și / sau e-mail lui E") | P6: -Наименование потребителя / контактное лицо Укажите наименование потребителя, у которого случилась проблема, и имя контактного лица у потребителя с его номером телефона и/или электронной почтой ") | Q6: -ลูกค้า / ชื่อผู้ติดต่อ ใส่ชื่อลูกค้าได้รับผลกระทบและชื่อผู้ติดต่อของลูกค้าพร้อมกับหมายเลขโทรศัพท์ของเขาและ / หรืออีเมล์ของเขา") | R6: -Müşteri / kişi adı onun telefon numarası ve / veya onun e posta ile müşteriye de müşteri etkilenen ve kişi adını girin")
A7: [2] | B7: Product (Designation + Ref) VALEO Indicate the designation and the Valeo part number of the concerned part") | C7: -Produit (Désignation + Ref) VALEO Indiquer la désignation et le numéro de référence Valeo de la partie concernée") | D7: -Produto (Designação + Ref) VALEO Indique a designação e o número da peça Valeo da peça em questão") | E7: -Producto (Designación + Ref) VALEO Indicar la designación y el número de pieza Valeo de la parte en cuestión") | F7: -法雷奥产品（名称+零件号） 指出所涉及到的零件,写清零件名称和法雷奥零件号。") | G7: -VALEO Produkt (Název + Reference) Uveďte název a číslo dílu dotčeného Valeo produktu") | H7: -Produkt (Bezeichnung + Ref) VALEO Geben Sie die Bezeichnung und die Valeo-Teilenummer des betreffenden Teils an") | I7: -Termék (kijelölés + Ref) VALEO Jelölje meg a kijelölés és a Valeo cikkszáma az érintett rész") | J7: -Produk (Penunjukan + Ref) VALEO Menunjukkan penunjukan dan Valeo nomor bagian dari bagian yang bersangkutan") | K7: -Prodotto (Denominazione + Ref) VALEO Indicare la denominazione e il numero di riferimento Valeo della parte interessata") | L7: -VALEOにおける製品名（種類+ 使用用途等） 製品種類や製品使用用途、不具合品のVALEO品番を記入") | M7: -발레오 제품 (지정 + 참조) 품명 및 관련 부품의 발레오 부품 번호") | N7: -Produkt (oznaczenie + Ref) VALEO Wskazać oznaczenie i numer katalogowy Valeo z danej części") | O7: -Produs (Denumire + Ref) VALEO Se indică denumirea și numărul Valeo parte a părții în cauză") | P7: -Продукт (обозначение + референс) VALEO Укажите наименование и Valeo номер детали для соответствующей детали") | Q7: -ผลิตภัณฑ์ (ชือผลิตภัณฑ์ + การอ้างอิง) VALEO ระบุชื่อผลิตภัณฑ์และหมายเลขผลิตภัณฑ์วาลีโอ ของชิ้นส่วนที่เกี่ยวข้อง") | R7: -Ürün (Adı + Referans) VALEO atamasını ve ilgili parçanın Valeo parça numarasını belirtiniz")
A8: [3] | B8: Origin Tick the appropriate box(es) according to the type of issue ") | C8: -Origine Cochez la case appropriée (s) en fonction du type d'émission") | D8: -Origem Marque a (s) caixa (s) apropriada (s) de acordo com o tipo de problema") | E8: -Origen Marque la casilla apropiada (es) de acuerdo con el tipo de problema") | F8: -起因 根据问题类型勾选相应的框。") | G8: -Původ Zaškrtněte vhodné možnosti v závislosti na typu problému") | H8: -Ursprung Markieren Sie das (die) entsprechende(n) Feld(er) nach der Art der Ausgabe") | I8: -Eredet Jelölje meg a megfelelő négyzet (ek) szerint a probléma típusát") | J8: -Asal Centang kotak yang sesuai (es) sesuai dengan jenis masalah") | K8: -Origine Barrare le caselle appropriate a seconda del tipo di problema") | L8: -区分 問題の種類に応じて、適切な欄を選択") | M8: -유래 문제의 종류에 따라 해당 박스(들) 선택") | N8: -Pochodzenie Zaznacz pole wyboru odpowiedniego (ES) w zależności od rodzaju emisji") | O8: -Origine Bifați căsuța corespunzătoare (ES) în funcție de tipul de emisiune") | P8: -Происхождение Отметьте соответствующие поля в соответствии с типом проблемы") | Q8: -ที่มา กาเครื่องหมายในช่องที่เหมาะสม ตามประเภทของปัญหา") | R8: -Menşei sorunun türüne göre uygun kutuyu (ler) Tick")
A9: [4] | B9: What happened? - Description of the problem with clear and precise facts as defined by the customer. - Recurrence information - Traceability elements of the defective parts") | C9: -Qu'est-il arrivé? - Description du problème avec des faits clairs et précis, tels que définis par le client. - informations Récurrence - les éléments de traçabilité des pièces défectueuses") | D9: -O que aconteceu? - Descrição do problema com fatos claros e precisos definidos pelo cliente. - Informações de recorrência - Elementos de rastreabilidade das peças defeituosas") | E9: -¿Que pasó? - Descripción del problema con hechos claros y precisos definidos por el cliente. - información de periodicidad - elementos de trazabilidad de las piezas defectuosas") | F9: -发生了什么？ - 用客户定义的清楚、准确的事实来描述问题. - 再发信息 - 缺陷零件的可追溯性信息") | G9: -Co se stalo? - Popis problému s jasnými a přesnými fakty jak je popisuje zákazník. - Informace o opakovaném problému - Způsob dohledatelnosti vadných dílů (označení dohledatelnosti)") | H9: -Was ist passiert? - Beschreibung des Problems mit klaren und genauen Fakten, wie vom Kunden definiert. - Informationen bzgl. Wiederauftreten - Rückverfolgbarkeit Elemente der defekten Teile") | I9: -Mi történt? - A probléma leírása egyértelmű és pontos tények által meghatározott ügyfél. - Az ismétlődés információk - nyomon követhetőség elemei hibás alkatrészek") | J9: -Apa yang terjadi? - Deskripsi masalah dengan fakta-fakta yang jelas dan tepat seperti yang didefinisikan oleh pelanggan. - Informasi Kambuh - elemen Lacak bagian yang rusak") | K9: -Cosa è successo - Descrizione del problema con i fatti chiari e precisi, come definito dal cliente - Informazioni sulla rioccorenza - Tracciabilità dei pezzi difettosi") | L9: -何が起こったか？ - 顧客によって定義された問題事象について明瞭かつ正確な事実に基づいて記述 - 再発情報 - 不具合部品のトレーサビリティ要素") | M9: -어떤 일이 발생하였습니까? - 고객에 의해 정의 된 명확하고 정확한 사실에 의거하여, 문제 설명 - 재발 정보 - 부적합 제품 추적 정보") | N9: -Co się stało? - Opis problemu z jasnych i precyzyjnych faktów określonych przez klienta. - informacja Nawrót - elementy identyfikowalność wadliwych części") | O9: -Ce s-a întâmplat? - Descrierea problemei cu fapte clare și precise, astfel cum sunt definite de către client. - informații Recurența - elemente Trasabilitatea pieselor defecte") | P9: -Что случилось? - описание проблемы с ясными и точными фактами, определенными потребителем - информация о повторении проблемы - прослеживаемость дефектных деталей") | Q9: -อะไร เกิดขึ้น? - รายละเอียดของปัญหาที่เกิดขึ้น กับข้อเท็จจริงที่ชัดเจนและแม่นยำตามที่กำหนดโดยลูกค้า - ข้อมูลการเกิดซ้ำ - องค์ประกอบตรวจสอบย้อนกลับของชิ้นส่วนที่บกพร่องเสียหาย") | R9: -Ne oldu? - müşteri tarafından tanımlanan net ve kesin gerçeklerle Sorunun açıklaması. - Tekrarlama bilgiler - hatalı parçaların izlenebilirlik elemanları")
A10: [5] | B10: Why is it a problem? In this section we need to understand what the impact of the problem is for the assembly site and/or for the final Customer. Those elements must be quantified (data) - What is the Customer effect of the defect ? - Impact on the logist"&"ic management of the part - Impact on the handling of the part - Impact on the assembly of the part - Technical impact in the application - Impact on the product reliability - Impact in term of safety - regulation - How important is the problem?") | C10: -Pourquoi est-il un problème? Dans cette section, nous devons comprendre l'impact du problème est pour le site d'assemblage et / ou pour le client final. Ces éléments doivent être quantifiés (données) - Quel est l'effet client du défaut? - Impact sur la ge"&"stion logistique de la partie - Impact sur la manipulation de la partie - Impact sur l'ensemble de la partie - Impact technique dans l'application - Impact sur la fiabilité du produit - Impact en terme de sécurité - réglementation - Quelle est l'importanc"&"e du problème?") | D10: -Por que isso é um problema? Nesta seção, precisamos entender qual é o impacto do problema para o local de montagem e / ou para o cliente final. Esses elementos devem ser quantificados (dados) - Qual é o efeito do defeito para o cliente? - Impacto na gestã"&"o logística da peça - Impacto no manuseio da peça - Impacto na montagem da peça - Impacto técnico na aplicação - Impacto na confiabilidade do produto - Impacto em termos de segurança - regulamentação - Quão importante é o problema?") | E10: -Por qué es un problema? En esta sección tenemos que entender lo que el impacto del problema es que el sitio de montaje y / o para la final al cliente. Esos elementos deben ser cuantificados (datos) - ¿Cuál es el efecto del cliente del defecto? - Impacto e"&"n la gestión logística de la parte - Impacto en el manejo de la parte - Impacto en el montaje de la parte - impacto técnico en la aplicación - Impacto sobre la fiabilidad del producto - Impacto en términos de seguridad - Reglamento - ¿Qué tan importante e"&"s el problema?") | F10: -为什么是一个问题？ 在这个模块,我们需要明白问题对装配工厂和/或终端使用者所产生的影响, 下面这些要素必须要量化(数据) - 缺陷会对客户产生什么样的影响？ - 对零件物流管理的影响 - 对零件处理的影响 - 对零件装配的影响 - 对应用的技术影响 - 对产品可靠性的影响 - 对安全-法规的影响 - 问题有多严重") | G10: -Proč je to problém? V této částije třeba pochopit, jaké dopady má tento problém v montážním závodě a/nebo pro konečného zákazníka (řidič). Tyto dopady musí být kvantifikovány (data) - Jaký je efekt problému u zákazníka? - Dopad na logisticku výrobku - Dop"&"ad na manipulaci s výrobkem - Dopad na montáž výrobku - Technický dopad v aplikaci výrobku - Dopad na spolehlivost výrobku - Dopad z hlediska bezpečnosti - regulace (S/R) - Jak důležitý je tento problém?") | H10: -Warum ist das ein Problem? In diesem Abschnitt müssen wir verstehen, was die Auswirkungen des Problems für das Produktionswerk und / oder für die Endkunden sind. Diese Elemente müssen quantifiziert (Daten) werden - Was ist die Auswirkung dieses Mangels fü"&"r den Kunden? - Auswirkungen auf das Logistik-Management des Teils - Auswirkungen auf die Handhabung des Teils - Auswirkungen auf die Montage des Teils - Technische Auswirkungen in der Anwendung - Auswirkungen auf die Zuverlässigkeit des Produktes - Auswi"&"rkungen in der Bezeichnung der Sicherheits - Verordnung - Wie wichtig ist das Problem?") | I10: -Miért probléma? Ebben a részben meg kell értenünk, hogy mi milyen hatással van a probléma a szerelés helyszínén és / vagy a végső fogyasztót. Ezeket az elemeket kell számszerűsíteni (adatok) - Mi az Ügyfél hatása a hiba? - hatása a logisztikai menedzsment"&" a rész - gyakorolt ​​hatás kezelése a rész - hatása a szerelvény a rész - Műszaki hatás az alkalmazás - Hatás a termék megbízhatóságát - Ütközés távú biztonság - szabályozás - Mennyire fontos a probléma?") | J10: -Mengapa masalah? Pada bagian ini kita perlu memahami apa dampak dari masalah adalah untuk situs perakitan dan / atau untuk Pelanggan akhir. Unsur-unsur harus diukur (data) - Apa efek Nasabah cacat? - Dampak terhadap manajemen logistik dari bagian - Dampak"&" terhadap penanganan bagian - Dampak pada perakitan bagian - Dampak Teknis dalam aplikasi - Dampak terhadap keandalan produk - Dampak dalam hal keselamatan - regulasi - Seberapa penting masalah?") | K10: -Perché è un problema? In questa sezione bisogna spiegare quale sarà l'impatto del problema per il sito di assemblaggio e / o per il cliente finale. Tali elementi devono essere quantificati (dati) - Quale effetto la non conformità genera sul Cliente? - Imp"&"atto sulla gestione logistica - Impatto sulla movimentazione del prodotto - Impatto sul montaggio del prodotto - impatto tecnico nell'applicazione - Impatto sulla affidabilità del prodotto - Impatto in termini di Sicurezza - Regolamentazione - Quanto è im"&"portante il problema?") | L10: -なぜそれが問題ですか？ このセクションでは、問題の影響が、生産工場および/または最終顧客にどのような影響を及ぼすか理解する必要があります。これらの要素は、数値定量化されなければならない（データ） - 不具合の顧客への影響は何か？ - 物流・生産管理への影響 - 製品・部品取扱い上の影響 - 製品・部品生産上の影響 - 技術的な見地に関する影響 - 製品の信頼性への影響 - 安全性のへの影響 - 規制に係るか？ - 問題はどの程度の重要性か？") | M10: -왜 문제 입니까? 본 내용에서, 우리는 해당문제가 조립 공장 그리고/또는 최종 고객에 어떤 영향을 끼치는지 이해할 필요가 있습니다. 아래 내용은 반드시 정량화되어야 합니다. - 고객에 미치는 영향은 무엇입니까? - 물류관리에 미치는 영향? - 취급에 미치는 영향? - 조립에 미치는 영향? - 응용 프로그램의 기술에 미치는 영향? - 제품 신뢰성에 미치는 영향? - 안전 / 법규에 미치는 영향? - 얼마나 중요한 문제입니까?") | N10: -Dlaczego jest to problem? W tym punkcie musimy zrozumieć jaki wpływ problemu jest na miejscu montażu i / lub dla klienta końcowego. Te elementy muszą być ilościowo (dane) - Jaki jest efekt klienta wady? - Wpływ na logistycznego zarządzania części - Wpływ "&"na obsługę części - Wpływ na montaż części - wpływ techniczny we wniosku - Wpływ na niezawodność produktu - Wpływ w perspektywie bezpieczeństwa - regulacja - Jak ważny jest problem?") | O10: -De ce este o problemă? În această secțiune trebuie să înțelegem ce impactul problemei este locul de asamblare și / sau pentru clientul final. Aceste elemente trebuie să fie cuantificate (date) - Care este efectul de client al defectului? - Impactul asupra"&" managementului logistic al părții - Impactul asupra manipularea părții - Impactul asupra ansamblului părții - Impactul tehnic în cerere - Impactul asupra fiabilității produsului - Impactul în termen de siguranță - Regulamentul - Cât de important este pro"&"blema?") | P10: -Почему это является проблемой? В этом разделе нам нужно понять, какое влияние проблема оказывает на сборочный завод и / или на конечного потребителя. Эти элементы должны быть количественно определены (данные) - Каковы последствия дефекта для потребителя? "&"- Влияние на логистическое управление деталью - Влияние на обращение с деталью - Влияние на сборку детали - Техническое влияние при применении - Влияние на надежность продукта - Влияние с точки зрения безопасности - регулирования - Насколько важна пробл"&"ема? ") | Q10: -ทำไม ถึงเป็นปัญหา? ในส่วนนี้เราต้องเข้าใจสิ่งที่ผลกระทบของปัญหาสำหรับการประกอบที่ไลน์ผลิต และ / หรือสำหรับลูกค้าปลายทาง องค์ประกอบเหล่านั้นจะต้องมีการวัดผล (ข้อมูล) - ผลกระทบต่อลูกค้า จากงานบกพร่องคืออะไร ? - ผลกระทบต่อการจัดการโลจิสติกของชินส่วน - ผลกระ"&"ทบต่อการจัดการของชิ้นส่วน - ผลกระทบต่อการประกอบของชิ้นส่วน - ผลกระทบทางเทคนิคในการใช้งาน - ผลกระทบต่อความน่าเชื่อถือของผลิตภัณฑ์ - ผลกระทบในด้านความปลอดภัย - ข้อกำหนด - ปัญหามีความสำคัญอย่างไร") | R10: -O niçin bir problem olsun ki? Bu bölümde problemin darbe montaj sitenin ve / veya nihai Müşteri için ne olduğunu anlamak gerekir. Bu elementler miktarı gerekir (veri) - defekt Müşteri etkisi nedir? - parçanın lojistik yönetimi konusunda Darbe - parçanın k"&"ullanım ile ilgili Etkisi - parçanın montajı Üzerindeki Etkisi - uygulamada teknik etkisi - Ürün güvenilirliği üzerinde etkisi - emniyet vadede Etkisi - regülasyon - Sorun ne kadar önemli?")
A11: [6] | B11: When detected? The objective is to know exactly when the defect has been detected for the first time for the Customer. - date of the detection of the problem - Exact time, hour, minute - Manufacturing shift In addition of the date of detection, the follow"&"ing data must be added for the warranty issues : - Mileage of the car - Date of the registration of the car - Date of notification of the defect to Valeo") | C11: -Lorsqu'il est détecté? L'objectif est de savoir exactement quand le défaut a été détecté pour la première fois pour le client. - date de la détection du problème - Heure exacte, heure, minute - changement de fabrication En plus de la date de détection, le"&"s données suivantes doivent être ajoutées pour les questions de garantie: - Kilométrage de la voiture - La date de l'enregistrement de la voiture - Date de la notification du défaut de Valeo") | D11: -Quando detectado? O objetivo é saber exatamente quando o defeito foi detectado pela primeira vez para o Cliente. - data da detecção do problema - Hora exata; hora, minuto - Turno de fabricação Além da data de detecção, os seguintes dados devem ser adicion"&"ados para os problemas de garantia: - Quilometragem do carro - Data da matrícula do carro - Data de notificação do defeito à Valeo") | E11: -Cuando se detecta? El objetivo es saber exactamente cuando se ha detectado el defecto por primera vez para el cliente. - fecha de la detección del problema - La hora exacta, hora, minuto - turno de fabricación Además de la fecha de detección, los datos si"&"guientes se deben añadir a los problemas de garantía: - Kilometraje del coche - Fecha del registro del coche - Fecha de notificación del defecto a Valeo") | F11: -什么时候探测到的？ 目的是要确切的知道，客户是何时第一次探测到缺陷的。 - 发现问题的日期 - 准确的时间（小时 / 分钟） - 生产班次 除了发现缺陷的日期之外，对于售后来说下面数据需要被考量到： - 车辆的里程数 - 车辆的注册登记日期 - 法雷奥收到缺陷的日期") | G11: -Kdy byl problém nalezen? Cílem je přesně vědět, kdy byl problém poprvé zákazníkem zjištěn. - datum zjištění problému - přesný čas, hodina, minuta zjištění probému - Výrobní směna Kromě času zjištění problému musí být v případě záruční reklamace přidány ty"&"to údaje: - celkové najete kilometry auta - datum registrace auta do provozu - datum oznámení vady Valeu") | H11: -Wann wurde es erkannt? Ziel ist es, genau zu wissen, wann der Mangel zum ersten Mal für die Kunden festgestellt wurde. - Datum der Erfassung des Problems - Genaue Zeit, Stunde, Minute - Fertigungs-Schicht Zusätzlich zum Zeitpunkt der Erkennung, müssen die"&" folgenden Daten für die Gewährleistungsfragen hinzugefügt werden: - Kilometerstand des Autos - Datum der Eintragung des Autos - Datum der Anzeige des Mangels an Valeo") | I11: -Amikor kimutatható? A cél az, hogy pontosan tudja, mikor a hibát észlelte először az ügyfél számára. - időpontja az észlelési probléma - Pontos idő, óra, perc - Gyártási műszak Ezen kívül az észlelés időpontjától, a következő adatokat ki kell egészíteni a"&" garanciális kérdéseket: - futásteljesítménye az autó - időpontja a regisztrációs az autó - időpontja a hiba bejelentésétől a Valeo") | J11: -Ketika terdeteksi? Tujuannya adalah untuk tahu persis kapan cacat telah terdeteksi untuk pertama kalinya bagi Nasabah. - tanggal deteksi masalah - waktu Exact, jam, menit - Manufaktur pergeseran Selain dari tanggal deteksi, data berikut harus ditambahkan "&"untuk masalah garansi: - Jarak tempuh dari mobil - Tanggal pendaftaran mobil - Tanggal pemberitahuan cacat untuk Valeo") | K11: -Quando è stato rilevato? L'obiettivo è quello di sapere esattamente quando è stato rilevato il difetto per la prima volta da parte del Cliente. - data del rilevamento del problema - orario: ore, minuti - turno di produzione Oltre alla data di rilevamento,"&" i seguenti dati devono essere aggiunti per problemi di garanzia: - Chilometraggio della vettura - Data di immatricolazione della vettura - Data di notifica del difetto a Valeo") | L11: -何時発見されたか？ 目的は、不具合がいつお客様に初めて発見されたかを正確に知ることです。 - 問題検出の日時 - 正確な時間、時間、分 - 製造シフト 発見日付の他に、市場不具合に関しては、以下のデータを追加する必要があります。 - 車の走行距離 - 車の登録の日 - Valeoに対する不具合通知日") | M11: -언제 발견되었습니까? 질문의 목적은 언제 고객으로부터 처음 발견되었는지를 정확히 이해하는 것 입니다. - 문제 발견 일자 - 정확한 시간(시 / 분) - 제조 쉬프트 워런티 문제를 위해 아래 정보를 추가로 인지해야 합니다. - 차량 주행거리 - 차량 등록일자 - 문제 통보 일자") | N11: -Kiedy wykryty? Celem jest, aby wiedzieć dokładnie, kiedy wada została wykryta po raz pierwszy dla klienta. - data wykrycia problemu - Zegar, godzina, minuta - przesunięcie Produkcja Ponadto od dnia wykrycia następujące dane muszą być dodane do spraw gwara"&"ncyjnych: - Przebieg samochodu - Data rejestracji samochodu - data zgłoszenia wady do Valeo") | O11: -Când detectat? Obiectivul este de a ști exact când defectul a fost detectat pentru prima dată pentru client. - data detectarea problemei - timp exact, oră, minut - schimbare de fabricație În plus, de la data de detecție, trebuie adăugate următoarele date "&"pentru problemele de garanție: - kilometrajul mașinii - Data înregistrării mașinii - Data notificării defectului Valeo") | P11: -Когда обнаружено? Цель состоит в том, чтобы точно узнать, когда дефект был обнаружен потребителем впервые . - дата обнаружения проблемы - точное время, час, минута - производственная смена В дополнение к дате обнаружения следующие данные должны быть добав"&"лены для гарантийных проблем: - Пробег автомобиля - Дата регистрации автомобиля - дата уведомления Valeo о дефекте ") | Q11: -เมื่อไหร่ ที่ปัญหาถูกตรวจพบ? วัตถุประสงค์คือเพื่อให้ทราบแน่ชัดว่าเมื่อใดที่งานบกพร่องถูกตรวจพบเป็นครั้งแรกสำหรับลูกค้า - วันที่ปัญหาถูกตรวจพบ - เวลาที่แน่นอน , ชั่วโมง, นาที - กะการผลิต นอกจากวันที่ตรวจพบแล้วต้องเพิ่มข้อมูลต่อไปนี้สำหรับปัญหาการรับประกัน:"&" - ระยะไมล์ของรถ - วันที่ของการลงทะเบียนของรถ - วันที่ของการแจ้งเตือนของงานบกพร่องไปที่วาลีโอ") | R11: -Algılandığında? Amaç kusur Müşteri için ilk kez tespit edildi tam olarak ne zaman bilmektir. - bir sorun tespiti tarihi - Tam zamanlı, saat, dakika - İmalat vardiya algılama tarihi ek olarak, aşağıdaki veri garanti sorunları için eklenmelidir: - Arabanın "&"Kilometre - arabanın tescil tarihi - Valeo'ya için defekt Tebliğ tarihi")
A12: [7] | B12: Who detected (name of operator) To know who has detected the defect is key to have the possibility to ask for more precise data. - Name of the person or his registered number - Function of the person, qualification In addition of the date of detection(the"&" personal who detected), the following data, when available, must be added for the warranty issues : - Garage name - End user name") | C12: -Qui détecté (nom de l'opérateur) Pour savoir qui a détecté le défaut est la clé d'avoir la possibilité de demander des données plus précises. - Nom de la personne ou son numéro d'immatriculation - Fonction de la personne, la qualification En plus de la da"&"te de détection, les données suivantes, lorsqu'elles sont disponibles, il faut ajouter les problèmes de garantie: - Nom de Garage - Fin nom d'utilisateur") | D12: -Quem detectou (nome do operador) Saber quem detectou o defeito é fundamental para poder solicitar dados mais precisos. - Nome da pessoa ou seu número registrado - Função da pessoa, qualificação Além da data de detecção, os seguintes dados, quando disp"&"oníveis, devem ser adicionados para os problemas de garantia: - Nome da garagem - Nome do usuário final") | E12: -Quien detectó (nombre del operador) Para saber quién ha detectado el defecto es la clave para tener la posibilidad de solicitar los datos más precisos. - Nombre de la persona o su número de registro - Función de la persona, calificación Además de la fecha"&" de detección, los datos siguientes, cuando estén disponibles, se deben añadir a los problemas de garantía: - Nombre del garaje - Nombre de usuario final") | F12: -谁探测到的（操作员工的名字）? 知道是谁探测到的缺陷，是可能继续询问到更准确数据的关键。 - 人员的姓名或他的工号 - 人员的职能，资质 除了发现缺陷的人员之外，如果有可能，下面数据必须加入到售后的事故中来： - 4S店名称 - 终端使用者姓名") | G12: -Kdo problém našel? (jméno operátora) Musíme vědět, kdo problém nalezl - to je klíčové, abychom se ho mohli vyptat na další důležité informace a data. - Jméno osoby nebo jeho číslo zaměstnance - Funkce osoby, kvalifikace Kromě osoby která nalezla problém m"&"usí být v případě záruční reklamace přidány tyto údaje: - jméno servisu - jméno koncového uživatele (řidiče)") | H12: -Wer hat es erkannt (Name des Bedieners) Zu wissen, wer den Fehler erkannt hat, ist der Schlüssel, um nach genaueren Daten zu fragen. - Name der Person oder seine Registriernummer - Funktion der Person, Qualifikation Zusätzlich zum Zeitpunkt der Erkennung,"&" die folgenden Daten, wenn vorhanden, müssen für Gewährleistungsfragen hinzugefügt werden: - Name der Werkstatt - Name des Endnutzers ") | I12: -Ki mutatható ki (neve operátor) Ahhoz, hogy tudjuk, ki a hiányosságot kulcsfontosságú a lehetőséget, hogy kérjen pontosabb adatokat. - A személy neve vagy bejegyzett száma - Funkció a személy, végzettség Ezen kívül az észlelés időpontjától, a következő ad"&"atokat, amennyiben azok rendelkezésre kell egészíteni a garanciális ügyek: - Garázs neve - Vége felhasználói név") | J12: -Yang terdeteksi (nama operator) Untuk mengetahui siapa yang telah mendeteksi cacat adalah kunci untuk memiliki kemungkinan untuk meminta data yang lebih tepat. - Nama orang atau nomor yang terdaftar nya - Fungsi dari orang tersebut, kualifikasi Selain dar"&"i tanggal deteksi, data berikut, bila tersedia, harus ditambahkan untuk masalah garansi: - nama Garage - Akhir nama pengguna") | K12: -Chi ha rilevato il problema (nome dell'operatore) Conoscere chi ha rilevato il difetto è indispensabile per avere la possibilità di richiedere dati più precisi. - Nome della persona o suo identificativo - Funzione, qualifica della persona Inoltre, la pers"&"ona che ha rilevato il problema, deve aggiungere i seguenti dati per problemi di garanzia ove disponibili: - Nome officina di riparazione - Nome utente finale") | L12: -誰が発見したか（オペレータの名前） 誰が不具合を発見したか知る事は更なる詳細を知るための重要な手がかりです - 名前、電話番号等 - その人の職種やタイトル発見日時の他、市場不具合に関しては、情報ある場合は、次のデータを加える事が望ましい。 - Dealer詳細 - エンドユーザ名") | M12: -검출자 (이름)? 누가 문제를 발견했는지를 아는 것은 더 정확한 정보를 얻기 위해 필수 사항입니다. - 발견자 이름 / 사번 - 발견자 소속팀 / 자격 발견 일자와 마찬가지로, 워런티 문제 대응을 위해 아래 정보를 추가적으로 인지해야 합니다. - 수리처 - 차량 소유주") | N12: -Który wykryto (nazwa operatora) Aby dowiedzieć się, który wykrył wadę jest kluczem, aby mieć możliwość poproszenia o bardziej precyzyjne dane. - Imię i nazwisko osoby lub jego numer rejestrowy - Funkcja osoby, kwalifikacje Ponadto od dnia wykrycia, następ"&"ujące dane, jeśli są dostępne, należy dodać do spraw gwarancyjnych: - nazwa Garaż - nazwa użytkownika końcowego") | O12: -Cine a detectat (numele operatorului) Pentru a afla cine a detectat defectul este cheia pentru a avea posibilitatea de a solicita date mai precise. - Numele persoanei sau numărul său înregistrat - funcția persoanei, calificarea În plus, de la data detectă"&"rii, următoarele date, atunci când sunt disponibile, trebuie să fie adăugate pentru problemele de garanție: - numele de garaj - Numele utilizatorului final") | P12: -Кто обнаружил (имя оператора) Чтобы узнать, кто обнаружил дефект, необходимо иметь возможность запросить более точные данные. - Имя человека или его регистрирационный номер - должность человека, его/ее квалификация В дополнение к данной информации следую"&"щие данные, если таковые имеются, должны быть добавлены для гарантийных проблем: - название дилерского центра - имя конечного пользователя") | Q12: -ใคร คือผู้ตรวจพบ (ชื่อพนักงาน) เพื่อทราบว่าใครเป็นผู้ตรวจพบข้อบกพร่องซึ่งเป็นกุญแจสำคัญที่มีความเป็นไปได้ที่จะขอข้อมูลที่แม่นยำมากขึ้น - ชื่อบุคคล หรือรหัสพนักงาน ของผู้ตรวจพบ - แผนก , หน่วยงาน ของผู้ตรวจพบ นอกจากบุคคลผู้ตรวจพบแล้วจะต้องเพิ่มข้อมูลต่อไปนี"&"้สำหรับปัญหาการรับประกัน: - ชื่ออู่ซ่อมรถ - ชื่อลูกค้าผู้งานใช้ปลายทาง") | R12: -tespit edilen (operatörün ismi) kusur tespit etti kim olduğunu bilmek daha kesin veriler isteyecek olanağına sahip anahtarıdır. - kişinin adı veya onun kayıtlı numara - kişinin İşlevi, yeterlilik algılama tarihi ek olarak, aşağıdaki bilgileri mevcut, gara"&"nti sorunları için eklenmelidir: - Garaj adı - Son kullanıcı adı")
A13: [8] | B13: Where detected? - Plant name or Garage name - Assembly line name - Step of the process of assembly including step before and after (reception, warehouse, subassembly, assembly, test, warehouse, logistic, garage, field…)") | C13: -En cas de détection? - Nom de la plante ou le nom Garage - le nom de la ligne Assemblée - l'étape du processus d'assemblage comprenant l'étape avant et après (réception, entrepôt, sous-ensemble, l'assemblage, test, entrepôt, logistique, garage, terrain .."&".)") | D13: -Onde detectado? - Nome da planta ou nome da concessionária - Nome da linha de montagem - Etapa do processo de montagem incluindo a etapa antes e depois (recepção, armazém, submontagem, montagem, teste, armazém, logística, concessionária, campo ...)") | E13: -Cuando se detecta? - Nombre de la planta o el nombre de Garaje - Nombre de la línea de ensamble - Paso del proceso de ensamblaje incluyendo paso antes y después (recepción, almacén, subconjunto, conjunto, prueba, almacén, logística, garaje, campo ...)") | F13: -在哪里探测到的？ - 工厂或4S店名称 - 装配线名称 - 装配工艺的步骤，包括之前和之后（收货区，仓库，下级装配，装配，测试，仓库，物流，4S店，市场…）""") | G13: -Kde byl problém nalezen? - název výrobního závodu nebo servisu - název montážní linky - krok procesu montáže včetně předchozího a následujícího montážního kroku (příjem, sklad, předmontáž, montáž, testy, sklad, logistická platforma, servis, pole...)") | H13: -Wo erkannt? - Name des Produktionswerkes oder der Werkstatt - Name der Montagelinie - Prozessschritt des Zusammenbaus einschließlich der Stufe davor und danach (Empfang, Lager, Unterbaugruppe, Test, Lager, Logistik, Garage, FIELD ...)") | I13: -Amennyiben észlel? - Növényi nevét vagy garázs neve - Futószalagon neve - lépés a folyamat a szerelvény, beleértve a lépés előtt és után (vétel, raktár, alegység, szerkezeti egység, vizsgálat, raktár, logisztikai, garázs, mező ...)") | J13: -Dimana terdeteksi? - Nama Tanaman atau nama Garage - Nama jalur Majelis - Langkah dari proses perakitan termasuk langkah sebelum dan sesudah (penerimaan, gudang, subassembly, perakitan, pengujian, gudang, logistik, garasi, bidang ...)") | K13: -Dove è stato rilevato? - Nome dello stabilimento o dell'Officina di riparazione - Nome della linea di assemblaggio - Fase di assemblaggio con indicazione dello step di processo prima e dopo (accettazione arrivi, magazzino, semilavorato, test, logistica, o"&"fficina di riparazione, garanzia dal campo ...)") | L13: -どこで発見されましたか？ - 工場名あるいはDealer名 - 組立ラインの名前 - 生産ラインのどの工程での発見か。その前後の工程情報も含めて（受入、倉庫、サブアセンブリ、アセンブリ、テスト、倉庫、ロジスティック、ガレージ、フィールド...）") | M13: -발견 장소? - 공장명 또는 수리처 - 발견 공정명(공정 전 / 후 명 포함) - 입고, 창고, 부분조립, 조립, 시험, 창고, 물류, 필드...)") | N13: -Gdzie wykryto? - nazwa roślin lub nazwa Garaż - nazwa Linia montażowa - Etap procesu montażu włącznie krok przed i po (recepcja, magazyn, podzespół, zespół, testy, magazyn, logistyka, garaż, boisko ...)") | O13: -În cazul în care detectat? - numele plantelor sau numele de garaj - numele liniei de asamblare - Etapa procesului de asamblare, inclusiv pas înainte și după (recepție, depozit, subansamblu, ansamblu, testare, depozit, logistica, garaj, teren ...)") | P13: -Где обнаружено? - Наименование завода-потребителя или дилера - Наименование сборочной линии - Шаг сборочного процесса, включая стадии до и после (поступление, складское хранение, подсбор, сборка, испытания, транспортировка, дилерский центр, гарантия ...)") | Q13: -ที่ไหน ที่ปัญหาถูกตรวจพบ? - ชื่อโรงงานหรือชื่ออู่ซ่อมรถ - ชื่อไลน์การประกอบ - ขั้นตอนของกระบวนการประกอบรวมทั้งขั้นตอนก่อนและหลัง (การรับชิ้นส่วน, คลังสินค้า, การประกอบย่อย, การประกอบ, การทดสอบ, คลังจัดเก็บสินค้า, โลจิสติกส์, โรงรถ, สนามจอดรถ เป็นต้น)") | R13: -Nerede algılandı? - Bitki adı veya Garaj adı - Montaj hattı adı - Montaj öncesi ve sonrası aşamaları içeren sürecin Adım (resepsiyon, depo, alt montaj, montaj, test, depo, lojistik, garaj, alan ...)")
A14: [9] | B14: How detected? The way and the circumstances the defect has been detected is key to understand why the Valeo process did not detect the defect internally - Operation done to detect the defect - Reference to the work instruction when relevant - Type of tool"&" or machine used to detect the defect - Process parameters including distance, time to detect visually the problem, limits or master samples used - Environmental conditions such as light, temperature, ambient noise…") | C14: -Comment détecter? La manière et les circonstances, le défaut a été détecté est la clé pour comprendre pourquoi le processus Valeo n'a pas détecté le défaut interne - Opération effectuée pour détecter le défaut - Référence à l'instruction de travail le cas"&" échéant - Type d'outil ou d'une machine utilisée pour détecter le défaut - Les paramètres de traitement, y compris la distance, le temps de détecter visuellement le problème, des limites ou des échantillons de base utilisés - Les conditions environnement"&"ales telles que la lumière, la température, le bruit ambiant ...") | D14: -Como detectado? A forma e as circunstâncias em que o defeito foi detectado são fundamentais para entender por que o processo da Valeo não detectou o defeito internamente - Operação realizada para detectar o defeito - Referência à instrução de trabalho qua"&"ndo relevante - Tipo de ferramenta ou máquina/equipamento usada para detectar o defeito - Parâmetros do processo, incluindo distância, tempo para detectar visualmente o problema, limites ou amostras padrões usadas - Condições ambientais, como luz, tempera"&"tura, ruído ambiente ...") | E14: -¿Cómo se detecta? La forma y las circunstancias que ha sido detectado el defecto es la clave para entender por qué el proceso de Valeo no detectó el defecto internamente - Operación hace para detectar el defecto - Referencia a la instrucción de trabajo cu"&"ando sea pertinente - Tipo de herramienta o máquina que se utiliza para detectar el defecto - Los parámetros del proceso, incluyendo distancia, el tiempo de detectar visualmente el problema, límites o muestras maestras utilizan - Las condiciones ambiental"&"es tales como la luz, la temperatura, el ruido ambiental ...") | F14: -如何探测到的？ 了解探测到该缺陷的方式及环境很关键，是为了理解为什么法雷奥的内部生产过程无法探测到该缺陷 - 检查该缺陷的操作已完成 - 当相关时，参考作业指导书 - 用来探测该缺陷的工装或设备 - 工艺参数，包括距离，目视检查所用的时间，极限样件或标准样件的使用 - 环境条件，如光照，温度，环境噪声等...") | G14: -Jak byl problém nalezen? To, jak a za jakých okolností byl problém nalezen je klíčové k pochopení, proč nebyl problém nalezen interně v procesu Valeo - Provedené operace vedoucí k nalezení problému - Číslo pracovní instrukce, pokud je to relevantní - typ "&"nástroje nebo stroje použitého k nalezení problému - Procesní parametry včetně vzdálenosti, času pro detekci vizualizaci problému, použité limity nebo master vzorky - Podmínky okolního prostředí, jako je světlo, teplota, okolní hluk ...") | H14: -Wie festgestellt? Die Art und Weise und die Umstände wie der Fehler erkannt wurde ist der Schlüssel zu verstehen, warum der Valeo-Prozess den Fehler nicht intern erkannt hat - durchgeführte Arbeitsfolge, um den Fehler zu entdecken - Bezugnahme auf die Arb"&"eitsanweisung, wenn relevant - Werkzeugtyp oder verwendete Maschine, um den Defekt zu detektieren - Prozessparameter einschließlich Entfernung, Zeit zur visuellen Erfassung des Problems, verwendete Grenzmuster - Umweltbedingungen wie Licht, Temperatur, Um"&"gebungsgeräusche ...") | I14: -Hogyan észlel? Az út és a körülmények a hiba észlelése kulcsfontosságú megérteni, hogy miért a Valeo folyamat nem észleli a hibát belsőleg - Operation tenni, hogy észleli a hibát - Hivatkozás a munkautasítás amikor releváns - Milyen szerszám vagy gép észl"&"eli a hibát - Az eljárás paraméterei, beleértve távolságot, időt felismerni vizuálisan a probléma, korlátozza vagy mester használt minták - környezeti feltételektől, mint a fény, hőmérséklet, a környezeti zaj ...") | J14: -Bagaimana terdeteksi? Cara dan keadaan cacat telah terdeteksi adalah kunci untuk memahami mengapa proses Valeo tidak mendeteksi cacat internal - Operasi dilakukan untuk mendeteksi cacat - Referensi instruksi kerja bila relevan - Jenis alat atau mesin yang"&" digunakan untuk mendeteksi cacat - Parameter proses termasuk jarak, waktu untuk mendeteksi secara visual masalah, batasan atau sampel induk yang digunakan - Kondisi lingkungan seperti cahaya, suhu, kebisingan ambient ...") | K14: -Come è stato rilevato? Il modo e le circostanze in cui è stato rilevato il difetto sono necessari per comprendere il motivo per cui il processo Valeo non ha rilevato il difetto internamente - Operazione eseguita per rilevare il difetto - Riferimento alle "&"istruzioni di lavoro se pertinenti - Tipo di utensile o macchina utilizzata per rilevare il difetto - Parametri di processo, ad esempio distanza visiva e tempo per rilevare il problema, limiti o campioni primari utilizzati per il confronto - Condizioni am"&"bientali quali luce, temperatura, rumore ...") | L14: -どのように発見されましたか？ 不具合が発見された方法や環境を知ることは何故Valeo社内で発見されなかったのかを知る為の重要な鍵です。 - 不具合検出の為の作業内容 - 必要に応じて作業指示書との比較 - 不具合検出の為の治工具あるいは設備の種類 - 目視による不具合発見の為の距離や時間設定含めた工程パラメータ、リミットサンプルやOK/NGマスターの使用 - 業務環境、照明、室温、ノイズレベル等") | M14: -발견 방법? 문제를 발견한 방법 및 문제 현상에 대한 발견 방법은 왜 발레오 내부에서 문제를 감지 못했는지를 이해하는 중요 단서입니다. - 작동 중 부적합 검출 - 작업 지침서를 통한 검출 - 지그 또는 설비에 의한 검출 - 길이, 시간등 시각적 문제를 검출하는 공정 파라미터, 한계 또는 마스터 샘플에 의한 검출 - 빛, 온도, 주변 잡음과 같은 환경적인 요소에 의한 검출") | N14: -Jak wykrywane? Sposób i okoliczności została wykryta wada jest kluczem do zrozumienia, dlaczego proces Valeo nie wykrył usterkę wewnętrznie - Działanie zrobić, aby wykryć wadę - Odniesienie do instrukcji pracy, gdy istotne - Typ narzędzia lub maszyny stos"&"owane do wykrywania wad - parametry procesu, takich jak odległość, czas potrzebny do wykrycia wzrokowo problem ograniczenia lub próbki wzorcowe stosowane - warunki środowiska, takie jak światło, temperatura, ... hałasu otoczenia") | O14: -Cum a detectat? Modul și circumstanțele a fost detectată defectul este cheia pentru a înțelege de ce procesul Valeo nu a detectat defectul intern - Operația făcut pentru a detecta defectul - Trimitere la instrucțiunile de lucru atunci când sunt relevante "&"- Tipul de unealtă sau mașină folosită pentru a detecta defectul - parametrii de proces, inclusiv la distanță, timp pentru a detecta vizual problema, limite sau mostre de master utilizate - condițiile de mediu, cum ar fi lumina, temperatura, zgomotul ambi"&"ant ...") | P14: -Как обнаружено? Способ и обстоятельства обнаружения дефекта являются ключевыми для понимания того, почему дефект был не обнаружен внутри процесса Valeo - Какие действия были выполнены для обнаружения дефекта - Ссылка на рабочую инструкцию, если это примен"&"имо - Тип инструмента или оборудования, используемого для обнаружения дефекта - Параметры процесса, включая расстояние, время для визуального обнаружения проблемы, пределы или используемые эталонные образцы - Условия окружающей среды, такие как свет, темп"&"ература, окружающий шум… ") | Q14: -อย่างไร ปัญหาถูกตรวจพบได้วิธีใด? วิธีและสถานการณ์ที่ตรวจพบข้อบกพร่องเป็นกุญแจสำคัญในการทำความเข้าใจว่าเหตุใดกระบวนการของวาลีโอ จึงตรวจไม่พบข้อบกพร่องได้ภายในวาลีโอ - ดำเนินการเพื่อตรวจหาข้อบกพร่อง - การอ้างอิงถึงคู่มือการปฏิบัติงานเมื่อมีความเกี่ยวข้อง - "&"ประเภทของเครื่องมือหรือเครื่องจักรที่ถูกใช้ในการตรวจจับข้อบกพร่อง - พารามิเตอร์กระบวนการรวมถึงระยะทางเวลาในการตรวจจับปัญหาที่มองเห็นได้, ลิมิตหรือตัวอย่างต้นแบบที่ใช้ - สภาพแวดล้อม เช่น แสง, อุณหภูมิ, เสียงรบกวนรอบข้าง เป็นต้น") | R14: -Nasıl tespit? yolu ve kusur tespit edildi koşullar Valeo süreci içten kusur tespit etmedi anlamak için anahtar - Çalışma kusur tespit etmek için yapılan - zaman ilgili iş talimatına Referans - araç veya makine tipi kusuru tespit etmek için kullanılan - me"&"safe, görsel sorunu tespit zamanı da dahil olmak üzere işlem parametrelerinin, sınırları veya ana örnekleri kullanılmıştır - Böyle ışık, sıcaklık, ortam gürültüsü gibi çevresel koşullar ...")
A15: [10] | B15: How many bad parts? - Precise how many bad parts have been found defective at the time of detection in the Customer process? - Precise how it costs when appropriate") | C15: -Combien de pièces de mauvais? - précise combien de mauvaises pièces ont été trouvés défectueux au moment de la détection dans le processus client? - précise comment il en coûte le cas échéant") | D15: -Quantas peças ruins? - Precise quantas peças defeituosas foram consideradas defeituosas no momento da detecção no processo do Cliente? - Precis o custa quando apropriado") | E15: -¿Cuántas partes malas? - Preciso cuántas partes mal se han encontrado defectuoso en el momento de la detección en el proceso de atención al cliente? - Preciso cómo cuesta cuando sea apropiado") | F15: -有多少坏件？ - 统计有多少坏件在客户的检测过程中被发现 - 在适当的时候，统计要产生多少成本") | G15: -Kolik špatných dílů nalezeno? - Upřesni, kolik špatných dílů bylo nalezeno v okamžiku detekce problému u zákazníka? - Upřesni jaké jsou náklady (pokud je to vhodné)") | H15: -Wie viele schlechte Teile? - ​​wie viele fehlerhafte Teile sind zum Zeitpunkt der Erfassung im Kundenprozess gefunden worden? - wie hoch sind die Kosten, falls angemessen") | I15: -Hány rossz részek? - Pontos mennyi rossz alkatrészeket találtak időpontjában hibás kimutatási Ügyfél folyamat? - Pontos, hogyan kerül szükség esetén") | J15: -Berapa banyak bagian yang buruk? - Precise berapa banyak bagian yang buruk telah ditemukan cacat pada saat deteksi dalam proses Pelanggan? - Precise bagaimana harganya saat yang tepat") | K15: -Quanti pezzi difettosi? - Precisare quanti pezzi difettosi sono stati trovati nel momento della rilevazione nel processo Cliente - Precisare, ove appropriato, l'impatto economico") | L15: -不良品の数？ - 顧客ラインにて同時に何個不具合品が発見されたかを正確に？ - 不具合に付随するコストはどれくらいか、必要に応じて") | M15: -부적합 수량? - 부적합 발견시 얼마나 많은 수량의 불량이 발견되었는가? - 부적합 제품의 비용") | N15: -Ile części źle? - Precyzyjne ilu złe części zostały znalezione wadliwy w momencie wykrycia w procesie klienta? - Precyzyjny jak to kosztuje w stosownych przypadkach") | O15: -Câte părți rele? - precis cât de multe părți rele au fost găsite defecte la momentul detectării în procesul de Client? - precis modul în care costurile atunci când este cazul") | P15: -Сколько плохих деталей обнаружено? - Уточните, сколько плохих деталей было обнаружено потребителем в его процессе? - Уточните стоимость плохих деталей, когда это применимо") | Q15: -เท่าไหร่ จำนวนของเสียกี่ชิ้น? - ระบุจำนวนชิ้นส่วนเสียที่พบข้อบกพร่อง ณ เวลาที่ตรวจพบในกระบวนการของลูกค้าอย่างแม่นยำหรือไม่? - กำหนดค่าใช้จ่ายได้อย่างแม่นยำตามความเหมาะสม") | R15: -Kaç kötü parçalar? - Müşteri sürecinde tespiti sırasında kusurlu kaç kötü parça Hassas bulunmuştur? - Hassas o zaman uygun düzgün maliyeti nasıl")
A16: [11] | B16: What is the difference between good and bad parts? The defect must be described as the deviation between a good and a bad part. Focus on the part and not on the customer application or customer process. These data prepare the analysis team to look in the "&"right direction, this definition will be the starting point of the FTA - Description of the problem with clear and precise facts as seen by Valeo") | C16: -Quelle est la différence entre le bien et les mauvaises parties? Le défaut doit être décrit comme l'écart entre une bonne et une mauvaise partie. Focus sur la partie et non sur l'application client ou processus client. Ces données préparent l'équipe d'ana"&"lyse à regarder dans la bonne direction, cette définition sera le point de départ de l'ALE - Description du problème avec des faits clairs et précis vu par Valeo") | D16: -Qual é a diferença entre as peças boas e ruins? O defeito deve ser descrito como o desvio entre uma peça boa e uma peça ruim. Concentre-se na peça e não no aplicativo ou processo do cliente. Esses dados preparam a equipe de análise para olhar na direção c"&"erta, essa definição será o ponto de partida do FTA - Descrição do problema com fatos claros e precisos, vistos pela Valeo") | E16: -¿Cuál es la diferencia entre el bien y partes malas? El defecto debe ser descrito como la desviación entre una buena y una parte mala. Centrarse en la pieza y no en la aplicación cliente o proceso de cliente. Estos datos preparan el equipo de análisis par"&"a mirar en la dirección correcta, esta definición será el punto de partida del TLC - Descripción del problema con hechos claros y precisos, como se ve por Valeo") | F16: -好件与坏件之间的区别？ 缺陷必须被描述为好件和坏件之间的偏差。关注零件本身，而不是客户的应用或客户的过程。这些数据是为分析小组找到正确方向做准备的，这个定义将会是FTA的起始点 - 从法雷奥观点清楚、准确地描述问题") | G16: -Jaký je rozdíl mezi dobrými a špatnými díly? Vada musí být popsána jako odchylka mezi dobrým a špatným dílem. Zaměřte se na díl a ne na zákaznickou aplikaci nebo proces. Tyto údaje pomohou celému týmu se dívat správným směrem při analýze problému, tato de"&"finice bude výchozím bodem pro analýzu FTA - Popis problému s jasnými a přesnými skutečnostmi z pohledu Valea") | H16: -Was ist der Unterschied zwischen guten und schlechten Teilen? Der Fehler muss als Abweichung zwischen einem guten und einem schlechten Teil beschrieben werden. Konzentrieren Sie sich auf das Teil und nicht auf die Kundenanwendung oder Kundenprozess. Diese"&" Daten dienen zur Vorbereitung für das Analyse-Team in der richtigen Richtung zu suchen, diese Definition ist der Ausgangspunkt für die FTA. - Beschreibung des Problems mit klaren und präzisen Fakten aus Valeo Sicht") | I16: -Mi a különbség a jó és rossz részek? A hibát úgy kell leírni, mint a szórás között egy jó és egy rossz része. Fókuszban a részét, és nem az ügyfél alkalmazás vagy az ügyfél folyamatban. Ezek az adatok előkészítése az elemzés csapat nézni a helyes irányba,"&" ez a meghatározás lesz a kiindulási pont a szabadkereskedelmi - A probléma leírása egyértelmű és pontos tények által látott Valeo") | J16: -Apa perbedaan antara baik dan bagian yang buruk? cacat harus digambarkan sebagai deviasi antara yang baik dan bagian yang buruk. Fokus pada bagian dan bukan pada aplikasi pelanggan atau proses pelanggan. Data ini mempersiapkan tim analisis untuk melihat k"&"e arah yang benar, definisi ini akan menjadi titik awal dari FTA - Deskripsi masalah dengan fakta-fakta yang jelas dan tepat seperti yang terlihat oleh Valeo") | K16: -Qual è la differenza tra i pezzi buoni e quelli difettosi? Il difetto deve essere descritto come differenza tra un pezzo buono e uno di scarto. Bisogna focalizzarsi sul pezzo e non sull'applicazione o processo del Cliente. Questi dati guidano il team di a"&"nalisi nella giusta direzione, e questa definizione sarà il punto di inizio dell'FTA - Descrizione del problema con descrizione chiara e precisa dei fatti come visti da Valeo") | L16: -良品と不良品の差は何ですか？ 不具合は良品と不良品の差に基づいて記述されなければならない。顧客使用状況や工程ではなく、製品そのものに焦点をあてること。これらのデータは分析するチームを正しい方向に導くための準備となり、これはFTAのスタートポイントとなる。 - Valeoの観点で見た場合の明瞭で正確な事実に基づいて記述") | M16: -부적합 제품과 정상제품의 차이점은 무엇입니까? 부적합은 반드시 정상 제품과 부적합 제품간의 차이를 설명해야 합니다. 차이점은 고객의 작업 또는 고객의 공정이 아닌 제품에 초점을 맞추어야 합니다. 이 정보는 분석팀이 옳바른 방향으로 부적합을 분석할 수 있게 하며, FTA의 시작점이 될 것 입니다. - 발레오의 시선으로 사실에 기반하여 명확하게 문제 정의가 되어야 합니다. ") | N16: -Jaka jest różnica między dobrymi i złymi częściami? Wada musi być opisana jako odchylenie o dobrych i złych części. Skupić się na części, a nie w aplikacji klienta lub procesu klienta. Dane te przygotowanie zespołu analitycznego spojrzenia we właściwym ki"&"erunku, definicja ta będzie punktem wyjścia FTA - Opis problemu z jasnych i precyzyjnych faktów widzianych przez Valeo") | O16: -Care este diferența dintre bine și rău părți? Defectul trebuie să fie descrisă ca abaterea între o bună și o parte proastă. Focus pe partea și nu pe aplicația client sau procesul de client. Aceste date pregăti echipa de analiză să se uite în direcția core"&"ctă, această definiție va fi punctul de plecare al ALS - Descrierea problemei cu fapte clare și precise văzut de Valeo") | P16: -В чем разница между хорошими и плохими деталями? Дефект должен быть описан как отклонение между хорошей и плохой деталью. Сосредоточьтесь на детали, а не на заявлении клиента или процессе клиента. Эти данные подготовят аналитическую группу к тому, чтобы с"&"мотреть в правильном направлении, это определение станет отправной точкой для FTA. - Описание проблемы с ясными и точными фактами, как это видит Valeo") | Q16: -อะไรคือความแตกต่างระหว่างงานดีและงานเสีย? ข้อบกพร่องต้องอธิบายว่าความเบี่ยงเบนระหว่างงานดีและงานเสีย มุ่งเน้นไปที่ชิ้งานไม่ใช่ในการใช้งานของลูกค้าหรือกระบวนการของลูกค้า ข้อมูลเหล่านี้เตรียมทีมวิเคราะห์เพื่อมองไปในทิศทางที่ถูกต้อง, คำจำกัดความนี้เป็นจุด"&"เริ่มต้นของ FTA - คำอธิบายปัญหาพร้อมข้อเท็จจริงที่ชัดเจนและแม่นยำตามมุมมองของวาลีโอ") | R16: -iyi ve kötü parçaları arasındaki fark nedir? kusur iyi ve kötü bir parça arasındaki sapma olarak tanımlanabilir olmalıdır. parçası değil müşteri uygulama veya müşteri süreci odaklanın. Bu veriler doğru yönde bakmak için analiz ekibi hazırlamak, bu tanım F"&"TA başlangıç ​​noktasını olacak - net ve kesin gerçeklerle Sorunun açıklaması Valeo'ya tarafından görülen")
A17: [12] | B17: Was part produced in the standard process? Any product or process deviation or rework or operation done by non qualified person must be taken in consideration. If the answer is NO, the deviation must be clearly described and the references of the associat"&"ed documents mentionned. Use tracability information on the part to answer to the question.") | C17: -Faisait partie produit dans le processus standard? Tout écart de produit ou d'un procédé ou une opération reprise effectuée par personne non qualifié doit être pris en considération. Si la réponse est NON, l'écart doit être clairement décrit et les référe"&"nces des documents associés mentionné. Utiliser les informations de tracabilité de la part de répondre à la question.") | D17: -A peça foi produzida no processo padrão? Qualquer desvio de produto ou processo ou retrabalho ou operação feito por pessoa não qualificada deve ser levado em consideração. Se a resposta for NÃO, o desvio deve ser claramente descrito e as referências dos "&"documentos associados mencionadas. Use as informações de rastreabilidade da peça para responder à pergunta.") | E17: -Se produce en parte el proceso estándar? Cualquier desviación de producto o proceso o la reanudación o la operación realizada por una persona no calificada deben ser tomados en consideración. Si la respuesta es NO, la desviación se debe describir con clar"&"idad y las referencias de los documentos asociados mencionado. El uso de información por parte trazabilidad para responder a la pregunta.") | F17: -零件是在标准的过程中生产出来的吗？ 任何产品或过程的偏差或返工或由未认证的员工操作，都必须被考虑到。如果答案是否定的，该偏差必须要被清楚地描述，并且要提到引用的相关的文件。用该零件的追溯性信息来回答问题。") | G17: -Byl díl vyroben ve standardním procesu? Je třeba vzít v úvahu jakoukoliv odchylku výrobku nebo výrobního procesu, opravy (reworks) nebo operace provedené nekvalifikovanou osobou. Je-li odpověď NE, musí být odchylky jasně popsány a zmíněny odkazy na souvis"&"ející dokumenty. K odpovědi na tuto otázku použijte informace o dohledatelnosti (traceability) přítomné na špatném výrobku.") | H17: -Wurde das Teil mit dem Standardprozess hergestellt? Alle Produkt- oder Prozessabweichung oder Nacharbeit oder der Betrieb durch nicht qualifiziertes Personal muss in Betracht gezogen werden. Wenn die Antwort NEIN ist, so muss die Abweichung klar beschrieb"&"en und die Referenzen der zugehörigen Dokumente erwähnt werden. Die Rückverfolgbarkeits-Informationen auf dem Teil sind zur Beantwortung der Frage zu benutzen.") | I17: -Része volt elő a szokásos eljárással? Bármilyen termék vagy folyamat eltérés vagy átdolgozásra vagy művelet történik, nem képesített személy kell figyelembe venni. Ha a válasz nem, az eltérés világosan le kell írni, és a hivatkozások a kapcsolódó dokument"&"umok említettük. Felhasználási tracability információt a része, hogy válaszoljon a kérdésre.") | J17: -Itu bagian diproduksi dalam proses standar? Setiap produk atau proses penyimpangan atau pengerjaan ulang atau operasi yang dilakukan oleh orang non memenuhi syarat harus diambil dalam pertimbangan. Jika jawabannya adalah TIDAK, penyimpangan harus diuraika"&"n secara jelas dan referensi dari dokumen-dokumen terkait mentionned. Gunakan informasi tracability pada bagian untuk menjawab pertanyaan itu.") | K17: -Il pezzo è stato prodotto in un processo standard? Devono essere prese in considerazione deroghe di prodotto o processo e rilavorazioni fatte da personale non qualificato. Se la risposta è NO, il difetto deve essere chiaramente descritto facendo riferimen"&"ti ai documenti di processo associati. Utilizzare le informazioni di rintracciabilità sul pezzo per rispondere alla domanda.") | L17: -製品は通常標準工程で生産されたか？ どのような製品または製造工程における標準逸脱あるいは認定されていないオペレーターによるリワークも考慮する事。もし回答がNOであれば、標準逸脱は正確に記述され関連書類の詳細も同様記述される事。質問に回答する為、トレーサビリティー情報を使用する事") | M17: -제품은 표준 프로세스를 따라 생산되었습니까? 제품 또는 공정의 차이, 또는 리워크, 또는 지정되지 않은 작업자에 의한 생산등을 확인해야 합니다. 만약 답변이 ""아니요"" 라면, 차이점은 명확하게 기술되어야 하며, 관련 문서 또한 확인이 필요합니다. 제품 추적정보를 사용하여, 질문에 답변하시기 바랍니다.") | N17: -Została część produkowana w standardowym procesie? Wszelkie odchylenia produktu lub procesu lub przerobienie lub praca wykonywana przez wykwalifikowaną osobę nie muszą być brane pod uwagę. Jeśli odpowiedź brzmi NIE, odchylenie musi być jasno opisane i odn"&"iesienia do dokumentów związanych mentionned. Wykorzystanie informacji spójność pomiarowa na części, aby odpowiedzieć na to pytanie.") | O17: -A fost parte produs în procesul standard? Orice produs sau proces deviere sau reprelucrate sau operație efectuată de către persoana care nu calificată trebuie să fie luate în considerare. În cazul în care răspunsul este NU, abaterea trebuie să fie descris"&"ă în mod clar și referințele documentelor asociate mentionate. Utilizați informații tracability pe partea de a răspunde la întrebarea.") | P17: -Деталь была произведена в стандартном процессе? Необходимо учитывать любые отклонения продукта или процесса, доработки или операции, выполненные неквалифицированным лицом. Если ответ отрицательный, необходимо четко описать отклонение и указать ссылки на с"&"оответствующие документы. Используйте информацию о прослеживаемости детали, чтобы ответить на вопрос.") | Q17: -ชิ้นงานถูกผลิตภายใต้กระบวนการมาตรฐานหรือไม่? ผลิตภัณฑ์หรือกระบวนการใดๆ ที่เบี่ยงเบนหรือการดำเนินผลิตโดยบุคคลที่ไม่ผ่านการรับรองจะต้องถูกนำมาพิจารณา ถ้าคำตอบคือไม่, ถ้าคำตอบคือไม่ต้องอธิบายความเบี่ยงเบนอย่างชัดเจนและการอ้างอิงของเอกสารที่เกี่ยวข้องที่กล่าว"&"ถึง. ใช้ข้อมูลการตรวจสอบย้อนกลับในส่วนนั้นเพื่อตอบคำถาม.") | R17: -bölüm standart süreçte üretilen mı? olmayan uzman bir kişi tarafından yapılan herhangi bir ürün veya yöntem sapma ya da yeniden işleme veya işletme dikkate alınmalıdır. cevabınız HAYIR ise, sapma açıkça tarif ve ilgili belgelerin referanslar bahsettiğimde"&" edilmelidir. kısmında Kullanım izlenebilirlik bilgileri soruya cevap vermek.")
... A37: [32] | B37: Immediate countermeasures in Customer line Mention immediate countermeasures - Sorting - 100% control - call resident engineer to collect information ") | C37: -contre-mesures immédiates en ligne à la clientèle Mention immédiates contre-mesures - tri - le contrôle à 100% - ingénieur résident d'appel à l'information Collect") | D37: -Contra-medidas imediatas na linha do cliente Mencione contra-medidas imediatas - Seleção - 100% de controle - ligue para o engenheiro residente para coletar informações") | E37: -contramedidas inmediatas en la línea de atención al cliente Mención inmediata adopción de medidas - Clasificación - control del 100% - ingeniero residente llamada a cobro revertido a la información") | F37: -客户端的临时措施 临时措施： - 挑选 - 100％检查 - 通知常驻工程师收集信息") | G37: -Okamžitá protiopatření na lince Zákazníka Popište okamžitá protiopatření - třídění - 100% kontrola - zavolejte rezidentním inženýrům pro sběr informací") | H37: -Sofortige Gegenmaßnahmen in Kunden Linie Erwähnen Sie sofort Gegenmaßnahmen - Sortierung - 100% Kontrolle - Anruf Resident Engineer, Informationen zu sammeln") | I37: -Azonnali ellenintézkedéseket Ügyfél vonal Oldalon azonnali ellenintézkedéseket - Válogatás - 100% kontroll - hívás rezidens mérnök információk összegyűjtésére") | J37: -penanggulangan Segera sejalan Pelanggan Menyebutkan penanggulangan segera - Sortasi - kontrol 100% - panggilan warga insinyur untuk informasi mengumpulkan") | K37: -Contromisure immediate sulla linea del cliente Menzionare le immediate contromisure - Selezione - Controllo al 100% - Chiamare il resident engineer per raccogliere informazioni") | L37: -顧客ラインでの即時対策？ 即時対策について述べよ： - 選別 - 100％コントロール - GREへ連絡しての情報収集") | M37: -고객 라인 즉각 조치 즉각 조치내용에 대해 기입 : - 선별 - 100% 관리 - 정보 수집을 위한 상주원과 연락") | N37: -Natychmiastowe środki zaradcze w linii Klienta Wspomnieć natychmiastowych środków zaradczych - sortowanie - Kontrola 100% - inżynier rezydent wezwanie do zbierania informacji") | O37: -contramăsuri imediate în linie pentru clienți Menționează contramăsuri imediate - Sortare - control 100% - inginer rezident apel la informații collect") | P37: -Незамедлительные контрмеры на линии потребителя Упоминание незамедлительных контрмер: - сортировка - 100% контроль - звонок инженеру-резиденту для сбора информации") | Q37: -มาตรการตอบโต้ทันทีในไลน์ของลูกค้า กล่าวถึงการตอบโต้ทันที - การคัดแยก - การควบคุม 100% - เรียกวิศวกรประจำพื้นที่ลูกค้าเพื่อจำเก็บรวบรวมข้อมูล") | R37: -Müşteri hattında Acil önlemler hemen karşı bahsedin - Sıralama -% 100 kontrol - ödemeli bilgilere çağrı şantiye mühendisi")
B39: -Timeline") | C39: -Chronologie") | D39: -Linha do Tempo") | E39: -Cronología") | F39: -时间轴 ") | G39: -Časová osa") | H39: -Zeitleiste") | I39: -Idővonal") | J39: -Linimasa") | K39: -Sequenza temporale") | L39: -タイムライン") | M39: -타임 라인") | N39: -Oś czasu") | O39: -Cronologie") | P39: -Временная шкала") | Q39: -เส้นเวลา") | R39: -Zaman çizelgesi")
A40: [1] | B40: -Timeline starts from the date of production of the bad part / situation and works backwards from that date to identify events which may have generated the occurrence or lack of detection. These key events should be highlighted on the timeline, and then "&"identified as factors in the FTAs. - To easily identify the events, it may help to split the timeline into multiple timelines, for example: Customer event timeline / Valeo timeline / Supplier timeline / Project timeline.......") | C40: -Chronologie commence à partir de la date de production de la mauvaise partie / situation et travaille à rebours à partir de cette date pour identifier les événements qui peuvent avoir généré l'apparition ou l'absence de détection. Ces événements clés devr"&"aient être mis en évidence sur la timeline, puis identifiés comme des facteurs dans les ALE. - Pour identifier facilement les événements, il peut aider à diviser le calendrier en plusieurs échéances, par exemple: calendrier calendrier / Valeo événement cl"&"ient / calendrier fournisseur / Calendrier du projet .......") | D40: -A linha do tempo começa na data de produção da peça / situação ruim e retrocede a partir dessa data para identificar os eventos que podem ter gerado a ocorrência ou falta de detecção. Esses eventos-chave devem ser destacados na linha do tempo e, em seguid"&"a, identificados como fatores nos FTAs. - Para identificar facilmente os eventos, pode ser útil dividir o cronograma em vários cronogramas, por exemplo: cronograma do evento do cliente / cronograma da Valeo / cronograma do fornecedor / cronograma do proj"&"eto .......") | E40: -Línea de tiempo comienza a partir de la fecha de producción de la parte mala / situación y trabaja hacia atrás a partir de esa fecha para identificar eventos que pueden haber generado la aparición o la falta de detección. Estos eventos clave deben ser res"&"altados en la línea de tiempo, y luego se identificaron como factores en los TLC. - Para identificar fácilmente los eventos, puede ser útil para dividir la línea de tiempo en múltiples líneas de tiempo, por ejemplo: línea de tiempo de eventos de cliente /"&" Valeo Linea de tiempo / distribuidor / línea de tiempo del proyecto .......") | F40: -时间轴是从坏件/坏的状态生产日期开始，并从该日期向前追溯，以确定是什么可能的事件导致了问题的发生或流出。这些关键事件应该在时间轴上突出显示，然后汇总为FTA分析的因子。 - 为了便于识别这些事件，可以将一个时间轴分解为多个时间轴，例如：客户事件时间轴 / 法雷奥时间轴 / 供应商时间轴 / 项目时间轴.......") | G40: -Časová osa začíná od data výroby špatné části / situace a pracuje zpětně od tohoto okamžiku tak, abychom identifikovali všechny události. které mohly vytvořit příčinu problému nebo nedostatek detekce. Tyto klíčové události mají být zvýrazněny na časové "&"ose, a pak popsány jako faktory v FTA analýzách (Occ/ND). - K usnadnění identifikace událostí může pomoci rozdělení časové osy na několik časových os. Například Časová osa Zákazníka, časová osa Valeo, časová osa dodavatele, časová osa projektu... ") | H40: -Timeline beginnt ab dem Zeitpunkt der Herstellung der schlechten Teil / Situation und arbeitet nach hinten ab diesem Zeitpunkt Ereignisse zu identifizieren, die das Auftreten erzeugt haben können oder das Fehlen des Nachweises. Diese Schlüsselereignisse s"&"ollen auf der Zeitleiste hervorgehoben werden, und dann als Faktoren in der FHA identifiziert. - Um leicht die Ereignisse zu identifizieren, kann es helfen, die Zeitleiste in mehrere Zeitrahmen, zum Beispiel zu spalten: Kundenveranstaltung Timeline / Vale"&"o Timeline / Lieferant Timeline / Timeline-Projekt .......") | I40: -Idővonal kezdődik a gyártás dátuma a rossz része / helyzetet, és működik visszafelé ettől az időponttól azonosítani eseményeket, amelyek esetleg keletkező bekövetkezése vagy hiányzik a felismerés. Ezek a kulcsfontosságú eseményeket kell emelni az idővonal"&"on, majd olyan tényezőnek a szabadkereskedelmi megállapodások. - Ahhoz, hogy könnyen azonosítani az események, akkor segíthet, hogy szét az idővonal a több idővonal, például: Ügyfél esemény idővonal / Valeo idővonal / szállító idővonal / Projekt idővonal "&".......") | J40: -Timeline dimulai dari tanggal produksi yang buruk bagian / situasi dan bekerja mundur dari tanggal tersebut untuk mengidentifikasi peristiwa yang mungkin telah dihasilkan terjadinya atau kurang dari deteksi. peristiwa penting ini harus disorot pada timeli"&"ne, dan kemudian diidentifikasi sebagai faktor dalam FTA. - Untuk mudah mengidentifikasi peristiwa, mungkin membantu untuk membagi timeline menjadi beberapa jadwal, misalnya: acara Pelanggan garis waktu / Valeo waktu / Pemasok waktu / Proyek waktu .......") | K40: -Cronologia inizia dalla data di produzione della parte difettosa / situazione e procede a ritroso da quella data per identificare gli eventi che possono aver generato la comparsa del problema o la mancata rilevazione dello stesso. Questi eventi chiave dev"&"ono essere evidenziati nella sequenza temporale ed identificati come fattori nella FTAs. - Per identificare facilmente gli eventi, può essere utile dividere la linea temporale in più linee temporali, ad esempio: cronologia dell'evento dal cliente / cronol"&"ogia in Valeo / cronologia dal fornitore / cronologia del progetto...") | L40: -タイムラインは不具合品/不具合状況の発生日から始まり、そこから遡及して、不良が発生した、あるいは、不良が検出できなかった理由に起因しそうな出来事を特定してゆきます。これら重要な出来事はタイムラインに記載され、FTAでの分析要素となります。 - 簡単に出来事を特定する為に、タイムラインを複数分割事は役に立ちます。例えば、顧客出来事タイムライン / Valeotimeライン/ 協力企業タイムライン / Projectタイムラインなど.......") | M40: - 타임 라인은 부적합 제품 생산일자 / 부적합 상황의 시작일자부터 시작하며, 문제가 발견된 날짜 또는 미검출된 날짜까지 작성됩니다. 중요 사건은 타임라인상에 명기되어야하며, 해당 사건은 FTA의 요소로 검증되어야 합니다. - 각각의 타임 라인을 분할하여 쉽게 작성할 수 있습니다. 예를 들어 : 고객 사건 타임 라인 / 발레오 타임 라인 / 협력업체 타임 라인 / 프로젝트 타임 라인 등") | N40: -Oś czasu rozpoczyna się od daty produkcji złej części / sytuacji i działa wstecz od tej daty do identyfikacji zdarzeń, które mogły być generowane występowanie lub brak detekcji. Te kluczowe wydarzenia powinny być podświetlone na osi czasu, a następnie zid"&"entyfikowane jako czynniki w umowach o wolnym handlu. - Aby łatwo identyfikować zdarzenia, może się to przyczynić do dzielenia oś czasu na wiele terminów, na przykład: Event klienta osi czasu / timeline Valeo / osi czasu Dostawca / osi czasu projektu ...."&"...") | O40: -Cronologie începe de la data producției de proastă parte / situația și lucrări înapoi de la această dată pentru a identifica evenimentele care ar putea fi generat apariția sau lipsa de detecție. Aceste evenimente-cheie ar trebui să fie evidențiate pe cron"&"ologie, și apoi identificați ca factori în acordurile de liber schimb. - Pentru a identifica cu ușurință evenimentele, aceasta poate ajuta să împartă cronologie în mai multe termene, de exemplu: eveniment Client cronologie / Valeo cronologie / furnizor cr"&"onologie / cronologia proiectului .......") | P40: -Временная шкала начинается с даты производства плохой детали / ситуации и работает в обратном порядке с этой даты, чтобы идентифицировать события, которые могли привести к возникновению или отсутствию обнаружения. Эти ключевые события должны быть выделены"&" на временной шкале, а затем идентифицированы как факторы в FTA. - Чтобы легко идентифицировать события, можно разделить временную шкалу на несколько временных шкал, например: временная шкала событий клиента / временная шкала Valeo / временная шкала пост"&"авщика / временная шкала проекта ....... ") | Q40: -เส้นเวลาเริ่มจากวันที่ผลิตของที่ไม่ดีส่วนหนึ่ง / สถานการณ์และผลงานย้อนหลังนับจากวันที่การระบุเหตุการณ์ที่อาจเกิดขึ้นได้สร้างหรือขาดการตรวจสอบ เหตุการณ์สำคัญเหล่านี้ควรจะเน้นบนไทม์ไลน์และจากนั้นระบุว่าเป็นปัจจัยในเขตการค้าเสรี - เพื่อให้ง่ายต่อการระบุเหตุก"&"ารณ์ที่เกิดขึ้นมันอาจจะช่วยในการแยกระยะเวลาลงในระยะเวลาหลายตัวอย่างเช่นกรณีที่ลูกค้าไทม์ไลน์ / Valeo ระยะเวลา / ผู้ผลิตไทม์ไลน์ / เส้นเวลาโครงการ .......") | R40: -Zaman Çizelgesi kötü tarafı / durumun üretim tarihinden itibaren başlar ve oluşumunu oluşturulmuş veya algılama eksikliği olabilir olayları tanımlamak için bu tarihten itibaren geriye doğru çalışır. Bu temel olaylar zaman çizgisinde vurgulanır ve sonra ST"&"A faktörler olarak tanımlanmalıdır. - To kolaylıkla örneğin, birden çok zaman çizelgeleri içine çizelgesi bölmek için yardımcı olabilir, olayları tanımlamak: Müşteri olay çizelgesini / Valeo çizelgesi / Tedarikçi çizelgesi / Proje zaman çizelgesi .......")
B42: -Process Flow") | C42: -Flux de processus") | D42: -Fluxo de Processo") | E42: -Flujo del proceso") | F42: -过程流程") | G42: -Průběh procesu") | H42: -Prozessablauf") | I42: -Folyamatábra") | J42: -proses Arus") | K42: -Flusso di processo") | L42: -プロセスフロー") | M42: -공정 흐름") | N42: -Przebieg procesu") | O42: -Procesați Flow") | P42: -Последовательность процесса") | Q42: -ผังกระบวนการ") | R42: -Süreç akışı")
A43: [1] | B43: -Describe flow-chart reflecting real situation & Indicate workstation / Location where Occurrence / Non Detection could occur It could be process flow-Chart, photograph, manual sketch,.... ") | C43: -Décrire organigramme reflétant la situation réelle et indiquer la station de travail / Lieu où Occurrence / non détection pourrait se produire Il pourrait être SCHEMA, photographie, croquis processus manuel, ....") | D43: -Descreva o fluxograma que reflete a situação real e indica a estação de trabalho / local onde a ocorrência / não detecção pode ocorrer Pode ser fluxograma de processo, fotografia, esboço manual, ....") | E43: -Describir diagrama de flujo que refleja la situación real y de la estación de trabajo Indique / Lugar donde Ocurrencia / No detección podría ocurrir Podría ser proceso de diagrama de flujo, fotografía, dibujo manual, ....") | F43: -绘制流程图，反映真实情况和指明问题可能发生或流出的工站 /位置。 可以是过程流程图，照片，手工草图，....") | G43: -Popište Flow-chart (blokový diagram procesu) tak, aby odrážel skutečnou situaci. Zvýrazněte pracovní stanící nebo místo, kde mohlo dojít k výskytu nebo/a k nalezení problému. Můžete použít blokový diagram procesu, fotografie, ruční nákres, atd.") | H43: -Beschreiben Flussdiagramm reflektieren reale Situation & Geben Sie Arbeitsplatz / Ort, an dem Auftreten / Nichterkennung auftreten könnte Es könnte Prozessfluss-Diagramm, Fotografie, manuelle Skizze sein, ....") | I43: -Ismertesse folyamatábra tükröző valós helyzetet & Jelölje munkaállomás / hely, ahol előfordulása / Non Detection előfordulhatnak Ez lehet folyamatábra-diagram, fénykép, kézi vázlat, ....") | J43: -Jelaskan aliran-chart mencerminkan situasi nyata & Menunjukkan workstation / Lokasi di mana Terjadinya / Non Deteksi bisa terjadi Ini bisa menjadi proses aliran-Chart, foto, panduan sketsa, ....") | K43: -Descrivere il diagramma di flusso che riflette la situazione reale e indica la postazione di lavoro / posizione in cui potrebbe verificarsi un evento / mancato rilevamento Ad esempio diagramma di flusso del processo, fotografia, schema...") | L43: -現実を加味した工程フローチャートの記入＆ワークステーションの特定 / 発生あるいは未検出が起こったであろう場所の特定 プロセス・フロー・チャート、写真、スケッチなどを用いて.....") | M43: -실제 상황 & 작업 스테이션 / 발생 공정 / 미 검출 발생 공정 등 을 반영하여 설명 공정 흐름은 ""공정 흐름도"", ""사진"", ""스케치""로 도 사용이 가능합니다.") | N43: -Opisać schemat blokowy odzwierciedla rzeczywistą sytuację i wskazać Workstation / Location gdzie Występowanie / Non Wykrywanie może wystąpić Może to być proces przepływu Wykres, fotografia, ręczny szkic, ....") | O43: -Descrie fluxul de diagramă care reflectă situația reală și Indicați stația de lucru / Locul de amplasare în cazul în care Apariție / Non detectare ar putea avea loc Ar putea fi procesul de flux Chart, fotografie, schiță manuală, ....") | P43: -Опишите последовательность процесса, отражающую реальную ситуацию, и укажите рабочую станцию / место, где может произойти вознкновение / необнаружение. Это может быть блок-схема процесса, фотография, ручной эскиз и т. д...") | Q43: -อธิบายผังงานที่สะท้อนสถานการณ์จริงและระบุเวิร์กสเตชัน / สถานที่ที่อาจเกิดขึ้น / ตรวจไม่พบ อาจเป็นผังงานกระบวนการภาพถ่ายร่างคู่มือ ....") | R43: -Gerçek durumu yansıtan akış şeması tarif edin ve iş istasyonu / Yer nerede Oluşum / Sigara Algılama oluşabilir belirtiniz Bu süreç akış Grafik, fotoğraf, manuel kroki olabilir ....")
B45: -Assignment / Breakdown") | C45: -Cession / Ventilation") | D45: -Atribuição / Divisão") | E45: -Asignación / Distribución") | F45: -任务分配 / 分解") | G45: -Zaúkolování / Rozdělení na menší úkoly") | H45: -Zuordnung / Aufteilung") | I45: -Hozzárendelés / bontás") | J45: -Tugas / Breakdown") | K45: -Assegnazione / Ripartizione") | L45: -割り当て/内訳") | M45: -업무 지정 / 브레이크다운") | N45: -Przypisanie / Podział") | O45: -Tema / Breakdown") | P45: -Поручения") | Q45: -การกำหนด / พังทลาย") | R45: -Atama / Arıza")
A46: [1] | B46: -Assignment Define detailled actions to carry on the analysis of the issue, does not include final counter measures. The objective is to breakdown the analysis in parallel activities to speed up the resolution of the problem") | C46: -Affectation Définir les actions à DETAILLE porter sur l'analyse de la question, ne comprend pas les mesures de contre-finales. L'objectif est de répartition de l'analyse des activités parallèles pour accélérer la résolution du problème") | D46: -Atribuições Definir ações detalhadas para continuar a análise do problema, não inclui contra-medidas finais. O objetivo é decompor a análise em atividades paralelas para agilizar a resolução do problema") | E46: -Asignación Definir acciones detallado para llevar a cabo el análisis de la cuestión, no incluye medidas finales de contador. El objetivo es para la descomposición del análisis de actividades paralelas para acelerar la resolución del problema") | F46: -任务分配 制定详细的行动计划来分析问题，但不包括最终对策。目的是将分析分解为一些同时进行的行动以加快问题的解决速度。") | G46: -Zaúkolování Definujte detailní akce k provedení analýzy problému, nezahrnujte konečná nápravná opatření. Cílem je rozdělení analýzy na paralelní činnosti tak, aby se urychlilo řešení problému") | H46: -Zuordnung Definieren Sie detaillierte Aktionen zu tragen auf der Analyse des Problems, nicht enthalten endgültige Gegenmaßnahmen. Das Ziel ist die Analyse in parallelen Aktivitäten zum Abbau der Lösung des Problems zu beschleunigen") | I46: -Feladat Adjuk Reszletekert intézkedések carry elemzése a kérdés, nem tartalmaz végleges ellenintézkedéseket. A cél az, hogy bontás az elemzés párhuzamos tevékenységeket, hogy gyorsítsák fel az a probléma megoldását") | J46: -Tugas Menentukan tindakan detailled untuk membawa pada analisis masalah, tidak termasuk tindakan pencegahan akhir. Tujuannya adalah untuk rincian analisis dalam kegiatan paralel untuk mempercepat penyelesaian masalah") | K46: -Incaricare Definire le azioni dettagliate per portare avanti l'analisi del problema (non include le contromisure finali). L'obiettivo è scomporre l'analisi in attività parallele per velocizzare la risoluzione del problema") | L46: -タスク割り当て 不具合分析を進める為の詳細なタスク分割を行う。この段階で最終対策に係るタスクは含まない。目的は、タスクの細分化により分析が並行して進むようにして問題解決のスピードアップを図る事") | M46: -업무 지정 최종 조치를 제외하고, 문제 분석을 수행하기 위한 세부 조치내용을 정의합니다. 업무 지정의 목적은 여러 작은단위의 분석을 동시에 진행하여, 문제 해결 시간을 단축시키는 것 입니다.") | N46: -Zadanie Definiowanie zobaczyć szczegółowe działania na prowadzenie analizy problemu, nie zawiera ostateczne środki zaradcze. Celem jest analiza awarii w równoległych działań w celu przyspieszenia rozwiązania problemu") | O46: -Misiune Definirea acțiunilor detaliata pentru a continua analiza problemei, nu include măsuri finale contra. Obiectivul este de a analiza defalcare în activități paralele pentru a accelera soluționarea problemei") | P46: -Поручения Определите подробные действия для проведения анализа проблемы, не включая окончательные контрмеры. Цель состоит в том, чтобы разбить анализ на параллельные действия, чтобы ускорить решение проблемы ") | Q46: -การมอบหมาย กำหนดการดำเนินงานโดยละเอียดเพื่อดำเนินการวิเคราะห์ปัญหาโดยไม่รวมมาตรการตอบโต้ขั้นสุดท้าย มีวัตถุประสงค์เพื่อแยกวิเคราะห์การวิเคราะห์ในกิจกรรมคู่ขนานเพื่อเร่งการแก้ไขปัญหา") | R46: -Görev konunun analizine taşıma için ayrıntılandırılacaktır eylemleri tanımlayın, son saptiricilara içermez. Amaç arıza sorunun çözümünü hızlandırmak için paralel faaliyetlerde analizidir")
A47: [2] | B47: -Results Record the results of the action. If needed, put reference of document where information are available, join the document to the PDCA file.") | C47: -Résultats Enregistrer les résultats de l'action. Le cas échéant, référence des documents mis où les informations sont disponibles, joignez-vous au document dans le fichier PDCA.") | D47: -Resultados Registre os resultados da ação. Se necessário, coloque a referência do documento onde as informações estiverem disponíveis, junte o documento ao arquivo PDCA.") | E47: -resultados Registrar los resultados de la acción. Si es necesario, poner la referencia del documento en el que se dispone de información, se unen el documento en el fichero de PDCA.") | F47: -结果 记录行动措施的结果。如果需要的话，把相关的文件编号放在信息展示的位置，加入到PDCA文件中。") | G47: -Výsledky Zaznamenejte výsledky akce. Pokud je to nutné, uveďte odkaz na dokument, kde jsou tyto informace k dispozici , připojte tento dokument do souboru PDCA.") | H47: -Ergebnisse Notieren Sie die Ergebnisse der Aktion. Bei Bedarf stellen Referenz des Dokuments, wo Informationen verfügbar sind, verbinden sie das Dokument an die PDCA-Datei.") | I47: -Eredmények Jegyezzük fel az akció eredményeit. Ha szükséges, tegye referencia dokumentum, ahol az információk rendelkezésre állnak, csatlakozzon a dokumentumot a PDCA fájlt.") | J47: -hasil Merekam hasil dari tindakan. Jika diperlukan, menempatkan referensi dokumen mana informasi yang tersedia, bergabung dokumen ke file PDCA.") | K47: -Risultati Registra i risultati dell'azione. Se necessario, inserire il riferimento del documento dove sono disponibili le informazioni, unire il documento al file PDCA.") | L47: -結果 アクションの結果を記録します。必要であれば、有益な情報が含まれる書類の管理番号等を記載、PDCAファイルにも紐づけする") | M47: -결과 활동에 대한 결과를 입력합니다. 필요한 경우, 어디에서 해당 내용을 찾을 수 있는지 문서번호를 입력 할 수 있으며, PDCA 파일내에 문서를 추가 할 수 있습니다. ") | N47: -wyniki Rejestruje wyniki działania. W razie potrzeby umieścić odniesienie do dokumentu, jeśli informacje są dostępne, dołączyć dokument do pliku PDCA.") | O47: -Rezultate Înregistrați rezultatele acțiunii. Dacă este necesar, referința documentului pus în cazul în care sunt disponibile informații, se alăture documentul la dosar PDCA.") | P47: -Полученные результаты Запишите результаты действий. При необходимости укажите ссылки на документ, где доступна информация, прикрепите документ к файлу PDCA.") | Q47: -ผล บันทึกผลการดำเนินงาน หากจำเป็นให้ใส่การอ้างอิงของเอกสารที่มีข้อมูลรวมเอกสารเข้ากับไฟล์ PDCA") | R47: -Sonuçlar eylemin sonuçlarını kaydedin. Gerekirse, bilgi mevcuttur belgenin koymak referans PUKÖ dosyasına belgeyi katılmak.")
A48: [3] | B48: -Who Define who is the pilote for each activities - Only one pilot by activity") | C48: -OMS Définir qui est le pilote pour chaque activité - un seul pilote par l'activité") | D48: -Quem Defina quem é o piloto para cada atividade - apenas um piloto por atividade") | E48: -OMS Definir quién es el pilote para cada actividad - Sólo un piloto por la actividad") | F48: -谁 定义谁是每个行动的负责人 - 一个行动一个负责人") | G48: -Kdo Definujte kdo je pilotem pro každou aktivitu- Pouze jeden pilot pro každou aktivitu") | H48: -Wer Definieren Sie, wem die Pilote für jede Tätigkeit ist - nur ein Pilot nach Tätigkeit") | I48: -WHO Határozza meg, aki a pilote egyes tevékenységek - Csak egy kísérleti tevékenység") | J48: -WHO Tentukan yang merupakan pilote untuk setiap kegiatan - Hanya satu pilot oleh aktivitas") | K48: -Chi Definisci chi è il pilota per ciascuna attività - solo un pilota per attività") | L48: -誰が 誰がおのおののタスク分析のリーダーが定義する - 1 x タスク 1 x リーダー") | M48: -담당자 각 활동에 대한 담당자를 입력합니다 - 각 활동별 한명의 담당자만 가능합니다.") | N48: -WHO Określić, kim jest PILOTE dla każdej działalności - Tylko jeden pilot działalnością") | O48: -OMS Definiți cine este pilote pentru fiecare activități - Doar un singur pilot de activitate") | P48: -Кто Определите, кто является пилотом по каждому действию - только один пилот на каждое действие") | Q48: -ใคร/ผู้รับผิดชอบ กำหนดว่าใครเป็นผู้นำรับผิดชอบสำหรับแต่ละกิจกรรม ผู้รับผิดชอบเพียงคนเดียวตามกิจกรรม") | R48: -DSÖ aktivitesiyle Sadece bir pilotu - Her faaliyetler için pilote kim tanımlayın")
A49: [4] | B49: -Due date Record the date when the activity must be completed, due date must be short term dates respecting the 24 H - 5 days - 10 days rules.") | C49: -Date d'échéance Notez la date à laquelle l'activité doit être remplie, la date d'échéance doit être dates à court terme concernant la 24 H - 5 jours - 10 jours des règles.") | D49: -Data de Vencimento Registre a data em que a atividade deve ser concluída, a data de vencimento deve ser datas de curto prazo, respeitando as regras de 24 horas - 5 dias - 10 dias.") | E49: -Fecha de vencimiento Anote la fecha en que se debe completar la actividad, fecha de vencimiento debe ser fechas a corto plazo respetando la 24 H - 5 días - 10 reglas días.") | F49: -计划日期 记录行动必须要完成的日期，计划日期必须是短期的并遵守 24小时- 5天 - 10天的规则。") | G49: -Plánované datum ukončení Zapište datum, kdy musí být daná aktivita dokončena, plánované datum dokončení musí být v blízké budoucnosti a musí respektovat termíny PDCA: 24 hod - 5 dní - 10 dní ") | H49: -Geburtstermin Nehmen Sie das Datum, wenn die Aktivität müssen ausgefüllt werden müssen Fälligkeit werden kurzfristige Termine unter Beachtung der 24 H - 5 Tage - 10 Tage Regeln.") | I49: -Az esedékesség napja Jegyezzük fel a dátumot, amikor a tevékenységet úgy kell kitölteni, esedékességét kell rövid távon dátumokat tiszteletben tartja a 24 H - 5 nap - 10 nap szabályokat.") | J49: -Batas waktu Catat tanggal ketika kegiatan harus diselesaikan, tanggal jatuh tempo harus tanggal jangka pendek menghormati 24 H - 5 hari - 10 hari aturan.") | K49: -Scadenza Registrare la data in cui l'attività deve essere completata, la data di scadenza deve essere a breve termine rispettando le regole 24 ore - 5 giorni - 10 giorni.") | L49: -期限 タスクがいつ完了しなければならないか記載、期限は24時間、5 day, 10 Dayのルールを考慮して、短期的にすること。") | M49: -마감일자 각 활동의 요구된 마감일자를 입력합니다. 마감일자는 24H - 5일 - 10일 규칙을 준수하며, 이 보다 짧아야 합니다.") | N49: -termin Rejestrować datę aktywności muszą być wypełnione, termin musi być krótkie terminy termin poszanowaniu 24 h - 5 dni - 10 dni zasadami.") | O49: -Data scadentă Se înregistrează data la care activitatea trebuie să fie finalizată, data scadentă trebuie să fie date pe termen scurt, respectînd 24 H - 5 zile - 10 zile reguli.") | P49: -Планируемая дата завершения Запишите дату, когда действие должно быть завершено, дата должна быть краткосрочной датой, соблюдая правило 24 часа - 5 дней - 10 дней") | Q49: -วันที่ครบกำหนด บันทึกวันที่เมื่อมีกิจกรรมที่จะต้องเสร็จสิ้นวันที่ครบกำหนดวันที่จะต้องเคารพในระยะสั้น 24 H - 5 วัน - 10 วันกฎ") | R49: -Bitiş tarihi 5 gün - - 10 gün kurallar aktivite tamamlanması gerekir zaman vadesi 24 H saygı kısa vadeli tarihleri ​​olmalı, tarihini kaydedin.")
A50: [5] | B50: -Done date Record the date when the activity has been completed") | C50: -Date Terminé Notez la date à laquelle l'activité est terminée") | D50: -Data concluída Registre a data em que a atividade foi concluída") | E50: -la fecha hecho Registrar la fecha en que la actividad se haya terminado") | F50: -完成日期 记录行动措施实际完成日期。") | G50: -Datum dokončení Zapište datum, kdy byla daná akce dokončena") | H50: -erledigt Datum Nehmen Sie das Datum, wenn die Aktivität abgeschlossen ist") | I50: -Kész dátum Jegyezzük fel a dátumot, amikor a tevékenység befejezése") | J50: -tanggal Selesai Catat tanggal ketika aktivitas telah selesai") | K50: -Data Fine Registra la data in cui l'attività è stata completata") | L50: -完了日付 アクティビティが完了した日を記録") | M50: -완료 일자 각 활동의 완료 날짜를 기록합니다.") | N50: -Gotowe data Nagrać datę działalność została zakończona") | O50: -data Efectuat Se înregistrează data la care activitatea a fost finalizată") | P50: -Фактическая дата завершения Запишите дату, когда действие было завершено") | Q50: -วันที่เสร็จสิ้น บันทึกวันที่เมื่อมีกิจกรรมเสร็จเรียบร้อยแล้ว") | R50: -Yapıldı tarih etkinlik tamamlandığında tarihini kaydedin")
B52: -FTA & 5 Why's") | C52: -FTA et 5 Pourquoi ce") | D52: -FTA & 5 Porquê's") | E52: -TLC y 5 porqués") | F52: -FTA & 5 Why's") | G52: -FTA a 5 Proč") | H52: -FTA & 5 Warum ist") | I52: -FTA & 5 Miért a") | J52: -FTA & 5 Mengapa ini") | K52: -FTA & 5 Perché di") | L52: -FTA＆5 x なぜなぜ分析") | M52: -FTA & 5 Why's") | N52: -FTA i 5 to dlaczego") | O52: -FTA & 5 De ce lui") | P52: -FTA и 5 почему") | Q52: -FTA และ 5 ทำไม") | R52: -FTA & 5 Neden en")
A53: [1] | B53: -Problem description In this section, report exactly the answer to the question in the QR document ""What is the difference between good and bad parts""") | C53: -Description du problème Dans cette section, un rapport exactement la réponse à la question dans le document QR « Quelle est la différence entre les bonnes et les mauvaises parties »") | D53: -Descrição do Problema Nesta seção, relate exatamente a resposta à pergunta no documento QR ""Qual é a diferença entre as peças boas e ruins""") | E53: -Descripción del problema En esta sección, informar exactamente la respuesta a la pregunta en el documento QR ""¿Cuál es la diferencia entre buenos y malos partes""") | F53: -问题描述 在该模块，准确汇报在QR文件中 “好件与坏件的区别” 问题的答案。") | G53: -Popis problému V tomto oddíle popište přesnou odpověď na otázku z QR „Jaký je rozdíl mezi dobrými a špatnými díly“") | H53: -Problembeschreibung In diesem Abschnitt berichtet genau die Antwort auf die Frage in dem QR-Dokument „Was ist der Unterschied zwischen guten und schlechten Teilen“") | I53: -Problémaleírás Ebben a részben, jelentse, hogy pontosan a választ arra a kérdésre, a QR dokumentum „Mi a különbség a jó és a rossz részek”") | J53: -Soal deskripsi Pada bagian ini, melaporkan persis jawaban atas pertanyaan dalam dokumen QR ""Apa perbedaan antara baik dan buruk bagian""") | K53: -Descrizione del problema In questa sezione, riporta esattamente la risposta alla domanda nel documento QR ""Qual'è la differenza tra pezzi buoni e pezzi di scarto""") | L53: -問題の説明 このセクションでは、QRドキュメントにある""良品と不良品の差は何か？”という質問に対する正確な回答を記載する") | M53: -문제 정의 본 섹션에서는 QR에서 질문된 "" 정상제품과 부적합 제품의 차이는 무엇인가?"" 에 대한 정확한 답변을 기술합니다.") | N53: -Opis problemu W tej części raportu dokładnie odpowiedź na pytanie zawarte w dokumencie „QR Jaka jest różnica między dobrymi i złymi częściami”") | O53: -Descrierea problemei În această secțiune, un raport exact răspunsul la întrebarea în documentul QR „Care este diferența dintre părți bune și rele“") | P53: -Описание проблемы В этом разделе укажите точный ответ на вопрос в QR документа "" В чем разница между хорошими и плохими деталями "" ") | Q53: -คำอธิบายปัญหา ในส่วนนี้รายงานคำตอบของคำถามในเอกสาร QR ""อะไรคือความแตกต่างระหว่างงานดีและงานเสีย""") | R53: -Sorun Açıklaması Bu bölümde, ""iyi ve kötü parçaları arasındaki fark nedir"" QR belgesinde soruya tam olarak cevap rapor")
A54: [2] | B54: -4M The analysis is covering all factors according to the 4M: Machine, Method, Man and Material - MATERIAL: Material or components used for manufacturing, includes material for the product itself but also material used for the process (exemple: oil, chemic"&"al product to do an operation) - METHOD: Manufacturing and delivery process of the product including conditions, environment, method of work (work instructions), measurment methods... - MAN: Human factor involved in the process (example: trainings, valida"&"tion, seniority...) - MACHINE: Equipments, production tools, machine, poka-yoke, software... - When people are concerned by the issue (maintenance, assembly operator, testing operator…) the M Man must be systematically used to confirm the adaptation of th"&"e person to his job (magic square or equivalent)") | C54: -4 M L'analyse couvre tous les facteurs selon la 4M: Machine, méthode, homme et matériel - Matériel: Matériel ou composants utilisés pour la fabrication, comprend un matériau pour le produit lui-même, mais aussi du matériel utilisé pour le procédé (exemple"&": huile, produit chimique pour faire une opération) - Méthode: Procédé de fabrication et la livraison du produit, y compris les conditions, l'environnement, la méthode de travail (instructions de travail), les méthodes ajustages ... - MAN: Le facteur huma"&"in impliqué dans le processus (exemple: formation, validation, ancienneté ...) - MACHINE: Équipements, outils de production, machine, détrompeur, logiciel ... - Quand les gens sont concernés par la question (maintenance, opérateur montage, opérateur test "&"...) M L'homme doit être systématiquement utilisée pour confirmer l'adaptation de la personne à son travail (carré magique ou équivalent)") | D54: -4M A análise cobre todos os fatores de acordo com o 4M: Máquina, Método, Homem e Material - MATERIAL: Material ou componentes usados ​​na fabricação, inclui material para o próprio produto, mas também material usado para o processo (exemplo: óleo, produto"&" químico para fazer uma operação) - MÉTODO: Processo de fabricação e entrega do produto incluindo condições, ambiente, método de trabalho (instruções de trabalho), métodos de medição ... - HOMEM: Fator humano envolvido no processo (exemplo: treinamentos, "&"validação, senioridade ...) - MÁQUINA: Equipamentos, ferramentas de produção, máquina, poka-yoke, software ... - Quando as pessoas estão preocupadas com o problema (manutenção, operador de montagem, operador de teste ...) o M Man deve ser sistematicamente"&" usado para confirmar a adaptação da pessoa ao seu trabalho (quadrado mágico ou equivalente)") | E54: -4M El análisis está cubriendo todos los factores de acuerdo con la 4M: Machine, Método, Hombre y materiales - Material: el material o componentes utilizados para la fabricación, incluye material para el producto en sí, sino también el material utilizado p"&"ara el proceso (Ejemplo: aceite, producto químico para hacer una operación) - Método: fabricación y entrega proceso del producto, incluyendo condiciones, medio ambiente, método de trabajo (instrucciones de trabajo), los métodos de Measurment ... - MAN: El"&" factor humano involucrado en el proceso (por ejemplo: capacitación, validación, la antigüedad ...) - MÁQUINA: Equipos, herramientas de producción, máquina, Poka-Yoke, software ... - Cuando la gente está preocupada por el tema (de mantenimiento, montaje d"&"el operador, operador de pruebas ...) el hombre M debe ser utilizado sistemáticamente para confirmar la adaptación de la persona a su puesto de trabajo (cuadrado mágico o equivalente)") | F54: -4M 该分析从4M角度涵盖所有因素：机器，方法，人与材料 - 材料：用于生产的材料或零部件，包括产品自身的材料，还有用于过程的材料（例如：油，用于操作的化学试剂） - 方法：产品的生产和交付过程，包含条件、环境、工作方法（作业指导书），测量方法… - 人员：参与到过程中的人的因素（例如： 培训，认可，资历...） - 机器：设备，生产工装，机器，防错，软件… - 当人涉及到事件中时（维修人员，装配工人，测试工人...），人必须系统地用来确认他对工作的适应性（魔方四边形或者其它类似的） ") | G54: -4M Analýza pokrývá všechny faktory podle 4M: stroj (Machine), metoda (Method), člověk (Man) a materiál (Material) - MATERIAL Materiál nebo součástky použité pro výrobu. Zahrnuje finální výroběk sám o sobě, ale také materiál použitý v procesu výroby (např."&": olej, chemický prostředek provádějící operaci např. odmaštění, atd) - METHOD: Výrobní a logistické operace s výrobkem včetně vnějších podmínek, prostředí, způsobu práce (pracovní pokyny), měřící metody ... - MAN: Lidský faktor zapojený do procesu (příkl"&"ad: tréninky, potvrzení kvalifikace, délka zkušeností ...) - MACHINE: zařízení, výrobní nářadí, nástroje, stroje, poka-yoke, software ... - Když jsou v problému zapojení lidé (údržba, operátor montáže, operátor kontroly ...) M MAN (člověk) musí být využ"&"íváno systematicky k potvrzení adaptace člověka k jeho práci (magický čtverec nebo jeho ekvivalent)") | H54: -4M Die Analyse, die alle Faktoren nach der 4M: Maschine, Methode, Mensch und Material - MATERIAL: Material oder verwendete Komponenten zur Herstellung, beinhaltet das Material für das Produkt selbst, sondern auch Material für das Verfahren verwendet (exem"&"ple: Öl, chemisches Produkt eine Operation zu tun) - METHODE: Herstellung und Lieferprozess des Produkts einschließlich der Bedingungen, Umwelt, Art der Arbeit (Arbeitsanweisungen), Measurment Methoden ... - MAN: Der Faktor Mensch beteiligt in dem Prozess"&" (Beispiel: Schulungen, Validierung, Dienstalter ...) - MACHINE: Ausrüstungen, Produktionswerkzeuge, Maschinen, Poka-Yoke, Software ... - Wenn die Menschen durch die Ausgabe betroffen sind (Wartung, Montage Betreiber, Test Operator ...) die M Mann systema"&"tisch die Anpassung der Person, an seinen Job (magisches Quadrat oder ein Äquivalent) verwendet werden muss, um zu bestätigen,") | I54: -4M Az elemzés kiterjed az összes tényezőket a 4M: Machine, Method Man és anyag - Anyag: Anyag vagy komponensek gyártásához felhasznált, anyagát tartalmazza a termék maga, hanem használt anyag a folyamat (exemple: olaj, vegyipari termék, hogy nem egy művel"&"et) - módszer: Gyártási és szállítási folyamat a termék, beleértve a feltételeket, a környezet, a módszer a munka (munkautasítások) mérés módszerek ... - MAN: Az emberi tényező a folyamatban részt vevő (pl: tréningek, érvényesítés, szolgálati idő ...) - G"&"ÉP: berendezések, eszközök gyártása, gép, pokajoke, szoftverek ... - Amikor az emberek által érintett kérdés (karbantartási, szerelési üzemeltető tesztelés operátor ...) az M ember szisztematikusan kell használni, hogy erősítse meg az alkalmazkodás a szem"&"ély munkája (bűvös négyzet vagy azzal egyenértékű)") | J54: -4M Analisis ini mencakup semua faktor sesuai dengan 4M: Mesin, Method, Man dan Material - BAHAN: Bahan atau komponen yang digunakan untuk pembuatan, termasuk bahan untuk produk itu sendiri tetapi juga bahan yang digunakan untuk proses (contoh: minyak, pro"&"duk kimia untuk melakukan operasi) - METODE: Manufaktur dan proses pengiriman produk termasuk kondisi, lingkungan, metode kerja (instruksi kerja), metode pengukuran ... - MAN: Faktor manusia yang terlibat dalam proses (contoh: pelatihan, validasi, seniori"&"tas ...) - MESIN: Peralatan, alat produksi, mesin, poka-yoke, software ... - Ketika orang prihatin dengan masalah (maintenance, operator perakitan, pengujian Operator ...) M Manusia harus sistematis digunakan untuk mengkonfirmasi adaptasi orang untuk peke"&"rjaannya (sihir persegi atau setara)") | K54: -4M L'analisi copre tutti i fattori secondo le 4M: Macchina, Metodo, Manodopera e Materiale - MATERIALE: Materiale o componenti utilizzati per la produzione, inclusi i materiali per il prodotto ma anche il materiale usato per il processo (esempio: olio, pr"&"odotto chimico utilizzato durante un'operazione) - METODO: Processo di fabbricazione e spedizione del prodotto incluso condizioni, ambiente, metodo di lavoro (istruzioni di lavoro), metodi di misurazione... - MANODOPERA: Fattore umano coinvolto nel proces"&"so (esempio: formazione, validazione, esperienza...) - MACCHINA: Attrezzature, mezzi di produzione, macchina, poka-yoke, software... - Quando il personale è coinvolto nel problema (manutentore, operatore di linea, operatore addetto al controllo....) la M "&"Manodopera deve essere sistematicamente utilizzata per confermare la competenza della persona al suo lavoro (quadrato magico o equivalente)") | L54: -4M 分析は4Mに係る全ての要素をカバーしている事： - MATERIAL：材料又は製造に使用される部品、製造に必要な部品そのものに加えて、製造に必要は工程・副資材含む（オイル、薬品、その他製造に不可欠なアイテムなど） - METHOD：製造ならびに製品移送に係る方法、条件、環境、作業方法（作業指示書）、測定方法...など含め） - MAN：プロセスに関与する人的要因（例：トレーニング、スキル認証、経験...） - MACHINE：機器、製造ツール、機械、ポカヨケ、ソフトウェア... - "&"作業者が問題に対して憂慮している際には（保全、組立オペレーター、テストエンジニア...）彼らが業務遂行上適しているかを体系的に確認しなければならない（スキルグリッドあるいは類似のもの）") | M54: -4M 4M에 따른 모든 요소에 대해 분석을 합니다. : 설비, 방법, 사람, 재질 - 재질 : 제품, 부품의 제작에 사용된 원재료 및 생산과정중(오일, 화학원료 등) 사용되는 첨가물 - 방법 : 생산 조건, 환경, 작업 방법(작업 지시서), 측정 방법등을 포함한 생산과정의 제조, 이송 방법 등 - 사람 : 공정상 작업자 요인(교육, 인증, 경력 등) - 설비 : 장비, 생산 도구, 기계, 실수방지장치, 소프트웨어 등 - 문제가 ""사람"""&"과 연관이 있을 때(유지보수 작업자, 조립 작업자, 테스트 엔지니어 등), ""사람"" 이 그 작업 / 공정에 적절한지는 체계적인 방법으로 확인되어야 합니다.(매직 스퀘어 등)") | N54: -4M Analiza jest obejmujące wszystkie czynniki według 4M: automatyczna, Method Man i materialnej, - Materiały: Materiały i składniki stosowane do wytwarzania obejmuje materiał do samego produktu, lecz także materiały stosowane w procesie (exemple: naftowej"&", produktów chemicznych, aby wykonać operację) - METODA: Produkcja i dostawa Proces wyrobu w tym warunków, środowiska, sposobu pracy (instrukcje pracy) metod pomiarowych ... - MAN: Czynnik ludzki zaangażowany w proces (na przykład: szkolenia, walidacji, s"&"eniority ...) - maszyny: sprzęt, narzędzia produkcyjne, maszyny, Poka-Yoke, oprogramowanie ... - Kiedy ludzie są objęte emisji (technicznego, operator montaż, testowanie operatora ...) M Człowiek musi być systematycznie wykorzystywane w celu potwierdzenia"&" adaptację osoby do swojej pracy (magiczny kwadrat lub równoważny)") | O54: -4M Analiza acoperă toți factorii în funcție de 4M: Masina, Metoda, Om și material - MATERIAL: material sau componente utilizate pentru fabricarea, include materiale pentru produsul în sine, ci și materialul utilizat pentru procedeul (exemplul: ulei, produ"&"s chimic pentru a face o operație) - METODA: Fabricarea și livrarea de proces a produsului, inclusiv condițiile de mediu,, metoda de lucru (instructiuni de lucru), metode de masurare ... - MAN: factorul uman implicat în procesul (de exemplu: training-uri,"&" de validare, vechime ...) - MASINA: Echipamente, unelte de producție, mașini, Poka jug, software-ul ... - Când oamenii sunt preocupați de problema (întreținere, asamblare operatorul, operatorul de testare ...) Omul M trebuie să fie utilizat în mod sistem"&"atic pentru a confirma adaptarea persoanei la locul de muncă (pătrat magic sau echivalent)") | P54: -4M Анализ охватывает все факторы в соответствии с 4M: машина, метод Человек и материал - МАТЕРИАЛ: Материал или компоненты, используемые для изготовления, включает в себя материал для самого продукта, и материал, используемый для процесса (например: масл"&"о, химикаты необходимые для выполнения операции) - МЕТОД: процесс производства и доставки продукта, включая условия, окружающую среду, метод работы (рабочие инструкции), методы измерения ... - MAN: Человеческий фактор, участвующий в процессе (например, тр"&"енинги, проверки, старшинство ...) - МАШИНА: оборудование, инструменты производства, машина, Poka Yoke, программное обеспечение ... - Когда люди вовлечены в проблему (техническое обслуживание, оператор сборки, оператор тестирования ...) фактор М Человек д"&"олжен систематически использоваться для подтверждения адаптации человека к своей работе (магический квадрат или эквивалент)") | Q54: -4M การวิเคราะห์ครอบคลุมปัจจัยทั้งหมดตาม 4M: เครื่องจักรวิธีการคนและวัสดุ - วัสดุ: วัสดุหรือส่วนประกอบที่ใช้ในการผลิตรวมถึงวัสดุสำหรับผลิตภัณฑ์เอง แต่ยังรวมถึงวัสดุที่ใช้สำหรับกระบวนการ (ตัวอย่างเช่นน้ำมันผลิตภัณฑ์เคมีในการดำเนินการ) - METHOD: กระบวนการผ"&"ลิตและส่งมอบผลิตภัณฑ์รวมถึงเงื่อนไขสภาพแวดล้อมวิธีการทำงาน (คู่มือปฏิบัติงาน) วิธีการวัด ... - MAN: ปัจจัยมนุษย์ที่เกี่ยวข้องในกระบวนการ (ตัวอย่างเช่นการฝึกอบรมการตรวจสอบความอาวุโส ... ) - MACHINE: อุปกรณ์เครื่องมือในการผลิตเครื่องจักรโพก้าแอกซอฟแวร์ .."&". - เมื่อผู้คนมีความกังวลในปัญหา (การบำรุงรักษาผู้ประกอบการผู้ดำเนินการทดสอบ ... ) M Man จะต้องถูกใช้อย่างเป็นระบบเพื่อยืนยันการปรับตัวของบุคคลให้เข้ากับงานของเขา (สี่เหลี่ยมวิเศษหรือเทียบเท่า)") | R54: -4M Analiz 4M göre tüm faktörleri kapsayan: Makine, Yöntem, Man ve Malzeme - Materyal: (: bir işlem yapmak için yağ, kimyasal madde exemple) maddeler ya da imal edilmesi için kullanılan bileşenler, kendisi ürünün malzeme ama işlem için kullanılan aynı zama"&"nda malzeme içerir - Yöntem: koşulları, çevre, çalışma yöntemi (çalışma talimatları), ölçüm yöntemleri de dahil olmak üzere ürünün imalatı ve dağıtım işlemi ... - ADAM: sürecine dahil İnsan faktörü (örnek: eğitim, doğrulama, kıdem ...) - MAKİNE: Ekipmanla"&"r, üretim araçları, makine, poka-yoke, yazılım ... - insanlar sorundan açısından bakıldığında (bakım, montaj operatörü, operatörü test ...) M Adam sistematik işine (sihirli kare veya eşdeğeri) kişinin adaptasyonu onaylamak için kullanılmalıdır")
A55: [3] | B55: -Factors Any factor (such as process parameters, characteristics of a material, way to do an operation) linked to the issue must be recorded. In this section, nominate precisely the factor only (never qualify the factor as good, bad, big, small…): temperat"&"ure of the mould for instance To identify the factors: - Compare good and bad parts - Go to the genba, ask the operators - Use documents such as FMEAs, drawings, control plans, process / machine description, procedure/process steps... - Involve experts") | C55: -Facteurs Tout facteur (comme les paramètres du procédé, les caractéristiques d'un matériau, moyen de faire une opération) liée à la question doit être enregistré. Dans cette section, désigner précisément le seul facteur (jamais qualifier le facteur aussi "&"bon, mauvais, grand, petit ...): la température du moule, par exemple, Identifier les facteurs: - Comparer les bonnes et les mauvaises pièces - Aller à la Genba, demandez aux opérateurs - Utiliser des documents tels que AMDEC, dessins, plans de contrôle, "&"processus / description de la machine, la procédure / étapes du processus ... - Faire participer les experts") | D55: -Fatores Qualquer fator (como parâmetros de processo, características de um material, forma de fazer uma operação) vinculado ao problema deve ser registrado. Nesta seção, indique exatamente o fator apenas (nunca qualifique o fator como bom, ruim, grande, p"&"equeno ...): temperatura do molde, por exemplo Para identificar os fatores: - Compare as peças boas e ruins - Vá para o genba, pergunte aos operadores - Use documentos como FMEAs, desenhos, planos de controle, descrição do processo / máquina, procedimento"&" / etapas do processo ... - Envolva especialistas") | E55: -factores Cualquier factor (tales como parámetros de proceso, características de un material, forma de hacer una operación) vinculado a la cuestión debe ser registrada. En esta sección, nominar, precisamente, el único factor (nunca calificar el factor tan "&"bueno, malo, grande, pequeño ...): la temperatura del molde, por ejemplo, Para identificar los factores: - buenas y malas partes Comparar - Ir a la genba, solicitar a los operadores - Usar los documentos tales como FMEAs, dibujos, planes de control, proce"&"so / descripción de la máquina, procedimiento / pasos del proceso ... - Involucrar a los expertos") | F55: -因子 任何与事故相关的因子都必须被记录下来（例如工艺参数，材料特性，操作方法）。 在这一部分，仅仅只是准确指出因素（不鉴定因素好，坏，大，小）： 以模具温度为例 确定因子： - 比较好件和坏件 - 去现场，问操作工 - 使用文件例如FMEAs，图纸，控制计划，过程 / 机器描述，程序 / 过程步骤… - 专家介入") | G55: -Faktory Musí zde být zaznamenán jakýkoliv faktor spojený s problémem (např. procesní parametr, charakteristika materiálu, způsob provedení operace, atd). V této části vyjmenujte pouze faktory samé (nikdy neposuzujte faktor jako dobrý, špatný, velký, malý,"&" ...): například teplota formy (nepsat faktor ""nízká teplota formy"") K nalezení faktorů: - Srovnejte dobré a špatné díly - Jděte do genby, ptejte se operátorů - Používejte dokumenty jako je FMEA, výkresy, kontrolní plány, popis procesu/stroje, postup či"&"nosti/procesních kroky ... - zapojte odborníky-experty") | H55: -Faktoren Jeder Faktor für das Problem verknüpft (wie Prozessparameter, Eigenschaften eines Materials, Art und Weise eine Operation zu tun) müssen aufgezeichnet werden. In diesem Abschnitt nominiert genau den Faktor nur (nie den Faktor als gut, schlecht, g"&"roß, klein ... qualifizieren): Temperatur der Form zum Beispiel Um die Faktoren zu identifizieren: - Vergleichen Sie gute und schlechte Teile - Gehen Sie auf die Genba, fragen die Betreiber - Verwenden Sie Dokumente wie FMEAs, Zeichnungen, Kontrollpläne, "&"Prozess- / Maschinenbeschreibung, Verfahren / Prozessschritte ... - Beteiligen Experten") | I55: -tényezők Minden olyan tényező (például a technológiai paraméterek, jellemzők valamely anyag, módja, ha egy művelet) kapcsolódik a kérdést meg kell jegyezni. Ebben a részben jelöljenek pontosan az a tényező csak (nem minősül az a tényező, mint a jó, a ross"&"z, nagy, kicsi ...): A forma hőmérséklete például Ahhoz, hogy azonosítsa azokat a tényezőket: - Hasonlítsa össze a jó és a rossz részek - Menj a genba, kérje az üzemeltetők - Az iratok, például FMEA, rajzok, ellenőrzési tervek, folyamat / gép leírását, el"&"járás / eljárási lépések ... - Vonja szakértők") | J55: -faktor Faktor (seperti parameter proses, karakteristik dari bahan, cara untuk melakukan operasi) terkait dengan masalah tersebut harus dicatat. Pada bagian ini, mencalonkan justru faktor satu-satunya (tidak pernah lolos faktor sebagai baik, buruk, besar, "&"kecil ...): suhu cetakan misalnya Untuk mengidentifikasi faktor-faktor: - Bandingkan baik dan buruk bagian - Pergi ke Genba, tanyakan operator - Gunakan dokumen seperti meningkatkan FMEA, gambar, rencana pengendalian, proses / deskripsi mesin, prosedur / "&"langkah-langkah proses ... - Libatkan ahli") | K55: -Fattori Deve essere registrato ogni fattore (come i parametri di processo, le caratteristiche del materiale, il modo di fare un operazione) legato al problema. In questa sezione, nominare precisamente solo il fattore (mai qualificare il fattore come buono"&", catttivo, grande , piccolo...): la temperatura dello stampo per esempio Identificare i fattori: - Confrontare i pezzi buoni con quelli di scarto - Andare in officina, chiedere agli operatori - Utilizzare i documenti quali la FMEA, disegni, piani di co"&"ntrollo, descrizione del processo / macchina, fasi della procedura/processo - Coinvolgere gli esperti") | L55: -要因 問題に関係するすべての要因（例えば、プロセスパラメータ、材料特性、作業方法）は記録されなければならない。 このセクションでは、要因のみを正確に記載する事（要因が良い、悪い、大きい、小さいなどは不可）、例えば、金型温度についてもこれにあたる。 要因を特定するには： - 良品と不良品（良条件と不良条件）を比較 - genbaでオペレーターへ聞き込み - FMEA, 図面、コントロールプラン、工程/設備取扱い説明書、手順書、管理工程図などの書類を参照すること - 専門家を参加させること") | M55: -인자 문제와 관련된 모든 인자(공정 파라미터, 재질 특성, 작업 방법 등)이 모두 기록되어야 합니다. 본 항목에서는 안저만 정확하게 명기해야합니다.(인자의 품질 제외 - 좋음, 나쁨, 크다, 작다 등) 예를 들어 금형의 온도를 파악하려면, 아래의 인자들을 확인합니다. - Good Part 와 Bad Part 비교 - 현장방문, 작업자에게 질의 - 문서 확인(FMEA, 도면, Control plan, 공정 / 설비 설명자료, 공정순서 등) - 전문"&"가 참여 ") | N55: -czynniki Każdy czynnik, (takie jak parametry procesu, właściwości materiału, tak, aby wykonać operację) połączone z emisją musi być zarejestrowana. W tej sekcji precyzyjnie wyznaczyć współczynnik tylko (nie kwalifikuje się jako czynnik dobra, zła, duży, m"&"ały ...): temperatura formy, na przykład Zidentyfikować czynniki: - Porównaj dobrych i złych części - Przejść do genba, zapytać operatorów - Stosować dokumenty takie jak FMEAs, rysunków, planów kontroli, procesów / opis urządzenia, procedura / etapów proc"&"esu ... - Zaangażowanie ekspertów") | O55: -factori trebuie înregistrate orice factor (cum ar fi parametrii de proces, caracteristicile unui material, mod de a face o operație) legat de problema. În această secțiune, desemnează tocmai singurul factor (nu se califică factorul la fel de bun, rău, mar"&"e, mic ...): temperatura matriței, de exemplu, Pentru a identifica factorii: - piese Compară bune și rele - Du-te la Genba, cere operatorilor - Utilizați documente, cum ar fi FMEAs, desene, planuri de control, proces / descriere mașină, procedură / etape "&"de proces ... - Implicarea experților") | P55: -Факторы Любой фактор (например, параметры процесса, характеристики материала, способ выполнения операции), связанный с проблемой, должен быть записан. В этом разделе укажите только фактор (никогда не квалифицируйте фактор как хороший, плохой, большой, мал"&"енький…): например, температура формы Чтобы определить факторы: - Сравните хорошие и плохие детали - Сходите на генбу, спросите операторов - Используйте документы, такие как FMEA, чертежи, планы управления, описание процесса / машины, процедуры / этап"&"ы процесса ... - Привлеките специалистов ") | Q55: -ปัจจัย ต้องบันทึกปัจจัยใด ๆ (เช่นพารามิเตอร์กระบวนการลักษณะของวัสดุวิธีการดำเนินการ) ที่เชื่อมโยงกับปัญหา ในส่วนนี้ให้ระบุตัวประกอบอย่างแม่นยำเท่านั้น (ไม่ต้องถือว่าปัจจัยนั้นดีเลวใหญ่เล็ก ... ): อุณหภูมิของแม่พิมพ์เช่น เพื่อระบุปัจจัย: - เปรียบเทียบงา"&"นดีดีและงานเสีย - ไปที่ genba ถามโอเปอเรเตอร์ - ใช้เอกสารเช่น FMEAs, ภาพวาด, แผนการควบคุม, คำอธิบายกระบวนการ / เครื่องจักร, ขั้นตอน / ขั้นตอนกระบวนการ ... - มีส่วนร่วมกับผู้เชี่ยวชาญ") | R55: -Faktörler sorununa bağlı herhangi bir faktör (örneğin işlem parametreleri olarak, bir malzeme, bu arada özellikleri bir işlem yapmak için) kaydedilmelidir. Bu bölümde, sadece hassas faktör aday (faktörünü hak asla iyi, kötü, büyük, küçük ... gibi): Örneği"&"n kalıp sıcaklığı faktörleri belirlemek için: - Karşılaştırma iyi ve kötü parçalar - Genba gidin, operatörler sormak - Böyle FMEA'ları, çizimler, kontrol planları, süreç / makine açıklaması, prosedür / süreç adımları olarak kullanılacak olan belgelerin .."&". - uzmanlar dahil edin")
A56: [4] | B56: -CONTROL POINT The control point can be everywhere in the process including supplier, incoming inspection, process of assembly, final inspection, transportation. The answer cannot be """"NO CONTROL POINT"""". If control point was never defined before, ment"&"ion it and precise where and how the factor can be checked.""")
A57: [5] | B57: -Standard In this column, we must find the defined value of the factors, nominal value,its tolerances (Mininum & Maximum) and units . It can be the extract of a work instruction, the reference of master samples. Whatever it may be, it must be with facts an"&"d data or referenced to a clear nominated document that can be included in the analysis file. In this case, it must be precised. The answer cannot be "" NO STANDARD"" A standard may be not formalized but can be as a part of the culture.") | C57: -la norme Dans cette colonne, il faut trouver la valeur définie des facteurs, la valeur nominale, ses tolérances (Mininum et maximum) et les unités. Il peut être l'extrait d'une instruction de travail, la référence des échantillons de maître. Quoi qu'il en"&" soit, il doit être avec des faits et des données ou fait référence à un document nommé clair qui peut être inclus dans le fichier d'analyse. Dans ce cas, il doit être précisé. La réponse ne peut pas être « NO STANDARD » standard A peut être pas formalisé"&"e mais peut être aussi une partie de la culture.") | D57: -Padrão Nesta coluna, devemos encontrar o valor definido dos fatores, valor nominal, suas tolerâncias (mínimo e máximo) e unidades. Pode ser o extrato de uma instrução de trabalho, a referência de amostras padrões. Seja o que for, deve ser com fatos e dado"&"s ou referenciado a um documento nomeado claro que pode ser incluído no arquivo de análise. Neste caso, deve ser precisado. A resposta não pode ser ""SEM PADRÃO"". Um padrão pode não ser formalizado, mas pode ser parte da cultura.") | E57: -Estándar En esta columna, hay que encontrar el valor definido de los factores, el valor nominal, sus tolerancias (Mininum y máximo) y unidades. Puede ser el extracto de una instrucción de trabajo, la referencia de muestras maestras. Sea lo que sea, tiene "&"que ser con hechos y datos o se hace referencia a un documento nominado claro que se pueden incluir en el archivo de análisis. En este caso, hay que precisó. La respuesta no puede ser una norma ""NO ESTÁNDAR"" no puede ser formalizado, pero puede ser como"&" una parte de la cultura.") | F57: -标准 在此列中，我们须找到因子定义的值：规格值、公差（最小值 & 最大值）和单位。标准可以出自操作指导书，标准样件参考值。不管怎样，好件、坏件测量值及相应的标准要求或受控文件需要在FTA文件中列出，并且确保其准确性。 答案不可以是“无标准”，标准可能不是正式的，但可能是默认的不成文的规定。") | G57: -Standard V tomto sloupci musíme najít předepsanou hodnotu faktorů - jmenovitou hodnotu, její tolerance (minimální a maximální) a jednotky. Může být výtah z pracovní instrukce, referenční vzorků, výkresu, atd Ať už je zdrojem cokoliv, musí tato informace "&"být na základě faktů a dat nebo vztažená k jasně pojmenovaného dokumentu, který může být obsažen v souboru analýzy problému. V tomto případě musí být informace upřesněna. Odpověď nemůže být, že standard neexistuje - „NO STANDARD“ Standard může být nefor"&"mální (nepsaný), ale může být jako součást zvyku nebo kultury.") | H57: -Standard In dieser Spalte müssen wir den definierten Wert der Faktoren, Sollwert, seine Toleranzen (Mininum & Maximum) und Einheiten finden. Es kann der Extrakt einer Arbeitsanweisung sein, die Referenz von Urmuster. Was auch immer es sein mag, muss sie m"&"it Fakten und Daten sein oder zu einem klaren nominierten Dokument verwiesen wird, die in der Analysedatei aufgenommen werden kann. In diesem Fall muss es präzisierte werden. Die Antwort kann nicht „NO STANDARD“ Ein Standard kann nicht, kann formalisiert "&"werden, sondern als Teil der Kultur sein.") | I57: -Alapértelmezett Ebben az oszlopban, meg kell találni a megadott érték a tényezők, névérték, a tűrés (mininum & Maximum) és az egységek. Ez lehet a kivonat egy munkautasítás, a referencia-mester minták. Bármi is legyen az, meg kell a tényeket és adatokat, "&"vagy referencia egyértelmű jelölt dokumentumot, mely tartalmazza az elemzés fájlt. Ebben az esetben meg kell pontosítani. A válasz nem lehet „NEM STANDARD” A norma nem hivatalos, de lehet, mint a kultúra része.") | J57: -Standar Dalam kolom ini, kita harus menemukan nilai didefinisikan faktor, nilai nominal, toleransi nya (Mininum & Maksimum) dan unit. Hal ini dapat ekstrak dari instruksi kerja, referensi sampel induk. Apapun itu mungkin, itu harus dengan fakta dan data a"&"tau direferensikan ke dokumen nominasi yang jelas yang dapat dimasukkan dalam file analisis. Dalam hal ini, harus precised. Jawabannya tidak bisa ""NO STANDAR"" Sebuah standar mungkin tidak diformalkan tetapi dapat sebagai bagian dari budaya.") | K57: -Standard In questa colonna, dobbiamo trovare il valore definito dei fattori, valore nominale e la sua tolleranza. Può essere estratto dall'istruzione di lavoro, dal riferimento al campione master. Qualunque possa essere, deve essere riferito con fatti e d"&"ati ad un chiaro documento che può essere incluso nel file di analisi. In questo caso, deve essere precisato. La risposta non può essere ""NESSUNO STANDARD"". Uno standard può essere non formalizzato ma far parte della cultura.") | L57: -標準 このコラムでは、要因のさまざまな絶対値を見つけなければならない。ノミナル値、限界値（Minumm & Max）、単位など。それらは作業指示書からの引用、マスターサンプルの規定値など。何であれ、それらは事実とデータに基づく、あるいは、明確な参照資料であり分析ファイルに含まれるべき。その場合、正確に記載される事。 答えは「NO STANDARD」ではダメ。標準は書面化されていなくても慣習の一部として使用されている場合がある。") | M57: -표준 본 항목에서, 각 요소들 마다 정의된 값, 기준 값, 범위(최소 & 최대) 및 단위를 명기해야 합니다. 해당 항목은 작업 지시서 및 마스터 샘플에서 확인 할 수 있습니다. 어떤 경우에도, 해당 값들은 명확하게 명기된 문서에서 찾을 수 있는 ""사실"" / ""데이터"" / ""참고치"" 이어야 합니다. 해당 데이터는 명확해야 합니다. ""기준 없음""은 답이 될 수 없습니다. 기준은 정의되지 않았지만, 관례적으로 사용된 항목이 기준이 될 수 있습니"&"다.") | N57: -Standard W tej kolumnie, musimy znaleźć określoną wartość czynników, wartość nominalną, jego tolerancji (wymóg dostarczenia minimalnej i maksimum) i jednostek. Może to być wyciąg z instrukcji pracy, odniesienie do próbek wzorcowych. Cokolwiek to może być,"&" to musi być z faktami i danymi lub odwoływać się do jasnej nominowanych dokumentów, które mogą być zawarte w pliku analizy. W tym przypadku musi być sprecyzowane. Odpowiedź nie może być „NO STANDARD” standard A może nie być sformalizowane, ale może być j"&"ako część kultury.") | O57: -Standard În această coloană, trebuie să găsim valoarea definită a factorilor, valoarea nominală, toleranțele sale (Mininum & maxime) și unități. Acesta poate fi extractul de o instrucțiune de lucru, trimiterea probelor de master. Orice ar fi, trebuie să f"&"ie cu fapte și date sau se face referire la un document nominalizat clar că pot fi incluse în fișierul de analiză. În acest caz, trebuie să se precised. Răspunsul nu poate fi standard A „NU STANDARD“ poate să nu fie formalizată, dar poate fi ca o parte a "&"culturii.") | P57: -Стандарт В этом столбце мы должны найти определенное значение факторов, номинальное значение, его допуски (минимальный и максимальный) и единицы измерения. Это может быть вырезка из рабочей инструкции, ссылка на эталонный образец. Как бы то ни было, он до"&"лжен содержать факты и данные или ссылаться на четко обозначенный документ, который можно включить в файл анализа. В этом случае это должно быть уточнено. Ответом не может быть «НЕТ СТАНДАРТА». Стандарт может быть не формализован, но может быть частью кул"&"ьтуры.") | Q57: -มาตรฐาน ในคอลัมน์นี้เราต้องหาค่าที่กำหนดของปัจจัยค่าเล็กน้อยค่าความคลาดเคลื่อน (Mininum & Maximum) และหน่วย สามารถคัดมาจากคู่มือการปฏิบัติงานการอ้างอิงของตัวอย่างต้นแบบ ไม่ว่าจะเป็นอะไรก็ตามจะต้องมีข้อเท็จจริงและข้อมูลหรืออ้างอิงถึงเอกสารที่ได้รับการเสนอช"&"ื่อที่ชัดเจนซึ่งสามารถรวมอยู่ในไฟล์การวิเคราะห์ได้ ในกรณีนี้จะต้องมีความแม่นยำ คำตอบไม่สามารถเป็น ""NO STANDARD"" มาตรฐานอาจไม่เป็นทางการ แต่สามารถเป็นส่วนหนึ่งของวัฒนธรรมได้") | R57: -Standart Bu sütunda, faktör belirlenen değeri nominal değer olarak, tolerans (Mininum ve maksimum) ve birimleri bulmalıdır. Bu çalışma talimatı özü, ana örnekleri referans olabilir. o olabilir ne olursa olsun, gerçeklere ve verilere birlikte olmak veya an"&"aliz dosyasına dahil edilebilir net bir aday belgeye referans olmalıdır. Bu durumda, precised edilmelidir. Cevap ""HAYIR STANDART"" Standart bir resmileştirilmemişse edilebilir olamaz ama kültürünün bir parçası olarak olabilir.")
A58: [6] | B58: -FACTOR VALUE ON OK PARTS Based on the factor and the defined standard: - Values of the factor on good parts produced in the same process as the bad parts and when the problem happened or at least as close as possible of the time the problem happened - The"&" data or the facts must be directly comparable, same units, same calculation method. If factor concerns a manual operation, the operation is described to highlight the commonality and the differences.") | C58: -VALEUR SUR LE FACTEUR PIÈCES OK Basé sur le facteur et la norme définie: - Les valeurs du facteur sur les bonnes pièces produites dans le même processus que les mauvaises parties et quand le problème est survenu ou au moins aussi près que possible du mo"&"ment où le problème est arrivé - Les données ou les faits doivent être directement unités comparables, même, même méthode de calcul. Si le facteur concerne une opération manuelle, l'opération est décrite pour mettre en évidence les points communs et les "&"différences.") | D58: -VALOR DO FATOR EM PEÇAS OK Com base no fator e no padrão definido: - Valores do fator nas peças boas produzidas no mesmo processo das peças ruins e quando o problema aconteceu ou pelo menos o mais próximo possível do momento em que o problema aconteceu "&" - Os dados ou fatos devem ser diretamente comparáveis, mesmas unidades, mesmo método de cálculo. Se o fator diz respeito a uma operação manual, a operação é descrita para destacar a semelhança e as diferenças.") | E58: -PIEZAS DE FACTOR DE VALOR EN OK Con base en el factor y el estándar definido: - Los valores del factor de buenas piezas producidas en el mismo proceso que las partes malas y cuando ocurrió el problema o al menos lo más cerca posible de las veces el prob"&"lema sucedió - los datos o los hechos deben ser, mismas unidades directamente comparables, el mismo método de cálculo. Si el factor se refiere a una operación manual, el funcionamiento se describe a destacar el carácter común y las diferencias.") | F58: -好件的因子测量值 基于因子和定义的标准： - 当问题发生时，或尽可能的靠近问题发生时，与坏件相同的生产过程生产出来的好件的各因子测量值 - 数据或事实必须是直接可比的，相同的单位，相同的计算方法。如果因子涉及手动操作时，描述操作时应突出操作的共性和差异性") | G58: -HODNOTA FAKTORU NA OK DÍLU Založeno na faktoru a definovaném Standardu: - Hodnoty faktoru na dobrých dílech vyrobených ve stejném procesu jako špatné díly, a ve stejném čase kdy k problému došlo, nebo alespoň co nejblíže tomuto času. - údaje nebo fakta mu"&"sí být přímo srovnatelné - stejné jednotky, stejná metoda výpočtu. Pokud se faktor týká manuální operace, jsou v popisu oprace zvýrazněné jejich rozdíly a společné znaky.") | H58: -FACTOR Wert auf OK PARTS Basierend auf dem Faktor und dem definierten Standard: - Die Werte des Faktors auf gute Teilen in dem gleichen Verfahren wie die schlechten Teile hergestellt und wenn das Problem passiert ist oder zumindest so nahe wie möglich d"&"er Zeit das Problem geschah - Die Daten oder die Fakten müssen direkt vergleichbar, gleiche Einheiten, die gleiche Berechnungsmethode sein. Wenn Faktor eine manuelle Bedienung betrifft, wird der Vorgang beschrieben, um die Gemeinsamkeiten und die Untersc"&"hiede hervorzuheben.") | I58: -FAKTOR érték OK PARTS Ennek alapján a faktor és a meghatározott szabvány: - Az értékek a tényező a jó részek elő ugyanazt az eljárást, mint a rossz részeket, és ha a probléma történt, vagy legalábbis a lehető legközelebb az idő a probléma történt - az "&"adatok vagy a tényeket kell közvetlenül összehasonlítható, azonos egységek, azonos számítási módszer. Ha tényező vonatkozik kézi művelet, a művelet le, hogy kiemelje az egységesítés és a különbségeket.") | J58: -FAKTOR NILAI ON OK PARTS Berdasarkan faktor dan standar yang ditetapkan: - Nilai dari faktor pada bagian-bagian yang baik yang dihasilkan dalam proses yang sama seperti bagian yang buruk dan ketika masalah terjadi atau setidaknya sedekat mungkin dari wa"&"ktu masalah terjadi - Data atau fakta-fakta harus langsung dibandingkan, unit yang sama, metode perhitungan yang sama. Jika faktor menyangkut operasi manual, operasi dijelaskan untuk menyoroti kesamaan dan perbedaan.") | K58: -VALORE DEI FATTORI SUI PEZZI BUONI Con riferimento al singolo fattore a allo standard definito: - valori del fattore sui pezzi buoni prodotti nello stesso processo dei pezzi di scarto e quando è avvenuto il problema o almeno nel periodo più vicino possibi"&"le al periodo quando è avvenuto il problema. - dati e i fatti devono essere direttamente confrontabili, stesse unità, stesso metodo di calcolo. Se il fattore riguarda un'operazione manuale, l'operazione è descritta per evidenziare gli aspetti comuni e le "&"differenze.") | L58: -良品の要因に関する数値 要因ならびに特定された標準に基づいて： - 問題が発生した際と同じ時間に同じ工程で生産された良品について、その要因における数値を投入。最低でも問題が起こった時点に限りなく近い良品のデータを使う - データあるいは事実は必ず比較可能である事、同じ単位、同じ計算方法に基づく事。もし要因が手作業ラインに起因する場合、作業内容を共通要因と非共通要因に焦点をあてて記述する事") | M58: -정상 제품의 인자 값 정의된 인자 및 기준을 근거로 : - 문제가 발생한 시점 또는 문제가 발생한 시점과 가장 가까운 때에 문제 제품과 동일한 공정에서 생산된 정상 제품의 각 인자 별 값을 정의 - 데이터와 사실은 반드시 직접적으로 비교가 가능해야 합니다. ; 같은 단위, 같은 측정 방법 만약 인자가 수작업과 관련이 있다면, 작업 방법의 동일성 / 차이점을 명기해야 합니다. ") | N58: -FACTOR WARTOŚĆ na częściach OK Na podstawie współczynnika a określonym standardzie: - Wartości współczynnika na dobrych części produkowanych w tym samym procesie jako złych części i kiedy problem się lub przynajmniej jak najbliżej czasu pojawił się prob"&"lem - dane lub fakty należy bezpośrednio porównywalne, takie same jednostki, takiej samej metody. Jeśli czynnik dotyczy ręcznego, operacja jest opisana podkreślić zbieżności i różnice.") | O58: -FACTOR DE VALOARE PE PIESE OK Bazat pe factorul și standardul definit: - Valorile factorului de pe părțile bune produse în același proces ca și părțile rele și atunci când problema sa întâmplat sau cel puțin cât mai aproape de momentul în care problema "&"sa întâmplat - Datele sau faptele trebuie să fie aceleași unități în mod direct comparabile,, aceeași metodă de calcul. În cazul în care factorul se referă la o operație manuală, operația este descris pentru a evidenția diferențele și generalitatea.") | P58: -ФАКТОР ЗНАЧЕНИЯ НА ХОРОШИХ ДЕТАЛЯХ На основе фактора и определенного стандарта: - Значения фактора для хороших деталей, произведенных в том же процессе, что и плохая деталь, и когда возникла проблема, или, по крайней мере, как можно ближе к времени возник"&"новения проблемы - Данные или факты должны быть напрямую сопоставимы, одинаковые единицы измерения, одинаковый метод расчета. Если фактор касается ручной операции, операция описывается, чтобы выделить общие черты и различия. ") | Q58: -ปัจจัย VALUE ในชิ้นงานOK ขึ้นอยู่กับปัจจัยและมาตรฐานที่กำหนด: - ค่าของปัจจัยเกี่ยวกับชิ้นส่วนที่ดีที่ผลิตในกระบวนการเดียวกับชิ้นส่วนเสียและเมื่อปัญหาเกิดขึ้นหรืออย่างน้อยก็ใกล้เคียงที่สุดเท่าที่จะเป็นไปได้ของเวลาที่เกิดปัญหา - ข้อมูลหรือข้อเท็จจริงต้องเที"&"ยบเคียงกันโดยตรงหน่วยเดียวกันวิธีการคำนวณเดียวกัน หากปัจจัยเกี่ยวข้องกับการใช้งานด้วยตนเองการดำเนินการจะถูกอธิบายเพื่อเน้นความธรรมดาและความแตกต่าง") | R58: -FAKTÖR DEĞERİ ÜZERİNE TAMAM PARÇALARI faktörü ve tanımlanmış bir standarda göre: - Sorun ne zaman mümkün olduğunca yakın olarak kötü parçaları olarak ve ne zaman sorun olmuş ya da en azından aynı süreçte üretilen iyi parçalarda faktör değerlerini - ver"&"i ve bilgiler doğrudan karşılaştırılabilir, aynı birimler, aynı hesaplama yöntemi olmalıdır. faktör manuel işlem ilgiliyse, operasyon ortaklığı ve farklılıkları vurgulamak için anlatılmıştır.")
A59: [7] | B59: -FACTOR VALUE ON BAD PARTS Based on the factor and the defined standard: - Same comment than OK part - To be comparable the good parts and the bad parts must have the same background. For example, for warranty compare parts with the same mileage, same vehi"&"cule life.") | C59: -VALEUR FACTOR PIÈCES BAD Basé sur le facteur et la norme définie: - Même commentaire que partie OK - Pour être comparables les bonnes pièces et les pièces défectueuses doivent avoir le même arrière-plan. Par exemple, pour la garantie comparer les pièc"&"es avec le même kilométrage, même la vie de véhicule.") | D59: -VALOR DO FATOR EM PEÇAS RUINS Com base no fator e no padrão definido: - Mesmo comentário da peça OK - Para serem comparáveis, as peças boas e as peças ruins devem ter o mesmo background. Por exemplo, para garantia, compare peças com a mesma quilometragem,"&" a mesma vida útil do veículo.") | E59: -PARTS FACTOR VALOR EN BAD Con base en el factor y el estándar definido: - El mismo comentario que parte OK - Para ser comparables las partes buenas y malas las partes deben tener el mismo fondo. Por ejemplo, para la garantía comparar las piezas con el"&" mismo kilometraje, la vida misma vehiculo.") | F59: -坏件的因子测量值 基于因子和定义的标准： - 与好件是一样的描述 - 要比较的好件和坏件必须有相同的背景 例如，对于售后件，相同的里程，相同的车辆寿命") | G59: -HODNOTA FAKTORU NA ŠPATNÉM DÍLU Založeno na faktoru a definovaném Standardu: - Stejný komentář jako pro OK díl - Špatný a Dobrý díl musí mít stejné pozadí, aby je bylo možné srovnávat. Například: pro záruční reklamace z pole (Warranty) srovnejte díly se s"&"tejným počtem najetých kilometrů, stejným stářím vozidla, atd.") | H59: -Faktor-Wert ON PARTS BAD Basierend auf dem Faktor und dem definierten Standard: - gleicher Kommentar als OK Teil - Um vergleichbar guten Teile und die schlechten Teile müssen den gleichen Hintergrund haben. Zum Beispiel für Garantie vergleichen Teile "&"mit gleicher Laufleistung, gleichem Vehicule Leben.") | I59: -FAKTOR érték rossz részek Ennek alapján a faktor és a meghatározott szabvány: - Ugyanaz, mint a comment OK rész - Ahhoz, hogy összehasonlítható a jó részeket, és a rossz részeket meg kell egyeznie a háttérben. Például garanciális össze részeket azonos"&" futásteljesítmény, azonos járművel életet.") | J59: -FAKTOR NILAI BURUK PARTS Berdasarkan faktor dan standar yang ditetapkan: - komentar yang sama dari bagian OK - Untuk sebanding bagian yang baik dan bagian yang buruk harus memiliki latar belakang yang sama. Sebagai contoh, untuk garansi membandingkan "&"bagian dengan jarak tempuh yang sama, kehidupan vehicule yang sama.") | K59: -VALORE DEI FATTORI SUI PEZZI DI SCARTO Con riferimento al singolo fattore a allo standard definito: - Stessi commenti come per i pezzi buoni - Devono essere confrontabili i pezzi buoni e quelli di scarto e devono avere lo stesso background. Per esempio, p"&"er la garanzia confrontare i pezzi con la stessa percorrenza, stessa vita del veicolo.") | L59: -不良品の要因に関する数値 要因ならびに特定された標準に基づいて： - 良品と同様にコメントする - 比較する良品と不良品が同様の背景を持っている事。例えば、市場不具合品であれば、同じ走行距離、同じ車種、同じ経過年数である事が望ましい") | M59: -부적합 제품의 인자 값 정의된 인자 및 기준을 근거로 : - 정상 제품과 동일한 부분 확인 - 정상제품과 비교되는 부적합 제품(문제)는 반드시 정상제품과 동일한 조건을 갖추어야 합니다. 예를 들어, 워런티 파트를 검증시 같은 주행거리, 같은 차량 수명 등") | N59: -CZĘŚCI FACTOR WARTOŚĆ NA ZŁE Na podstawie współczynnika a określonym standardzie: - Ta sama uwaga niż OK części - Aby być porównywalne części dobrych i złych części muszą mieć takie samo tło. Na przykład, dla części z gwarancją porównać ten sam przebi"&"eg, samego życia terenowy.") | O59: -PIESE DE FACTORUL VALOARE PE RELE Bazat pe factorul și standardul definit: - Același comentariu decât o parte OK - Pentru a fi comparabile cu părțile bune și părțile rele trebuie să aibă același fond. De exemplu, pentru garanție compară piese cu acela"&"și kilometraj, aceeași viață VEHICULE.") | P59: -ФАКТОР ЗНАЧЕНИЯ НА ПЛОХИХ ДЕТАЛЯХ На основе фактора и определенного стандарта: - Тот же комментарий, как и для хорошей детали - Чтобы быть сопоставимыми, хорошие и плохие части должны иметь одинаковый фон. Например, для гарантийных проблем сравнивайте дет"&"али с одинаковым пробегом и одинаковым сроком службы автомобиля") | Q59: -ค่าปัจจัยในส่วนงานเสีย ขึ้นอยู่กับปัจจัยและมาตรฐานที่กำหนด: - ความคิดเห็นเดียวกันกับส่วน OK - การจะเทียบเคียงส่วนดีและส่วนเสียต้องมีความเป็นมาเหมือนกัน ตัวอย่างเช่นสำหรับการรับประกันเปรียบเทียบชิ้นส่วนที่มีระยะทางเท่ากันอายุการใช้งานรถเท่ากัน") | R59: -FAKTÖR DEĞERİ ÜZERİNE KÖTÜ PARÇALARI faktörü ve tanımlanmış bir standarda göre: - Tamam kısmı daha aynı açıklama - İyi parçaları karşılaştırılabilir olmak ve kötü parçalar aynı altyapıya sahip olmalıdır. Örneğin, garanti için aynı kilometre, aynı vehi"&"cule yaşamla parçaları karşılaştırın.")
A60: [8] | B60: -Good Part / Situation taken as reference Indicate traceability of Good Part and report this number for each data measured to know on which part measurement has been done") | C60: -Bonne partie / Situation pris comme référence Indiquez la traçabilité de la bonne partie et de faire rapport ce nombre pour chaque donnée mesurée à savoir sur lequel la mesure de la partie a été fait") | D60: -Peça boa / situação tomada como referência Indique a rastreabilidade da peça boa e relate este número para cada dado medido para saber em qual peça a medição foi feita") | E60: -Buena parte / Situación toma como referencia Indicar la trazabilidad de Buena parte e informar a este número para cada uno de los datos medidos a conocer en la que se ha realizado la medición parte") | F60: -作为参考的好件/好的状况 表明好件的追溯性，并记录每个测量数据的编号，便于知道哪些零件已经被测量了。") | G60: -Dobrý Díl / Situace braný jako referenční Popisuje sledovatelnost Dobrého dílu a tyto informace uveďte pro každá naměřená data, aby bylo vidět, na jakých dílech byly měření provedeny.") | H60: -Gutteil / Lage als Referenz genommen Geben Rückverfolgbarkeit von Gutteil und diese Nummer berichtet für alle Daten gemessen zu wissen, auf welchem ​​Teil Messung durchgeführt wurde") | I60: -Jó rész / szituáció vett referencia Jelölje meg a nyomon követhetőség a jó része, valamint ezt az szám az egyes mért adatok tudni, hogy melyik része mérés megtörtént") | J60: -Baik Bagian / Situasi diambil sebagai referensi Menunjukkan ketertelusuran Baik Bagian dan melaporkan nomor ini untuk setiap data yang diukur untuk mengetahui pada bagian mana pengukuran telah dilakukan") | K60: -Pezzo / Situazione Buono preso come riferimento Indicare la tracciabilità del Pezzo Buono e riferire a questo tutti i dati misurati per sapere in ogni momento a quali pezzi si riferisce la misura") | L60: -良品/良好な環境・条件を考慮する事 良品のトレーサビリティーを明示し、各データの数値を報告する事。これらは、どの測定が完了未完了であるかを知る為に必要") | M60: -정상 제품 / 환경 추적 정상 제품에 추적 식별번호 부여 및 각 측정 데이터에 해당 추적 식별번호 입력하여, 어떤 부품이 측정되었는지 표기 ") | N60: -Dobry Część / Sytuacja traktowane jako wzorce Wskazują identyfikowalność dobre strony i zgłosić ten numer dla każdego danych zmierzonych wiedzieć, w którym pomiar część została wykonana") | O60: -Partea bună / Situația luată ca referință Indicați trasabilitatea bună parte și să raporteze acest număr pentru fiecare date măsurate pentru a ști pe care a fost făcut de măsurare parte") | P60: -Хорошая деталь / ситуация, взятая за образец Укажите прослеживаемость хорошей детали и укажите этот номер для каждого измеренного значения, чтобы знать, для какой детали было выполнено измерение") | Q60: -งานดี / สถานการณ์นำมาเป็นข้อมูลอ้างอิง ระบุความสามารถในการตรวจสอบย้อนกลับของ งานดี และรายงานตัวเลขนี้สำหรับแต่ละข้อมูลที่วัดได้เพื่อให้ทราบว่ามีการวัดชิ้นส่วนใดบ้าง") | R60: -İyi Parça / Durum referans alınmıştır İyi Part izlenebilirliğini belirtin ve parça ölçümü yapılmıştır hangi bilmek ölçülen her veri için bu numarayı bildirmek")
A61: [9] | B61: -Bad Part / Situation taken as reference Indicate traceability of Bad Part and report this number for each data measured to know on which part measurement has been done") | C61: -Bad partie / Situation pris comme référence Indiquez la traçabilité de Bad partie et de faire rapport ce nombre pour chaque donnée mesurée à savoir sur lequel la mesure de la partie a été fait") | D61: -Peça ruim / situação tomada como referência Indique a rastreabilidade da peça defeituosa e relate este número para cada dado medido para saber em qual peça a medição foi feita") | E61: -Parte mala / Situación toma como referencia Indicar la trazabilidad de Bad Parte e informar a este número para cada uno de los datos medidos a conocer en la que se ha realizado la medición parte") | F61: -作为参考的坏件/坏的状况 表明坏件的追溯性，并记录每个测量数据的编号，便于知道哪些零件已经被测量了。") | G61: -Špatný Díl / Situace braný jako referenční Popisuje sledovatelnost Špatného dílu a tyto informace uveďte pro každá naměřená data, aby bylo vidět, na jakých dílech byly měření provedeny.") | H61: -Bad Teile- / Lage als Referenz genommen Geben Sie die Rückverfolgbarkeit von Bad Teil und diese Nummer berichtet für alle Daten gemessen zu wissen, auf welchem ​​Teil Messung durchgeführt wurde") | I61: -Bad rész / szituáció vett referencia Jelölje meg a nyomon követhetőség Bad rész, valamint ezt az szám az egyes mért adatok tudni, hogy melyik része mérés megtörtént") | J61: -Bad Bagian / Situasi diambil sebagai referensi Menunjukkan ketertelusuran Bad Bagian dan melaporkan nomor ini untuk setiap data yang diukur untuk mengetahui pada bagian mana pengukuran telah dilakukan") | K61: -Pezzo / Situazione Scarto preso come riferimento Indicare la tracciabilità del pezzo di scarto e riferire a questo tutti i dati misurati per sapere in ogni momento a quali pezzi si riferisce la misura") | L61: -不良品・不良な環境・条件を考慮する事 不良品のトレーサビリティーを明示し、各データの数値を報告する事。これらは、どの測定が完了未完了であるかを知る為に必要") | M61: -부적합 제품 / 환경 추적 부적합 제품에 추적 식별번호 부여 및 각 측정 데이터에 해당 추적 식별번호 입력하여, 어떤 부품이 측정되었는지 표기") | N61: -Bad Część / Sytuacja traktowane jako wzorce Wskazują identyfikowalność złe strony i zgłosić ten numer dla każdego danych zmierzonych wiedzieć, w którym pomiar część została wykonana") | O61: -Bad partea / Situația luată ca referință Indicați trasabilitatea Bad partea și să raporteze acest număr pentru fiecare date măsurate pentru a ști pe care a fost făcut de măsurare parte") | P61: -Плохая деталь / ситуация, взятая за образец Укажите прослеживаемость плохой детали и укажите этот номер для каждого измеренного значения, чтобы знать, для какой детали было выполнено измерение") | Q61: -งานเสีย / สสถานการณ์ที่ใช้เป็นข้อมูลอ้างอิง ระบุความสามารถในการตรวจสอบย้อนกลับของ งานเสีย และรายงานตัวเลขนี้สำหรับแต่ละข้อมูลที่วัดได้เพื่อให้ทราบว่ามีการวัดชิ้นส่วนใดบ้าง") | R61: -Kötü Parça / Durum referans alınmıştır Kötü Bölüm izlenebilirliğini belirtin ve parça ölçümü yapılmıştır hangi bilmek ölçülen her veri için bu numarayı bildirmek")
A62: [10] | B62: -Judgement - Standard OK? A standard is OK if the parameter is clearly defined with tolerances. This includes the way the standard is checked, frequency of measurement, method of measurement… To say standard is OK means that NO action is required to change"&" or to improve the standard or the way to check it. To say the standard is OK means also that applying the standard we obtain good parts.") | C62: -Jugement - Standard OK? Une norme est OK si le paramètre est clairement défini avec des tolérances. Cela comprend la manière dont la norme est activée, la fréquence des mesures, la méthode de mesure ... Dire la norme est OK signifie que l'action NO est né"&"cessaire pour modifier ou améliorer la norme ou la façon de le vérifier. Dire la norme est OK signifie également que l'application de la norme que nous obtenons de bonnes pièces.") | D62: -Julgamento - Padrão OK? Um padrão está OK se o parâmetro for claramente definido com tolerâncias. Isso inclui a forma como o padrão é verificado, frequência de medição, método de medição ... Dizer que o padrão está OK significa que NENHUMA ação é neces"&"sária para alterar ou melhorar o padrão ou a forma de verificá-lo. Dizer que o padrão está OK significa também que aplicando o padrão, obtemos peças boas.") | E62: -Juicio - Estándar OK? Un estándar es OK si el parámetro está claramente definido con tolerancias. Esto incluye la forma en que se comprueba el estándar, la frecuencia de medición, método de medición ... Decir estándar es OK medios que no se requiere ningu"&"na acción para cambiar o mejorar el nivel o la forma de comprobarlo. Decir que el estándar es OK medios también que la aplicación de la norma obtenemos partes buenas.") | F62: -判断 - 标准OK？ 标准是OK的，如果该参数被清楚地定义了，并且有公差。 这包括标准的检查方式，测量频率，测量方法... 如果说标准是OK的，表示不需要采取行动措施去改变或改善该标准或其检查方式。 如果说标准是OK的，也意味应用该标准，我们能够获得好的产品。") | G62: -Rozhodnutí- Standard OK? Standard je v pořádku, pokud je parametr jasně definován včetně tolerancí. To zahrnuje způsob, jakým se Standard kontroluje, četnost měření, způsob měření ... Prohlášení ""Standard je OK"" znamená, že není potřeba provést žádnou a"&"kci vedoucí ke změně nebo ke zlepšení standardu, nebo způsobu, jak ho kontrolovat. Prohlášení ""Standard je OK"" také znamená, že uplatňováním tohoto standardu dosáhneme dobrých dílů / situace.") | H62: -Urteil - Standard OK? Ein Standard ist OK, wenn der Parameter eindeutig mit Toleranzen definiert ist. Dazu gehört auch die Möglichkeit, der Standard überprüft wird, die Häufigkeit der Messung, Meßmethode ... Zu sagen, Standard OK Mittel ist, dass keine Ma"&"ßnahmen zur Änderung erforderlich sind oder den Standard oder die Art und Weise zu verbessern, um sie zu überprüfen. Zu sagen, dass die Standard-OK Mittel ist auch, dass die Standard-Anwendung wir gute Teile erhalten.") | I62: -Ítélet - Normál OK? A standard OK, ha a paraméter egyértelműen meghatározott tűréssel. Ez magában foglalja az utat a standard be van jelölve, a mérési frekvencia, mérési módszer ... Ha azt mondjuk, szabvány OK azt jelenti, hogy nincs szükség további lépés"&"ekre a változás, vagy hogy javítsa a szabvány vagy az út, hogy ellenőrizze azt. Ha azt mondjuk, a szabvány OK segítségével azt is, hogy az előírásoknak megkapjuk a jó részek.") | J62: -Penghakiman - Standard OK? Sebuah standar OK jika parameter yang jelas dengan toleransi. Ini termasuk cara standar tersebut akan diperiksa, frekuensi pengukuran, metode pengukuran ... Untuk mengatakan standar OK berarti bahwa NO tindakan yang diperlukan u"&"ntuk mengubah atau meningkatkan standar atau cara untuk memeriksa. Untuk mengatakan standar adalah OK berarti juga bahwa menerapkan standar kita memperoleh bagian yang baik.") | K62: -Giudizio - Standard OK? Uno standard è OK se il parametro è chiaramente definito con tolleranze. Questo include il modo in cui lo standard è controllato, la frequenza di misurazione, metodo di misura... Affermare che lo standard è OK significa che non è n"&"ecessaria NESSUNA azione per cambiare o migliorare lo standard o il modo di controllarlo. Affermare che lo standard è OK significa anche che applicando lo standard otteniamo pezzi buoni.") | L62: -判断 - 標準はOKか？ パラメーターが交差とともに明確に定義されていれば標準はＯＫ。ここには、標準が確認される方法や、測定頻度、測定方法などが含まれる。標準がＯＫという意味は、アクションが不要という事ではなく、場合によっては標準あるいは測定方法の改善が必要な場合もある。標準がＯＫという意味は、良品の確保方法が標準に則っているとう事でもある。") | M62: -판정 - 표준 OK? 각 파라미터와 공차가 명확하게 정의되어 있으면, 표준은 정상 입니다. 이 항목은, 어떻게 각 표준을 확인하는지, 측정 주기, 측정 방법 등을 포함합니다. 표준이 정상이라는 것은 표준 및 표준의 측정(확인) 방법 등의 변경 또는 개선이 불필요한 것을 의미하고 또한 해당 표준을 적용하였을 경우 정상제품을 생산 할 수 있는 것을 의미합니다.") | N62: -Wyrok - Standardowy OK? Norma jest OK, jeśli parametr jest jasno określony z tolerancją. Obejmuje to sposób średnia jest zaznaczone, częstotliwość pomiarów, metody pomiaru ... Powiedzieć standard jest OK, że środki nie są wymagane żadne działania w celu z"&"miany lub poprawy standardu lub sposób aby to sprawdzić. Muszę powiedzieć, że standard jest OK oznacza również, że zastosowanie standardu otrzymujemy dobre części.") | O62: -Hotărârea - Standard OK? Un standard este OK dacă parametrul este clar definit cu toleranțe. Aceasta include modul în care este verificat standardul, frecvența de măsurare, metoda de măsurare ... Pentru a spune standard este OK înseamnă că este necesară o"&" acțiune NO pentru a schimba sau pentru a îmbunătăți standardul sau modul de a verifica. Pentru a spune standardul este OK înseamnă, de asemenea, că aplicarea standardului obținem părți bune.") | P62: -Суждение - стандарт OK? Стандарт является приемлимым, если параметр четко определен с допусками. Это включает в себя способ проверки стандарта, частоту измерения, метод измерения… Сказать, что стандарт ОК, означает, что НЕ требуется никаких действий для и"&"зменения или улучшения стандарта или способа его проверки. Сказать, что стандарт ОК, означает также, что, применяя стандарт, мы получаем хорошие детали ") | Q62: -การตัดสิน - มาตรฐาน OK? มาตรฐานคือตกลงถ้าพารามิเตอร์ที่กำหนดไว้อย่างชัดเจนกับความคลาดเคลื่อน ซึ่งรวมถึงวิธีการที่มาตรฐานการตรวจสอบความถี่ของการวัดวิธีการวัด ... ที่จะบอกว่ามาตรฐานคือวิธีตกลงว่าการกระทำไม่จำเป็นต้องมีการเปลี่ยนแปลงหรือการปรับปรุงมาตรฐานหรื"&"อวิธีการที่จะตรวจสอบ ที่จะบอกว่ามาตรฐานคือวิธีตกลงว่าใช้มาตรฐานที่เราได้รับส่วนที่ดี") | R62: -Yargı - Standart tamam mı? Parametre açıkça toleranslarla tanımlanmış ise standart bir ok. Bu standard kontrol edilir şekilde, ölçme sıklığı, ölçüm yöntemi de içerir ... Standart YOK eylem değişikliğine gereklidir veya standart veya kontrol yolunu gelişti"&"rmek için bu Tamam demektir olduğunu söylemek için. Standart biz iyi parçalar elde standardın uygulanması olduğunu da tamam demektir olduğunu söylemek için.")
A63: [11] | B63: -Judgement - Meet the standard ? To answer to this question, check if you have respected the standard to produce the BAD part. - If you have respected the standard and you have produced bad parts, and if to produce good parts you have not respected the sta"&"ndard, then STANDARD OK is NO and MEET THE STANDARD is YES. - If you have not respected the standard and you have produced bad parts and to produce good parts you have respected the standard, then STANDARD OK is YES and MEET THE STANDARD is NO.") | C63: -Jugement - Satisfaire à la norme? Pour répondre à cette question, vérifier si vous avez respecté la norme pour produire la partie BAD. - Si vous avez respecté la norme et que vous avez produit des pièces défectueuses, et si pour produire de bonnes pièces "&"que vous ne l'avez pas respecté la norme, STANDARD OK est NON et conforme à la norme est OUI. - Si vous ne l'avez pas respecté la norme et que vous avez produit des pièces défectueuses et de produire de bonnes pièces que vous avez respecté la norme, STAND"&"ARD OK est OUI et la norme est MEET NO.") | D63: -Julgamento - Atende ao padrão? Para responder a esta pergunta, verifique se você respeitou o padrão para produzir a peça RUIM. - Se você respeitou o padrão e produziu peças ruins, e se para produzir peças boas você não respeitou o padrão, então PADRÃO O"&"K é NÃO e ATENDE AO PADRÃO é SIM. - Se você não respeitou o padrão e produziu peças ruins e para produzir peças boas você respeitou o padrão, então PADRÃO OK é SIM e ATENDER O PADRÃO é NÃO.") | E63: -Juicio - Conoce la norma? Para responder a esta pregunta, compruebe si ha respetado el estándar para producir la parte mala. - Si ha respetado la norma y que ha producido partes malas, y si a producir buenas piezas que no han respetado la norma, a continu"&"ación, bien estándar es NO y cumplir con el estándar es sí. - Si no se ha respetado la norma y que ha producido partes malas y para producir buenas piezas que han respetado la norma, a continuación, bien estándar es SÍ y satisfacer las normas es NO.") | F63: -判断 - 符合标准？ 要回答这个问题，检查是否尊守了标准来生产的坏件。 - 如果你尊守了标准，但生产出来了坏件，你没有遵守标准却生产出了好件，那么标准是否OK，判断为“NO”，是否遵守了标准，判断为“YES” - 如果你没有尊守标准，并且生产出了坏件，你遵守标准，就生产出了好件，那么标准是否OK，判断为“YES”，是否遵守了标准，判断为“NO”") | G63: -Rozhodnutí - Splňujeme standard? Chcete-li odpovědět na tuto otázku, zkontrolujte, zda jste splnili standard při výrobě ŠPATNÉHO Dílu. - Pokud jste byli v souladu se Standardem a přitom jste vyrobili ŠPATNÉ Díly, a k výrobě DOBRÝCH Dílů bylo třeba porušit"&" STANDARD, tak odpověď na STANDARD OK? je NE a SPLŇUJEME STANDARD? je ANO. - Pokud jste nerespektovali Standard a výsledkem jsou ŠPATNÉ díly a k výrobě DOBRÝCH dílů je nutné respektovat Standard, pak odpověď na otázku STANDARD OK? zní ANO a SPLŇUJEME STA"&"NDARD? je NE") | H63: -Urteil - Meet the Standard? Zur Beantwortung Prüfung auf diese Frage, wenn Sie den Standard eingehalten haben den schlechten Teil zu produzieren. - Wenn Sie den Standard eingehalten haben, und Sie haben schlechte Teile produziert, und wenn gute Teile zu p"&"roduzieren haben Sie den Standard nicht eingehalten, dann ist STANDARD OK NO und MEET THE STANDARD JA ist. - Wenn Sie den Standard nicht eingehalten haben, und Sie haben schlechte Teile produziert und gute Teile produzieren Sie den Standard eingehalten ha"&"ben, dann ist STANDARD OK JA und MEET THE STANDARD NEIN.") | I63: -Ítélete - Meet a standard? A választ erre a kérdésre, akkor ellenőrizze, hogy betartotta a szabvány, hogy készítsen a rossz része. - Ha betartják a standard, és még elő a rossz alkatrészeket, és ha termelni jó részek már nem tartják a standard, majd STAND"&"ARD OK NEM és megfelelnek a szabványnak IGEN. - Ha nem tartják be a standard, és még elő rossz részeket és előállítani a jó részeket, betartották a standard, majd STANDARD OK IGEN és megfelelnek a szabványnak NEM.") | J63: -Penghakiman - Bertemu standar? Untuk menjawab pertanyaan ini, cek jika Anda telah dihormati standar untuk menghasilkan bagian BAD. - Jika Anda telah dihormati standar dan Anda telah menghasilkan bagian yang buruk, dan jika untuk menghasilkan bagian-bagian"&" yang baik Anda tidak menghormati standar, maka STANDARD OK adalah NO dan MEET THE STANDARD adalah YA. - Jika Anda belum dihormati standar dan Anda telah menghasilkan bagian yang buruk dan untuk menghasilkan bagian-bagian yang baik Anda telah dihormati st"&"andar, maka STANDARD OK adalah YA dan MEET THE STANDARD adalah NO.") | K63: -Giudizio - lo standard è soddisfatto? Per rispondere a questa domanda, controlla se hai rispettato lo standard per produrre il pezzo di SCARTO. - Se hai rispettato lo standard e hai prodotto pezzi di scarto, e se per produrre pezzi buoni non hai rispettat"&"o lo standard, allora lo STANDARD OK è NO e lo STANDARD E? SODDISFATTO è SI. - Se non hai rispettato lo standard e hai prodotto pezzi di scarto e prodotto pezzi buoni rispettando lo standard, allora STANDARD OK è SI e SODDISFA LO STANDARD è NO.") | L63: -判断 - 標準に適合しているか？ 質問に回答する為、不良品が生産された際に標準が守られていたかの確認をする事。 - もし、不良品が生産された際に標準が守られており、良品が生産された際に標準が守られていなかった場合は、「標準はＯＫ］は「ＮO」であり、「標準に則っている」は「ＹＥＳ」となる。 - もし、不良品が生産された際に標準が守られておらず、良品が生産された際に標準が守られていた場合は、「標準はＯＫ」は「ＹＥＳ］で「標準に則っている」は「ＮＯ］となる。") | M63: -판정 - 표준 준수? 질문의 답변을 위해서는, 부적합 제품이 해당 표준을 준수하였는지 확인해야 합니다. - 표준을 따를 경우 부적합 제품이 생산되고, 따르지 않았을 경우 정상 제품이 생산되면 ""표준 OK"" 는 ""아니요"" / ""표준 준수"" 는 ""예""로 표기 합니다. - 표준을 따르지 않을 경우 부적합 제품이 생산되고, 따를 경우 정상 제품이 생산되면 ""표준 OK"" 는 ""예"" / ""표준 준수"" 는 ""아니요""로 표기합니다.") | N63: -Wyrok - Meet standard? Aby odpowiedzieć na to pytanie, sprawdź czy masz przestrzegane standardy do produkcji części źle. - Jeśli przestrzegane normy i dały złe części, a jeśli produkować dobre części nie są przestrzegane standardy, to jest OK STANDARD NO "&"oraz spełniać standardy brzmi TAK. - Jeśli nie przestrzegają standardów i zostały wyprodukowane złych części i produkować dobre części zostały przestrzegane standardy, a następnie STANDARD OK TAK oraz spełniać standardy brzmi NIE.") | O63: -Judecata - Faceți cunoștință cu standardul? Pentru a răspunde la această întrebare, verificați dacă ați respectat standardul de a produce partea rea. - Dacă ați respectat standardul și ați produs piese rele, și în cazul în care pentru a produce piese bune"&" pe care nu ați respectat standardul, apoi STANDARD OK este NO și să respecte standardul este DA. - Dacă nu ați respectat standardul și ați produs piese rele și pentru a produce piese bune pe care le-au respectat standardul, apoi STANDARD OK este DA și să"&" respecte standardul este NR.") | P63: -Суждение - соответствие стандарту? Чтобы ответить на этот вопрос проверьте, соблюдаете ли вы стандарт для производства плохой детали. - Если вы соблюдали стандарт и производили плохие детали, и если для производствахороших деталей вы вынуждены не соблю"&"дать стандарт , то СТАНДАРТ ОК - НЕТ, а СОБЛЮДЕНИЕ СТАНДАРТА - ДА. - Если вы не соблюдаете стандарт и производите плохие детали, а для производства хороших деталей вы соблюдаете стандарт, тогда СТАНДАРТ ОК - ДА, а СОБЛЮДЕНИЕ СТАНДАРТА - НЕТ .") | Q63: -การตัดสิน - พบมาตรฐานหรือไม่? เพื่อที่จะตอบคำถามนี้ให้ตรวจสอบว่าคุณได้รับการเคารพมาตรฐานในการผลิตงานเสีย - หากคุณเคารพในมาตรฐานและคุณได้ผลิตงานเสียและหากในการผลิตงานดีแต่คุณยังไม่เคารพมาตรฐาน, จากนั้น STANDARD OK คือ NO (ไม่ใช่) และ MEET THE STANDARD คือ"&" YES (ใช่) - หากคุณไม่เคารพมาตรฐานและคุณได้ผลิตงานเสียและในการผลิตงานดีที่คุณได้รับการยอมรับมาตรฐานนั้น จากนั้น STANDARD OK คือ YES (ใช่) และ MEET THE STANDARD iคือ NO (ไม่ใช่) .") | R63: -Yargı - Tanışma standart? Eğer kötü bir kısmını üretmek için standart saygı varsa, bu soruya çeki cevaplamak için. - Eğer standart saygı duydum ve kötü yanları ürettiler ve iyi parçalar üretmek için eğer standart saygı varsa, o zaman STANDART Tamam HAYIR "&"ve TANIŞIN STANDART EVET olmasıdır. - Eğer standart saygı yok ve kötü yanları ürettiler ve saygı var standardını iyi parçalar üretmek için, o STANDART Tamam EVET ve TANIŞIN STANDART HAYIR.")
A64: [12] | B64: -Judgement - Direct link ? - If to produce GOOD and BAD parts you have used exactly the same standard with same result your answer is NO direct link. The distribution of the values for good and bad parts inside the tolerance of the standard must be conside"&"red to confirm if the standard is OK or not. - If the comparizon shows clearly a difference between GOOD and BAD parts, your answer should be YES. If your answer is NO, explain why in the column ""Comments"". - Your answer may be D (doubt) when you are fa"&"cing to factors interfering on each other, in this case, deeper analysis is requested. - Identified potential causes must be confirmed by the reproduction of the defect. - If the answer is NO or doubt, standard must be clarified even if there is no direc"&"t link with the problem under analysis.") | C64: -Jugement - Lien direct? - Si pour produire le produit et les pièces BAD vous avez utilisé exactement la même norme avec le même résultat que votre réponse est pas de lien direct. La répartition des valeurs de bonnes et de mauvaises pièces à l'intérieur de"&" la tolérance de la norme doit être considérée pour confirmer si la norme est OK ou non. - Si les émissions de comparizon clairement une différence entre bonne et mauvaise, votre réponse doit être OUI. Si votre réponse est NON, expliquer pourquoi dans la "&"colonne « Commentaires ». - Votre réponse est peut-être D (doute) lorsque vous faites face à des facteurs qui interfèrent les uns des autres, dans ce cas, est demandé une analyse plus approfondie. - Les causes identifiées potentielles doivent être confirm"&"ées par la reproduction du défaut. - Si la réponse est NON ou de doute, la norme doit être clarifiée, même s'il n'y a pas de lien direct avec le problème en cours d'analyse.") | D64: -Julgamento - Link direto? - Se para produzir peças BOAS e RUINS você usou exatamente o mesmo padrão com o mesmo resultado sua resposta NÃO é link direto. A distribuição dos valores para peças boas e ruins dentro da tolerância do padrão deve ser considerad"&"a para confirmar se o padrão está OK ou não. - Se a comparação mostrar claramente uma diferença entre as peças BOAS e RUINS, sua resposta deve ser SIM. Se sua resposta for NÃO, explique o motivo na coluna ""Comentários"". - Sua resposta pode ser D (dúvida"&") quando você se depara com fatores que interferem um no outro, neste caso, uma análise mais profunda é necessária. - As causas potenciais identificadas devem ser comprovadas pela reprodução do defeito. - Se a resposta for NÃO ou dúvida, a norma deve ser "&"esclarecida mesmo que não haja ligação direta com o problema em análise.") | E64: -Juicio - Enlace directo? - Si a buenos productos y partes malas que ha usado exactamente de la misma serie con mismo resultado que su respuesta es NO enlace directo. La distribución de los valores de las piezas buenas y malas dentro de la tolerancia de la"&" norma debe ser considerado para confirmar si el nivel es correcto o no. - Si en la pantalla comparizon claramente una diferencia entre el bien y partes malas, su respuesta debe ser sí. Si su respuesta es NO, explique por qué en la columna ""Comentarios"""&". - Su respuesta puede ser D (duda) cuando se enfrentan a factores que interfieren el uno del otro, en este caso, se solicita un análisis más profundo. - causas potenciales identificados deben ser confirmadas por la reproducción del defecto. - Si la respu"&"esta es NO o duda, norma debe aclararse incluso si no hay un vínculo directo con el problema bajo análisis.") | F64: -判断 - 直接相关？ - 如果好件和坏件，使用的是完全相同的标准，有相同的结果，那么是否直接相关，判断为“NO” 在标准的公差范围内的针对于好件和坏件的数值的分布必须要考虑到，以用来确认标准是否是OK的 - 如果对比时，清楚地显示出好件和坏件之间的差异，那么是否直接相关，判断为“YES”。如果答案是“NO”，在“注释栏”解释为什么 - 当面对因素互相之间干扰时答案也许是D（怀疑），在这种情况下，要求更深入的分析 - 识别出的潜在原因必须经过故障再现来确认 - 如果答案是“NO”或者怀疑，标准必须"&"明确，即使对于还在还在分析的问题没有直接关联") | G64: -Rozhodnutí - Přímá souvislost? - Jestliže jste k výrobě dobrých a špatných dílů použili přesně stejný Standard se stejným stavem (hodnotou) Standardu, pak je odpověď, že zde není přímá souvislost faktoru s problémem. Rozložení hodnot pro dobré a špatné dí"&"ly uvnitř tolerančního pole Standardu musí být považováno za vyhovující, jestliže je nebo není Standard v pořádku. - Pokud porovnání jasně ukazuje rozdíl mezi DOBRÝMI a ŠPATNÝMI díly, vaše odpověď by měla být ANO - je zde přímá souvislost mezi Faktorem a "&"Problémem. Pokud je vaše odpověď NE, vysvětlite proč ve sloupci „Poznámky“. - Vaše odpověď může být D (Doubt - Pochybnost), pokud se díváte na faktory, které se vzájemně ovlivňují. V tomto případě je požadována hlubší analýza. Pokud nemáte data pro stav f"&"aktoru na OK a NG díle, vaše odpověď by měla být také D a hlubší analýza (DOE testy) by měly být provedeny k vyjasnění spojitosti tohoto Faktoru. - Zjištěné potenciální příčiny musí být potvrzeny reprodukcí problému. - Je-li odpověď NE nebo D (pochybnost)"&", Standard musí být vyjasněn, i když neexistuje žádná přímá souvislost s tímto problémem v rámci analýzy.") | H64: -Urteil - Direkt-Link? - Wenn zu produzieren Gut- und Schlechtteilen Sie genau den gleichen Standard mit dem gleichen Ergebnis verwendet haben Ihre Antwort ist keine direkte Verbindung. Die Verteilung der Werte für gute und schlechte Teile innerhalb der To"&"leranz der Norm muss bestätigen berücksichtigt werden, wenn die Standard-OK ist oder nicht. - Wenn die comparizon zeigt deutlich einen Unterschied zwischen Gut- und Schlechtteilen, sollten Sie Ihre Antwort JA sein. Wenn Ihre Antwort NEIN ist, zu erklären,"&" warum in der Spalte „Bemerkungen“. - Ihre Antwort sein kann, D (Zweifel), wenn Sie an Faktoren konfrontiert sind auf einander zu stören, in diesem Fall eine tiefere Analyse angefordert wird. - Identifiziert mögliche Ursachen müssen durch die Wiedergabe d"&"es Mangels bestätigt werden. - Wenn die Antwort NEIN oder Zweifel, Standard muss geklärt werden, auch wenn es keine direkte Verbindung mit dem Problem unter Analyse ist.") | I64: -Ítélet - Közvetlen kapcsolat? - Ha a termék jó és rossz részeket használták pontosan ugyanazt a szabvány ugyanazt az eredményt a válasz nincs közvetlen kapcsolat. Elosztása az értékek jó és rossz alkatrészeket a tolerancia a szabvány figyelembe kell venni"&", hogy erősítse meg, ha a szabvány OK vagy sem. - Ha a comparizon világosan mutatja a különbséget a jó és a rossz részek, a válasz IGEN legyen. Ha a válasz nem, miért a „megjegyzések” oszlopban. - A válasz lehet D (kétséges), amikor szembesülnek a tényező"&"k zavaró egymásra, ebben az esetben, mélyebb elemzést kértek. - azonosított potenciális okokat meg kell erősíteni a reprodukció a hiba. - Ha a válasz NEM, vagy kétséges, szabványos tisztázni kell akkor is, ha nincs közvetlen kapcsolat a probléma mellett e"&"lemzést.") | J64: -Penghakiman - Link langsung? - Jika untuk menghasilkan BAIK dan bagian BURUK Anda telah menggunakan persis standar yang sama dengan hasil yang sama jawaban Anda adalah TIDAK link langsung. Distribusi nilai untuk bagian yang baik dan buruk dalam toleransi "&"standar harus dipertimbangkan untuk mengkonfirmasi jika standar OK atau tidak. - Jika menunjukkan comparizon jelas perbedaan antara BAIK dan bagian BURUK, jawaban Anda harus YES. Jika jawaban Anda adalah NO, menjelaskan mengapa di kolom ""Komentar"". - Ja"&"waban Anda mungkin D (diragukan) ketika Anda menghadapi faktor mengganggu satu sama lain, dalam hal ini, analisis yang lebih mendalam diminta. - Mengidentifikasi penyebab potensial harus dikonfirmasi oleh reproduksi cacat. - Jika jawabannya adalah TIDAK a"&"tau keraguan, standar harus diperjelas bahkan jika tidak ada hubungan langsung dengan masalah di bawah analisis.") | K64: -Giudizio - Collegamento diretto? - Se per produrre pezzi buoni e pezzi non conformi hai utilizzato esattamente lo stesso standard con lo stesso risultato, la risposta è NO al collegamento diretto. La distribuzione dei valori per pezzi buoni e di scarto de"&"ve essere considerata all'interno della tolleranza dello standard per confermare se lo standard è OK o no. - Se il confronto mostra chiaramente una differenza tra i pezzi BUONI e quelli di SCARTO, la risposta potrebbe essere SI. Se rispondi NO, spiega per"&"chè nella colonna "" Commenti"". - La risposta può essere D (dubbio) quando si presentano fattori che interferiscono l'un l'altro, in questo caso, è richiesta un'analisi approfondita. - Le potenziali cause identificate devono essere confermate dalla ripr"&"oduzione del difetto. - Se la risposta è NO o dubbia, lo standard deve essere chiarito anche se non c'è alcun collegamento diretto con il problema che si sta analizzando.") | L64: -判断 - ダイレクトリンク？ - もし、良品と不良品が全く同じ標準を使用して、同じ結果が得られた場合、ここの回答は「ＮＯ］ダイレクトリンクとなる。良品と不良品間の交差内でのばらつきが見られる場合、標準が正しいか否か確認する必要がある。 - もし良品と不良品の比較で明らかな違いがある場合、ここの回答は「ＹＥＳ］となる。もし回答が「ＮＯ］の場合、「コメント」欄で説明する事 - 以下の場合、回答は「ダウト」になりうる。要因がお互いを阻害している状況など。この場合、更なる詳細分析が必要。 - 特定された滞"&"在的原因については、再現試験により確認する事 - もし、回答が「ＮＯ］もしくは「ダウト」の場合、分析上ダイレクトリンクが認められない場合でも標準の再確認を行う事。") | M64: -판정 - 직접적인 관련(Direct Link)? - 정상 제품과 부적합 제품이 동일한 표준을 준수하고 표준에 준수하는 값을 가지고 있으면, 직접적인 관련(Direct Link)는 ""아니요""로 표기 표준의 공차 내에서 정상 제품과 부적합 제품의 분포를 고려하여, 표준이 옳바른지 아닌지를 확인해야 합니다. - 정상 제품과 부적합 제품의 비교를 통해 명확하게 다른 차이점이 발견된다면, 직접적인 관련(Direct Link)는 ""예""로 표기 만"&"약 해당 조건에서 ""아니요""로 표기한 경우 ""코멘트"" 란에 설명을 기입하여야 합니다. - 하나의 요인이 정상 / 부적합 제품에 영향을 끼치는 경우, 추가 분석이 필요하며, 직접적인 관련(Direct Link) 는 ""의심""으로 표기 - 검출된 잠재 원인은 재현을 통해 확인해야 합니다. - 답변이 ""아니오"" / ""의심"" 의 경우, 분석 중인 현재 문제와 직접적인 관련(Direct Link) 가 없더라도 표준을 명확하게 정의해야 합"&"니다.") | N64: -Wyrok - Direct link? - Jeśli produkować dobra i części BAD użyłeś dokładnie ten sam standard z samego rezultatu odpowiedź ma bezpośredniego związku. Rozkład wartości dla dobrych i złych części wewnątrz tolerancji normy należy rozważyć, aby potwierdzić, cz"&"y norma jest OK czy nie. - Jeśli pokazach comparizon wyraźnie różnicę między dobrem i części źle, odpowiedź powinna być YES. Jeśli odpowiedź brzmi NIE, dlaczego w kolumnie „Uwagi”. - Twoja odpowiedź może być D (wątpliwości), gdy stoją na działanie czynnik"&"ów zakłócających na siebie, w tym przypadku, głębsza analiza jest wymagana. - zidentyfikowane możliwe przyczyny muszą być potwierdzone przez reprodukcji wady. - Jeśli odpowiedź brzmi NIE lub wątpliwości, standard musi zostać wyjaśnione, nawet jeśli nie ma"&" bezpośredniego związku z problemem w ramach analizy.") | O64: -Hotărârea - Link direct? - În cazul în care să BUNĂ produse și piese de rele pe care le-au folosit exact același standard cu același rezultat răspunsul este o legătură directă. Distribuția valorilor pentru piese bune și rele din interiorul toleranța stand"&"ardului trebuie să fie luate în considerare pentru a confirma dacă standardul este OK sau nu. - În cazul în care arată în mod clar comparizon o diferență între bine și părțile rele, răspunsul ar trebui să fie DA. Dacă răspunsul este NU, explică de ce în c"&"oloana „Comentarii“. - Răspunsul dvs. poate fi D (îndoială), atunci când se confruntă cu factorii de interferență pe fiecare parte, în acest caz, se solicită o analiză mai detaliată. - cauze potențiale identificate trebuie să fie confirmată de reproducere"&"a defectului. - În cazul în care răspunsul este NU sau îndoială, standard trebuie să fie clarificate, chiar dacă nu există nici o legătură directă cu problema în cadrul analizei.") | P64: -Суждение - прямая связь? - Если для производства ХОРОШИХ и ПЛОХИХ деталей вы использовали один и тот же стандарт с одинаковым результатом, ваш ответ - НЕТ прямой связи. Распределение значений для хороших и плохих деталей в пределах допуска стандарта необх"&"одимо учитывать, чтобы подтвердить, в порядке ли стандарт. - Если сравнение ясно показывает разницу между ХОРОШЕЙ и ПЛОХОЙ деталями, ваш ответ должен быть ДА. Если ваш ответ НЕТ, объясните почему в графе «Комментарии». - Ваш ответ может быть D (сомнение),"&" когда вы сталкиваетесь с факторами, мешающими друг другу, в этом случае требуется более глубокий анализ. - Выявленные потенциальные причины должны быть подтверждены воспроизведением дефекта. - Если ответ НЕТ или DOUBD (сомнение), стандарт необходимо уточ"&"нить, даже если нет прямой связи с анализируемой проблемой ") | Q64: -คำตัดสิน- การเชื่อมโยงโดยตรง? - หากการผลิตงานดี (GOOD) และงานเสีย (BAD) ที่คุณได้ใช้ว่าเป็นมาตรฐานเดียวกันกับผลลัพธ์เดียวกันคำตอบของคุณคือ NO (ไม่ใช่) การเชื่อมโยงโดยตรง. การกระจายตัวของค่างานดีและงานเสียภายในค่าเผื่อของมาตรฐานจะต้องนำมาพิจารณาเพื่อยืนยั"&"นว่ามาตรฐานคือ OK หรือไม่ - หากการเปรียบเทียบแสดงความแตกต่างอย่างชัดเจนระหว่างส่วน GOOD และ BAD คำตอบของคุณควรเป็นใช่ หากคำตอบของคุณคือไม่ให้อธิบายเหตุผลในคอลัมน์ ""ความคิดเห็น"" - คำตอบของคุณอาจเป็น D (สงสัย) เมื่อคุณกำลังเผชิญกับปัจจัยที่ขัดขวางซึ่งกัน"&"และกันในกรณีนี้ขอให้มีการวิเคราะห์ที่ลึกซึ้งยิ่งขึ้น - สาเหตุที่เป็นไปได้ที่ระบุจะต้องได้รับการยืนยันโดยการทำซ้ำข้อบกพร่อง - หากคำตอบคือไม่ใช่หรือมีข้อสงสัยต้องมีการชี้แจงมาตรฐานแม้ว่าจะไม่มีการเชื่อมโยงโดยตรงกับปัญหาที่กำลังวิเคราะห์ก็ตาม") | R64: -Yargı - Doğrudan bağlantı? - üretim iyi ve kötü bölgelerine aynı sonuçla aynı standart kullandıysanız Cevabınız HAYIR doğrudan bağlantıdır. Standart Tamam olup olmadığını standardın tolerans içindeki iyi ve kötü parçalar için değerlerin dağılımı onaylayın"&" düşünülmelidir. - açıkça comparizon gösterileri iyi ve kötü parçalar arasında bir fark varsa, cevap EVET olmalıdır. Cevabınız HAYIR ise, neden sütun ""Yorumlar"" olarak açıklar. - Eğer birbirlerine müdahale faktörlere karşı karşıya iken Yanıtınız D (şüph"&"e) olabilir, bu durumda, daha derinlemesine analiz istenir. - Tespit edilen potansiyel nedenleri kusurun üreme ile teyit edilmelidir. - cevabınız HAYIR veya şüphe ise analiz edilen sorunla doğrudan bağlantı varsa, standart hatta açıklık olmalıdır.")
A65: [13] | B65: -5 WHYs Physical > System > Managment actions 5 Whys has to be done if and only if your factor is in link with issue Objective is to go deeply in analysis to identify system and management actions") | C65: -5 WHYS physiques> Système> Actions Managment 5 Whys doit être fait si et seulement si votre facteur est en lien avec le numéro L'objectif est d'approfondir l'analyse pour identifier les actions du système et de gestion") | D65: -5 PORQUÊS Físico> Sistema> Ações de gerenciamento 5 porques deve ser feito se e somente se o seu fator está relacionado com o problema O objetivo é aprofundar a análise para identificar o sistema e as ações de gestão") | E65: -5 porqués físicos> Sistema> acciones Managment 5 porqués se tiene que hacer si y sólo si su factor es en enlace con la edición El objetivo es profundizar en el análisis para identificar las acciones del sistema y de gestión") | F65: -5WHYs 实物>系统>管理行动 需要进行5Whys分析，当，仅当该因子与问题相关时。 目的是进行深入分析，找出系统和管理上的行动措施。") | G65: -5 Proč > Systém> Akce Managmentu 5 Proč musí být provedeno tehdy a jen tehdy, pokud je váš faktor s přímé souvislosti s Problémem Cílem je provést hloukovou analýzu a nalézt systémové opatření a opatření v souvislosti s managementem") | H65: -5 Whys Physical> System> Managment Aktionen 5 Whys muss getan werden, wenn und nur wenn Ihr Faktor ist in Verbindung mit der Ausgabe Ziel ist es tief in der Analyse zu gehen System und Management-Maßnahmen zu identifizieren") | I65: -5 Miért Fizikai> Rendszer> Managment akciók 5 Miért kell tenni akkor, ha a tényező a kapcsolat kérdése Cél az, hogy menjen mélyen elemzés azonosítani rendszert és kezelési intézkedések") | J65: -5 mengapa Fisik> System> tindakan Managment 5 Kenapa yang harus dilakukan jika dan hanya jika faktor Anda dalam hubungan dengan masalah Tujuannya adalah untuk pergi secara mendalam dalam analisis untuk mengidentifikasi sistem dan manajemen tindakan") | K65: -5 PERCHÉ Fisico> Sistema> Azioni di gestione 5 Perché: deve essere fatto se e solo se il fattore è collegato al problema L'obiettivo è approfondire l'analisi per identificare le azioni di sistema e di gestione") | L65: -なぜなぜ分析 物理的＞仕組的＞マネージメントアクション なぜなぜ分析は、要因が不具合に起因する場合に行う。 その目的は、仕組的マネージメント的アクションを取る為に深堀する事である。") | M65: -5Why 물리적 기준 > 시스템 > 관리 기준 ""5Why""는 문제와 관련이 있는 인자에 대해서 실시합니다. ""5Why"" 실시 목적은 시스템 측면 그리고 관리 기준에 대한 심층적인 분석입니다.") | N65: -Metoda 5 why fizyczne> System> Działania Managment 5 razy dlaczego należy zrobić, jeśli i tylko wtedy, gdy czynnikiem jest w związku z emisji Celem jest, aby przejść głęboko w analizie w celu zidentyfikowania działań systemowych i zarządzania") | O65: -5 Whys fizice> Sistem> Acțiuni Managment 5 Whys trebuie să fie făcut dacă și numai dacă factorul este în legătură cu problema Obiectivul este de a merge adânc în analiză pentru a identifica acțiunile de sistem și de management") | P65: -5 ПОЧЕМУ Физические> Системные> Управленческие действия 5 Почему нужно делать, если и только если ваш фактор имеет связь с проблемой Цель состоит в том, чтобы углубиться в анализ для определения действий системы и управления ") | Q65: -5 whys ทางกายภาพ> ระบบ> การดำเนินการจัดการ 5 Whys ถูกทำก็ต่อเมื่อปัจจัยของคุณเชื่อมโยงกับปัญหา วัตถุประสงค์คือการไปการวิเคราะห์ให้ลึกเพื่อระบุระบบและการบริหารจัดการ") | R65: -5 Whys Fiziksel> Sistem> Yönetim eylemler 5 Whys eğer yapılmalıdır yalnızca faktör sorunla bağlantıda ise Amaç sistem ve yönetim işlemleri tanımlamak için analizde derinden gitmektir")
A66: [14] | B66: -FACTOR TREE ANALYSIS FOR NON DETECTION Why the problem was not detected ? If issue linked to production : Why issue not detected during controls done on line and defined in control plan? Check PFMEA to confirm if risk identified If people issue : Why tr"&"aining material not detected insufficient? Why certification process not detected not robust enough? If Project issue : Why not detected during Design review? during DV? During PV? During Valeo FDPR?") | C66: -FACTEUR TREE ANALYSE DE NON DETECTION Pourquoi le problème n'a pas été détecté? Si le problème lié à la production: Pourquoi ne pas problème détecté lors de contrôles effectués en ligne et définis dans le plan de contrôle? Vérifiez PFMEA pour confirmer s"&"i le risque identifié Si les gens émettent: Pourquoi le matériel de formation non détectée insuffisante? Pourquoi le processus de certification non détecté pas assez robuste? Si le problème du projet: Pourquoi ne pas détecté lors de l'examen de concepti"&"on? pendant DV? Au cours de PV? Au cours de Valeo FDPR?") | D66: -ANÁLISE DA ÁRVORE DE FATORES PARA NÃO DETECÇÃO Por que o problema não foi detectado? Se o problema está vinculado à produção: Por que o problema não foi detectado durante os controles feitos on-line e definidos no plano de controle? Verifique o PFMEA par"&"a confirmar se o risco foi identificado") | E66: -FACTOR DE ANÁLISIS DE ÁRBOL NO DETECCIÓN ¿Por qué no se detectó el problema? Si el problema vinculado a la producción: ¿Por qué problema no se detecta durante los controles realizados en línea y definidas en el plan de control? Compruebe PFMEA para confi"&"rmar si el riesgo identificado Si la gente emisión: ¿Por qué no detectó material de formación insuficientes? ¿Por qué no se detectó proceso de certificación no lo suficientemente robusto? Si el problema del proyecto: ¿Por qué no se detecta durante la re"&"visión del diseño? durante DV? Durante PV? Durante Valeo FDPR?") | F66: -流出因子树分析 为什么没有探测到问题？ 如果问题与生产相关：为什么问题没有在生产线控制时被探测到并被定义在控制计划中？检查PFMEA确认是否有识别到该风险。 如果是人的问题：为什么培训材料中没有探测到能力不足？为什么认证过程不足够强健可探测？ 如果是项目问题：为什么没有在设计评审、DV、PV， FDPR 中被探测到？ ") | G66: -FACTOR TREE ANALÝZA PRO NEDETEKCI Proč nebyl problém zjištěn? Pokud problém souvisí s výrobou: Proč nebyl problém zjištěn při kontrolách provedených v souladu s definovaným kontrolním plánem? Zkontrolujte PFMEA a potvrdťe. že riziko (problém) je zde zmíňě"&"no. Pokud problém souvisí s lidmi: Proč nebyl školící materiál shledán nedostatečným? Proč nebly certifikační proces shledán dostatečně robustní? Pokud problém souvisí s Projektem: Proč nebyl problém objeven během Design Review? Během DV? Během PV? Běhe"&"m Valeo FDPR?") | H66: -FACTOR TREE ANALYSE FÜR NICHT NACHWEIS Warum wurde das Problem nicht erkannt? Wenn das Problem der Produktion verbunden ist: Warum Problem nicht getan bei den Kontrollen festgestellt auf der Leitung und in Kontrollplan definiert? Prüfen PFMEA zu bestätig"&"en, wenn Risiko identifiziert Wenn die Menschen ausgeben: Warum Trainingsmaterial nicht unzureichend erkannt? Warum Zertifizierungsprozess nicht nicht robust genug erkannt? Wenn Projekt Frage: Warum nicht während der Entwurfsprüfung erkannt? während DV?"&" Während PV? Während Valeo FDPR?") | I66: -FAKTOR fa elemzést NEM MOZGÁSÉRZ Miért van szükség a probléma nem volt kimutatható? Ha a probléma a termeléshez kapcsolódó: Miért kérdés nem mutatható ki az ellenőrzések során végzett on-line és meghatározott ellenőrzési terv? Ellenőrizze PFMEA megerősít"&"eni, hogy az azonosított kockázathoz Ha az emberek kiadni: Miért képzési anyagot nem ismeri elégséges? Miért tanúsítási folyamat nem mutatható nem elég hatékony ahhoz? Ha Project kérdés: miért nem észlel terv felülvizsgálata? alatt DV? Alatt PV? Alatt V"&"aleo FDPR?") | J66: -FAKTOR TREE ANALISIS NON DETEKSI Mengapa masalah itu tidak terdeteksi? Jika masalah terkait dengan produksi: Mengapa masalah tidak terdeteksi selama kontrol dilakukan pada baris dan didefinisikan dalam rencana pengendalian? Periksa PFMEA untuk mengkonfir"&"masi jika risiko yang diidentifikasi Jika orang-orang mengeluarkan: Mengapa materi pelatihan tidak terdeteksi cukup? Mengapa proses sertifikasi tidak terdeteksi tidak cukup kuat? Jika masalah Project: Mengapa tidak terdeteksi selama Desain review? selam"&"a DV? Selama PV? Selama Valeo FDPR?") | K66: -ANALISI DEL DIAGRAMMA DEI FATTORI PER NON RILEVAZIONE Perché il problema non è stato rilevato? Se il problema e collegato alla produzione: perché il problema non è stato rilevato durante i controlli effettuati in linea e definiti nel piano di controllo? "&"Controllare PFMEA per confermare se il rischio era stato identificato Se è un problema legato alle persone: Perché la formazione non è stato rilevata insufficiente? Perché il processo di certificazione non è stato rilevato non abbastanza robusto? Se il"&" problema è di progetto: Perché non è stato rilevato durante la revisione del progetto? Durante DV? Durante il PV? Durante Valeo FDPR?") | L66: -FACTOR TREE ANALYSIS 未検出 なぜ問題が検出されませんでしたか？ 問題が生産活動に関係する場合：なぜ、コントロールプランに定義されラインでも管理しているのに発見されなかったのか？ もし人の問題であれば：何故教育資料の不十分さが見つからなかったのか？何故、スキル認証プロセスで発見されなかったのか？教育資料の実効性はどうなのか？ プロジェクトの問題場合：なぜデザインレビュー時、ＤＶ時、ＰＶ時、ＦＤＰＲ時に発見されなかったのか？") | M66: -Factor Tree Analysis - 미 검출 왜 문제를 검출하지 못하였나요? 생산문제 : 부적합이 실시간 관리 중에 검출되지 못한 이유가 무엇입니까? 그리고 해당 내용은 관리계획서에 명기가 되어있습니까? 만약 리스크가 있다면, PFMEA 를 확인하십시오 사람(작업자) 문제 : 교육자료에 해당 내용이 명기되지 않은 이유가 무엇입니까? 교육 인증 프로세스의 부적합이 사전에 감지되지 않은 이유가 무엇입니까? 프로젝트 문제 : 문제가 디자인 검토 단계"&" / DV / PV / 발레오 FDPR 에서 검출되지 않은 이유가 무엇입니까?") | N66: -FACTOR TREE ANALIZA DLA NON DETEKCJA Dlaczego problem nie został wykryty? Jeśli problem związany z produkcją: Dlaczego problem nie zostało wykryte podczas kontroli przeprowadzonych na linii i zdefiniowanych w planie kontroli? Sprawdzić PFMEA aby potwierd"&"zić, czy zidentyfikowane ryzyko Jeśli ludzie wystawienia: Dlaczego nie wykryto materiały szkoleniowe niewystarczające? Dlaczego proces certyfikacji nie wykryto nie wytrzymała wystarczy? Jeśli problem Projekt: Dlaczego nie zostało wykryte podczas przeglą"&"du projektu? podczas DV? Podczas PV? Podczas Valeo FDPR?") | O66: -FACTOR TREE ANALIZA PENTRU NON DETECTARE De ce nu a fost detectată problema? În cazul în care problema legată de producție: De ce problema nu a fost detectat în timpul controalelor efectuate pe linie și definite în planul de control? Verificați PFMEA pen"&"tru a confirma dacă este identificat un risc Dacă oamenii emit: De ce nu a fost detectat un material de instruire insuficientă? De ce procesul de certificare nu a fost detectat nu este suficient de robust? Dacă problema de proiect: De ce nu a fost detec"&"tat în timpul examinării de proiectare? în timpul DV? În timpul PV? În timpul Valeo FDPR?") | P66: -FTA ДЛЯ НЕОБНАРУЖЕНИЯ Почему проблема не обнаружена? Если проблема связана с производством: почему проблема не обнаруживается во время оперативного контроля на линии, определенного в плане управления? Проверьте PFMEA, чтобы подтвердить, идентифицирован ли"&" риск Если проблема связана с людьми: почему обучающего материала по необнаружению недостаточно? Почему процесс сертификации недостаточно надежен? Если проблема в проекте: почему не было обнаружено во время Design review? во время DV? во время PV? во в"&"ремяValeo FDPR?") | Q66: -การวิเคราะห์ FACTOR TREE สำหรับการตรวจจับหลุดรอด ทำไมปัญหาถึงไม่ถูกตรวจพบ? หากปัญหาเชื่อมโยงกับการผลิต: เหตุใดจึงตรวจไม่พบปัญหาระหว่างการควบคุมที่ดำเนินการตามสายงานและกำหนดไว้ใน Control Plan หรือไม่? ตรวจสอบ PFMEA เพื่อยืนยันว่ามีความเสี่ยงที่ระบุ. หาก"&"เป็นปัญหาจากคน: ทำไมวัสดุการฝึกอบรมไม่พบไม่เพียงพอ? ทำไมกระบวนการรับรองไม่พบไม่แข็งแกร่งเพียงพอหรือไม่ หากเป็นปัญหาจากโครงการ: ทำไมไม่ตรวจพบในระหว่างการตรวจสอบการออกแบบ? ในช่วง DV? ในช่วง PV? ในช่วง Valeo FDPR?") | R66: -FAKTÖR AĞAÇ ANALİZ İÇİN OLMAYAN TESPİTİ Neden sorun tespit edilmedi? Sorun kontrolleri hattında yapıldığını ve kontrol planında tanımlanan sırasında tespit edilmedi Neden: Sorun Üretime bağlı ise? Risk tespit eğer onaylayın PFMEA Kontrol eğitim materyal"&"i yetersiz algılanmadı Neden: insanlar sorunu varsa? Neden sertifikasyon süreci değil sağlam yeterince algılanmıyor? Proje sorunu değilse: Neden Tasarım İnceleme sırasında tespit edilmedi? DV sırasında? PV sırasında mı? Valeo FDPR sırasında mı?")
B68: -ACTION PLAN & GENBA REVIEW") | C68: -PLAN D'ACTION ET EXAMEN Genba") | D68: -PLANO DE AÇÃO & REVISÃO NO GENBA") | E68: -PLAN DE ACCIÓN Y REVISIÓN genba") | F68: -行动计划 & 现场审核") | G68: -AKČNÍ PLÁN a GENBA REVIEW") | H68: -AKTIONSPLAN & Genba REVIEW") | I68: -ÖSSZEFOGÁS & genba ÁTTEKINTÉS") | J68: -RENCANA AKSI & Genba REVIEW") | K68: -PIANO D'AZIONE & VERIFICA SUL GENBA") | L68: -アクションプラン & 現場確認") | M68: -조치 계획 & GENBA 검토") | N68: -PLAN DZIAŁANIA & GENBA PRZEGLĄD") | O68: -PLAN DE ACȚIUNE & Genba REVIEW") | P68: -ПЛАН ДЕЙСТВИЙ И ОБЗОР НА ГЕНБЕ") | Q68: -ACTION PLAN & Genba REVIEW") | R68: -EYLEM PLANI & Genba İNCELEME")
A69: [1] | B69: -What was done to reproduce the concern? - Based on the identified factors in the FTA and the 5 whys, explain which activities have been done to confirm the root-cause of the problem. - The reproduction of the defect concerns occurrence and/or non detectio"&"n") | C69: -Ce qui a été fait pour reproduire le problème? - Sur la base des facteurs identifiés dans l'ALE et les 5 pourquoi, expliquent quelles activités ont été réalisées pour confirmer la cause du problème. - La reproduction du défaut concerne l'apparition et / o"&"u de non détection") | D69: -O que foi feito para reproduzir o problema? - Com base nos fatores identificados no FTA e nos 5 porquês, explique quais atividades foram realizadas para confirmar a causa raiz do problema. - A reprodução do defeito diz respeito à ocorrência e / ou não d"&"etecção") | E69: -¿Qué se hizo para reproducir el problema? - Sobre la base de los factores identificados en el TLC y los 5 porqués, explican las actividades que se han realizado para confirmar la causa raíz del problema. - La reproducción de la ocurrencia preocupaciones d"&"e defectos y / o no detección") | F69: -做了什么来再现故障？ - 基于在FTA和5Whys里被识别的因子，解释哪些行动已经被完成用来确认问题的根本原因 - 故障再现应包含发生和/或者流出") | G69: -Co jsme udělali, abychom reprodukovali problém? - na základě vyjmenovaných faktorů v FTA a 5 Proč vysvětlete, jaké akce byly provedeny pro potvrzení kořenové příčiny problému. - Reprodukce problému se týká výskytu (Occurrence) a / nebo Nedetekce (Non det"&"ekction)") | H69: -Was wurde getan, um die Sorge zu reproduzieren? - Auf der Grundlage der genannten Faktoren in der FTA und die 5 whys, erklären, welche durchgeführt wurden Maßnahmen im Bereich der Grundursache des Problems zu bestätigen. - Die Wiedergabe des Defekts betri"&"fft Auftreten und / oder nicht-Erfassungs") | I69: -Mi történt, hogy reprodukálja az aggodalom? - Az azonosított tényezők az FTA és az 5 miérteket, magyarázza, hogy mely tevékenységek volna tenni, hogy erősítse meg a gyökér-oka a problémának. - A reprodukciója a hiba aggodalmak előfordulását és / vagy nem "&"észlelési") | J69: -Apa yang dilakukan untuk mereproduksi kekhawatiran? - Berdasarkan faktor diidentifikasi dalam FTA dan 5 mengapa, menjelaskan yang kegiatan telah dilakukan untuk mengkonfirmasi akar-penyebab masalah. - Reproduksi kekhawatiran cacat kejadian dan / atau non "&"deteksi") | K69: -Cosa è stato fatto per riprodurre il problema? - Sulla base dei fattori individuati nell'FTA e dei 5 perché, spiegare quali attività sono state svolte per confermare la causa principale del problema. - La riproduzione del difetto riguarda sia l'occorrenza"&" che la mancata rilevazione") | L69: -問題再現の為に何を行いましたか？ - FTAとなぜなぜ分析を通じて特定された要因に基づき、原因を確認する為にどのような活動をしたか説明する。 - 不良の再現は発生、そして/あるいは未検出に関係するのか？") | M69: -문제의 재현을 위해 무엇을 하셨습니까? - FTA / 5Whys 에서 확인된 인자로 어떻게 근본원인을 확인하였는지 설명하십시오 - 문제의 재현은 ""문제 발생"" 그리고(또는) ""미 검출"" 부분에서 확인해야 합니다. ") | N69: -Co zostało zrobione do odtworzenia obawy? - na podstawie zidentyfikowanych czynników FTA i metoda 5 why, wyjaśnić, jakie działania zostały przeprowadzone w celu potwierdzenia pierwotnej przyczyny problemu. - Rozmnażanie występowania dotyczy wad i / lub ni"&"e wykrycie") | O69: -Ceea ce a fost făcut pentru a reproduce îngrijorarea? - Pe baza factorilor identificați în ALS și 5 analiza cauzele, explicați care activitățile au fost efectuate pentru a confirma rădăcină cauza problemei. - Reproducerea preocupărilor defecte apariția și"&" / sau non detectarea") | P69: -Что было сделано для воспроизведения дефекта? - На основании выявленных факторов в FTA и 5 почему, объясните, какие действия были предприняты для подтверждения коренной причины проблемы. - Воспроизведение дефекта касается возникновения и / или необнаруж"&"ения.") | Q69: -อะไรสิ่งที่ได้ดำเนินการในการทำซ้ำที่เกี่ยวข้อง? - ขึ้นอยู่กับปัจจัยที่ระบุไว้ในเขตการค้าเสรีและ 5 whys อธิบายกิจกรรมที่ได้ดำเนินการเพื่อยืนยันรากสาเหตุของปัญหา - ทำสำเนาของการเกิดความกังวลข้อบกพร่องและ / หรือการตรวจสอบที่ไม่ใช่") | R69: -Ne endişe çoğaltmak yapıldı? - FTA ve 5 whys, belirlediği faktörlere dayanarak, faaliyetler sorunun kök nedenini onaylamak için yapılmıştır hangi açıklar. - kusur ilgilidir oluşumu ve / veya algılama çoğaltılması")
A70: [2] | B70: -How was it done? 4M conditions applied during the reproduction must be recorded to be compared with the conclusions of the FTA. Precise what are the key elements followed during the trials.") | C70: -Comment at-il été fait? conditions 4M appliquées au cours de la reproduction doivent être enregistrées à comparer aux conclusions de l'ALE. Précise quels sont les éléments clés suivis au cours des essais.") | D70: -Como foi feito? As condições 4M aplicadas durante a reprodução devem ser registradas para serem comparadas com as conclusões do FTA. Precise quais são os elementos-chave seguidos durante os testes.") | E70: -¿Cómo se hizo? condiciones 4M aplicados durante la reproducción deben ser registrados de ser comparados con las conclusiones de la TLC. Precisa cuáles son los elementos clave seguidos durante los ensayos.") | F70: -怎样做的？ 再现故障时的4M条件必须被记录下来，与FTA的结论进行比较。在试验时明确什么是需要跟踪的关键要素。") | G70: -Jak to bylo provedeno? Musíte zaznamenat 4M podmínky platné při reprodukci problému tak, aby je bylo možné porovnat se závěry FTA analýzy. Upřesněte jaké klíčové prvky byly sledovány v průběhu zkoušek.") | H70: -Wie war es getan? 4M Bedingungen während der Wiedergabe angewendet müssen aufgezeichnet werden mit den Schlussfolgerungen des FTA verglichen werden. Präzise, ​​was sind die wichtigsten Elemente während der Versuche folgten.") | I70: -Hogy csinálta? 4M körülmények során alkalmazott reprodukciós fel kell jegyezni, hogy össze kell hasonlítani a következtetéseket az FTA. Pontos mik a legfontosabb elemei majd kísérletek során.") | J70: -Bagaimana hal itu dilakukan? kondisi 4M diterapkan selama reproduksi harus dicatat untuk dibandingkan dengan kesimpulan dari FTA. Precise apa saja elemen kunci diikuti selama persidangan.") | K70: -Come è stata fatta la riproduzione del problema? Le 4M applicate durante la riproduzione devono essere registrate per essere confrontate con le conclusioni dell'FTA. Precisare quali sono gli elementi chiave seguiti durante le prove.") | L70: -それはどのように行われていましたか？ 再現試験の際に考慮された4M条件は、FTAの結論と比較する為に記録されなければならない。試験の際に考慮して重要な要素について詳細に記述する") | M70: -어떻게 확인하였습니까? 재현시험시 적용된 4M 조건은 FTA의 결과와 비교를 위해 반드시 기록되어야 합니다. 해당 시험시 중요한 요소에 대해 상세하게 기술") | N70: -Jak to zrobić? Warunki 4M stosowane podczas odtwarzania muszą być zapisywane do porównania z wnioskami FTA. Dokładne jakie są kluczowe elementy, a następnie w trakcie prób.") | O70: -Cum a fost făcut? 4M condițiile aplicate în timpul reproducerii trebuie înregistrate pentru a fi comparate cu concluziile din ALS. Precis care sunt elementele cheie urmate în timpul studiilor.") | P70: -Как это было сделано? Условия 4M, применяемые во время воспроизведения, должны быть записаны для сравнения с выводами FTA. Уточните, какие ключевые элементы соблюдались во время проверки.") | Q70: -มันถูกทำอย่างไร ? เงื่อนไข 4M ที่ใช้ในระหว่างการทำการผลิตซ้ำ จะต้องถูกบันทึกเพื่อเปรียบเทียบกับข้อสรุปของ FTA กำหนดองค์ประกอบสำคัญที่ตามมาในระหว่างการทดลองอย่างแม่นยำ") | R70: -Bu nasıl oldu? üreme sırasında uygulanan 4M koşulları FTA sonuçları ile karşılaştırılabilir için kaydedilmesi gerekir. Kesin denemeler sırasında izlenen temel unsurları nelerdir.")
A71: [3] | B71: -When was it done? Indicate when the reproduction of the defect has been done: date - time - shift") | C71: -Quand at-il été fait? Indiquer lorsque la reproduction du défaut a été fait: date - heure - changement") | D71: -Quando foi feito? Indique quando a reprodução do defeito foi feita: data - hora - turno") | E71: -Cuando se hizo? Indicar cuando la reproducción del defecto se ha hecho: Fecha - Hora - turno") | F71: -什么时候做的？ 指出什么时候完成的故障再现：日期 - 时间 - 班次") | G71: -Kdy to bylo provedeno? Uveďte, kdy byla provedena reprodukce problému: datum - čas - směna") | H71: -Wann wurde es gemacht? Geben Sie, wenn die Wiedergabe des Mangels getan wurde: Datum - Zeit - Verschiebung") | I71: -Amikor csinálta? Jelezze, ha a reprodukció a hiba megtörtént: dátum - idő - váltás") | J71: -Kapan itu dilakukan? Menunjukkan bila reproduksi cacat telah dilakukan: tanggal - waktu - pergeseran") | K71: -Come è stata fatta la riproduzione del problema? Indica quando la riproduzione del difetto è stato fatta: data - ora - turno") | L71: -それは行われていましたか？ 再現試験実施の日時-シフトを明示する") | M71: -재현 시험은 언제 수행되었습니까? 문제 재현 시험 완료 일자 기록 : 일자 - 시간 - 쉬프트") | N71: -Kiedy to było zrobione? Wskazują gdy powielanie wady zostało wykonane: data - czas - przesunięcie") | O71: -Când a fost făcut? Indicați în cazul în care reproducerea defectului a fost făcut: data - ora - schimbare") | P71: -Когда это было сделано? Укажите, когда было выполнено воспроизведение дефекта: дата - время - смена") | Q71: -เมื่อไหร่ ที่ทำแล้วเสร็จ? ระบุเวลาที่เกิดข้อบกพร่องขึ้นใหม่: วัน - เวลา - กะ") | R71: -Ne zaman yapıldı? defekt üreme işlem tamamlandığında belirtiniz: tarih - saati - shift")
A72: [4] | B72: -What was the result? Based on facts and data, give the result of the reproduction of the defect on the parts produced.") | C72: -Quel était le résultat? Sur la base des faits et des données, donner le résultat de la reproduction du défaut sur les pièces produites.") | D72: -Qual foi o resultado? Com base em fatos e dados, dê o resultado da reprodução do defeito nas peças produzidas.") | E72: -¿Cuál fue el resultado? Sobre la base de los hechos y datos, dé el resultado de la reproducción del defecto en las piezas producidas.") | F72: -结果是什么？ 基于事实和数据，给出故障再现时生成出的产品的结果。") | G72: -Jaký byl výsledek? Na základě faktů a dat popište výsledek reprodukce problému na vyrobených dílech.") | H72: -Was war das Ergebnis? Auf der Grundlage von Fakten und Daten, gibt das Ergebnis der Wiedergabe des Defekts auf den hergestellten Teilen.") | I72: -Mi volt az eredmény? Tényeken alapuló adatokat, így az eredmény a reprodukció a hiba a gyártott alkatrészeket.") | J72: -Apakah hasilnya? Berdasarkan fakta dan data, memberikan hasil reproduksi cacat pada bagian-bagian yang dihasilkan.") | K72: -Qual'è stato il risultato? Sulla base di fatti e dati, dare il risultato della riproduzione del difetto sulle parti prodotte.") | L72: -結果はどうでしたか？ 事実とデータに基づいて、再現試験ので再現された不良品の詳細を明示する。") | M72: -재현 시험 결과는 무엇입니까? 사실과 데이터를 기반으로 수행한 문제 재현 시험의 결과를 기록하십시오") | N72: -Jaki był rezultat? Oparte na faktach i danych, daje wynik reprodukcji wady na części produkowanych.") | O72: -Care a fost rezultatul? Bazat pe fapte și date, da rezultatul reproducerii defectului asupra pieselor produse.") | P72: -Каков был результат? На основании фактов и данных опишите результат воспроизведения дефекта на произведенных деталях ") | Q72: -ผลที่ได้เป็นอะไร? จากข้อเท็จจริงและข้อมูลให้ผลลัพธ์ของการทำการผลิตซ้ำข้อบกพร่องของชิ้นส่วนที่ผลิต") | R72: -Sonuç neydi? olgular ve verilere göre, üretilen parçaların kusurun yeniden sonucunu verir.")
A73: [5] | B73: -Root-cause From the conclusions of the analysis (FTA, reproduction of the defect, 5 whys), report the root-cause of the problem needing a correction.") | C73: -Cause première D'après les conclusions de l'analyse (FTA, reproduction du défaut, 5 pourquoi), rapport de la cause profonde du problème nécessitant une correction.") | D73: -Causa raiz A partir das conclusões da análise (FTA, reprodução do defeito, 5 porquês), relate a causa raiz do problema que precisa de correção.") | E73: -Causa principal A partir de las conclusiones del análisis (TLC, la reproducción del defecto, 5 porqués), informan la causa raíz del problema que necesita una corrección.") | F73: -根本原因 从分析的结论中（FTA，故障再现，5Whys），总结需要改善的根本原因。") | G73: -Příčina Ze závěrů analýzy (FTA, reprodukce problému, 5 Proč) popište kořenovou příčinu problému, která potřebují nápravu.") | H73: -Ursache Aus den Schlussfolgerungen der Analyse (FTA, Reproduktion des Fehlers, 5 whys), berichtet über die Grundursache des Problems eine Korrektur erforderlich ist.") | I73: -Kiváltó ok A következtetések az elemzés (FTA, reprodukció a hiba, 5 Miért), jelentse a kiváltó oka a probléma igénylő Javítás.") | J73: -Akar masalah Dari kesimpulan dari analisis (FTA, reproduksi cacat, 5 mengapa), melaporkan akar-penyebab masalah membutuhkan koreksi.") | K73: -Causa radice Dalle conclusioni dell'analisi (FTA, riproduzione del difetto, 5 perché), riportare la causa radice del problema che necessita di correzione.") | L73: -問題真因 分析の結論より（FTA, 再現試験、なぜなぜ分析）是正が必要な問題真因を報告する") | M73: -근본 원인 분석결과(FTA, 재현시험, 5 Whys) 를 통해 각 근본원인별 필요한 개선점을 보고하십시오") | N73: -Root-przyczyna Z wnioskami z analizy (FTA, powielanie wady, 5 why), zgłoś pierwotnej przyczyny problemu, która korektę.") | O73: -Cauza de bază Din concluziile analizei (ALS, reproducerea a defectului, 5 problemă), raportează rădăcină cauza problemei au nevoie de o corecție.") | P73: -Основная причина По выводам анализа (FTA, воспроизведение дефекта, 5 почему) укажите коренную причину проблемы, требующую коррекции") | Q73: -สาเหตุที่แท้จริง จากข้อสรุปของการวิเคราะห์ (FTA, การทำซ้ำข้อบกพร่อง, 5 whys) ให้รายงานต้นตอของปัญหาที่ต้องการการแก้ไข") | R73: -Ana neden Analiz sonuçlarına itibaren (STA, kusur, 5 Whys çoğaltılması), düzeltme ihtiyacı sorunun kök nedenini bildirmektedir.")
A74: [6] | B74: -TECHNICAL / SYSTEMIC CORRECTIVE ACTION Explain clearly which corrective actions are implemented to correct the root-cause. Reader should understand what is the difference between previous and future situation. Put data when appropriate, process parameter "&"before and after for example.") | C74: -TECHNIQUE / SYSTÉMIQUE ACTION CORRECTIVE Expliquez clairement qui sont mis en œuvre des mesures correctives pour corriger la cause racine. Le lecteur doit savoir quelle est la différence entre la situation antérieure et future. données lorsque mettre des "&"paramètres appropriés, processus avant et après par exemple.") | D74: -AÇÃO CORRETIVA TÉCNICA / SISTÊMICA Explique claramente quais ações corretivas são implementadas para corrigir a causa raiz. O leitor deve entender qual é a diferença entre a situação anterior e a futura. Coloque os dados quando apropriado, processe o par"&"âmetro antes e depois, por exemplo.") | E74: -ACCIÓN TÉCNICA / sistémicos CORRECTIVO Explican claramente qué acciones correctivas sean implementadas para corregir la causa raíz. Lector debe entender lo que es la diferencia entre la situación anterior y el futuro. datos puestos en su caso, de parámetr"&"os de proceso antes y después de por ejemplo.") | F74: -技术 / 系统改善措施 解释清楚实施了哪些改善措施用于改善根本原因。读者应可以理解改善前后的区别。合适的时候，记录数据，比如改善前后的工艺参数。") | G74: -TECHNICKÁ / SYSTÉMOVÁ NÁPRAVNÁ OPATŘENÍ Jasně vysvětlete, která nápravná opatření jsou realizována k nápravě kořenové příčiny. Čtenář by měl pochopit rozdíl mezi předchozí a budoucí situaci. Pokud je to relevantní, uveďte konkrétní data (např. procesní pa"&"rametry před a po nápravě).") | H74: -TECHNISCHE / SYSTEMIC ABHILFE Erklären Sie deutlich, welche sind Abhilfemaßnahmen durchgeführt, die Grundursache zu korrigieren. Leser sollten verstehen, was der Unterschied zwischen früheren und zukünftigen Situation ist. Setzen Daten gegebenenfalls Proz"&"essparameter vor und nach zum Beispiel.") | I74: -MŰSZAKI / Szisztémás Teendő Világosan megmagyarázni, hogy milyen korrekciós intézkedések végrehajtását, hogy javítsa ki a gyökér-oka. Reader kell értenie, hogy mi a különbség a korábbi és jövőbeni helyzetét. Tedd adatokat, ha szükséges, eljárási paraméter"&" előtt és után például.") | J74: -TEKNIS / SISTEMIK HASIL TINDAKAN Menjelaskan dengan jelas yang tindakan korektif dilaksanakan untuk memperbaiki akar penyebab. Pembaca harus memahami apa perbedaan antara situasi sebelumnya dan masa depan. Data Masukan saat yang tepat, parameter proses se"&"belum dan sesudah misalnya.") | K74: -AZIONE CORRETTIVA SISTEMICA / TECNICA Spiegare chiaramente quali azioni correttive sono implementate per correggere la causa radice. Il lettore deve essere in grado di capire qual è la differenza tra la situazione precedente e quella futura. Registra i da"&"ti appropriati, ad esempio i parametri di processo prima e dopo.") | L74: -技術的/仕組み的是正措置 どのような是正措置が問題真因に対して行われたのかを明瞭に説明する事。読み手が以前の状況と今後の状況の何が違うのか分かるようにする事。必要に応じてデータや工程パラメーターについても以前と今後が分かる様にする事が望ましい。") | M74: -기술 / 시스템 개선 활동 근본원인 해결을 위해 어떤 개선 조치사항이 수행되었는지 명확하게 기술하십시오") | N74: -TECHNICZNE / SYSTEMOWEGO zaradcze Wyjaśnić dokładnie, jakie działania naprawcze zostały wdrożone w celu skorygowania pierwotnej przyczyny. Czytelnik powinien zrozumieć, jaka jest różnica między poprzednim i przyszłej sytuacji. Dane umieszczone w stosownyc"&"h przypadkach, parametr proces przed i po na przykład.") | O74: -TEHNIC / SISTEMICĂ ACȚIUNE CORECTIVĂ Explicați în mod clar ce acțiuni corective sunt puse în aplicare pentru a corecta cauzelor fundamentale. Cititorul trebuie să înțeleagă ceea ce este diferența dintre situația anterioară și viitoare. Potrivit datelor at"&"unci când este cazul, un parametru de proces, înainte și după, de exemplu.") | P74: -ТЕХНИЧЕСКИЕ / СИСТЕМНЫЕ КОРРЕКТИРУЮЩИЕ ДЕЙСТВИЯ Четко объясните, какие корректирующие действия внедрены для устранения коренной причины. Читатель должен понимать, в чем разница между прошлой и будущей ситуацией. При необходимости внеите данные, например, "&"параметры процесса до и после ") | Q74: -การดำเนินการแก้ไขทางเทคนิค / เชิงระบบ อธิบายอย่างชัดเจนซึ่งการดำเนินการแก้ไขจะดำเนินการเพื่อแก้ไขที่ต้นตอสาเหตุ ผู้อ่านควรเข้าใจว่าอะไรคือความแตกต่างระหว่างสถานการณ์ก่อนหน้าและอนาคต ใส่ข้อมูลตามความเหมาะสมพารามิเตอร์กระบวนการก่อนและหลังเป็นต้น") | R74: -TEKNİK / SİSTEMİK ÖNERİ düzeltici faaliyetler kök nedenini düzeltmek için uygulanan hangi açıkça açıklar. Okuyucu önceki ve gelecekteki durum arasındaki farkın ne olduğunu anlamak gerekir. Put veriler, uygun işlem parametresi önce ve örneğin daha sonra.")
A75: [7] | B75: -STANDARD NUMBER REVISION LEVEL Specify which standard has been created or upgraded (Name and N° of Standard and Revision Level)") | C75: -STANDARD NOMBRE NIVEAU DE RÉVISION Spécifiez quel standard a été créé ou mis à niveau (Nom et N ° de la norme et du niveau de révision)") | D75: -NÍVEL DE REVISÃO DE NÚMERO PADRÃO Especifique qual padrão foi criado ou atualizado (Nome e N ° do Padrão e Nível de Revisão)") | E75: -NIVEL MEDIO NÚMERO DE REVISIÓN Especificar qué norma se ha creado o actualizado (Nombre y N ° de estándar y nivel de revisión)") | F75: -标准编号及版本 指明哪个标准被创建或更新了（标准的名称、编号及版本）。") | G75: -ČÍSLO A ÚROVEŇ REVIZE STANDARDU Specifikujte, jaký standard byl vytvořen nebo aktualizován (název standardu, jeho číslo a úroveň revize)") | H75: -STANDARD NUMBER REVISION LEVEL Gibt an, welche Standard erstellt oder aktualisiert wurde (Name und N ° von Standard- und Revisionsstand)") | I75: -Szabvány számát felülvizsgálati szint Határozza meg, mely a szabvány már létrehozott vagy továbbfejlesztett (neve és N ° Standard és felülvizsgálati szint)") | J75: -STANDAR NOMOR REVISI LEVEL Menentukan standar telah dibuat atau ditingkatkan (Nama dan N ° Standar dan Revisi Level)") | K75: -LIVELLO E NUMERO DI REVISIONE DELLO STANDARD Specificare quale standard è stato creato o aggiornato (nome e numero dello standard e livello di revisione)") | L75: -標準管理番号変更レベル どの標準が新規作成されたか、或いは、改定されたか分かる様に（文書名称と管理番号、各アクション責任者は1名）") | M75: -표준서 개정 어떤 표준서가 신규 생성되고, 개정이 되었습니까? (표준서 이름 / 개정번호 명기)") | N75: -Numer wersji STANDARD POZIOM Określ, jaki standard został utworzony lub uaktualniony (nazwa i nr standardowych i Revision Level)") | O75: -NIVEL STANDARD revision Precizați care standard a fost creat sau modernizate (Nume și N ° Standard și Revizie Level)") | P75: -УРОВЕНЬ ПЕРЕСМОТРА НОМЕРА СТАНДАРТА Укажите, какой стандарт был создан или обновлен (название и номер стандарта и уровень редакции) ") | Q75: -มาตรฐานจำนวนการแก้ไขระดับ ระบุมาตรฐานที่ได้รับการสร้างหรืออัพเกรด (ชื่อและที่ N °ของมาตรฐานและการทบทวนระดับ)") | R75: -STANDART NUMARASI REVISION SEVİYE oluşturulmuş veya yükseltildi hangi standart belirleme (Standart ve Revizyon Düzeyi Adı ve N °)")
